Workbook

Sheet Lembar Monitoring
A1: LEMBAR MONITORING DAN EVALUASI MANAJEMEN RISIKO UNIT
A2: SATUAN PENGAWAS INTERNAL
A3: POLITEKNIK NEGERI MALANG
A5: UNIT | B5: : | C5: =VLOOKUP(J7,Kegiatan!$A$3:$K$717,2,TRUE) -> D-III Akuntansi PSDKU Kediri-1 | E5: PEMONEV | F5: : | G5: Usman Nurhasan, S.Kom., M.T. | J5: No Kegiatan
A6: KODE RISIKO | B6: : | E6: Tahun Anggaran KEGIATAN | F6: : | G6: 2025 | J6: 1 | K6: 2 | L6: 3 | M6: 4 | N6: 5 | O6: 6 | P6: 7 | Q6: 8 | R6: 9
A7: KEGIATAN | B7: : | C7: =VLOOKUP(J7,Kegiatan!$A$3:$K$717,3,TRUE) -> Focus Group Discussion Kurikulum Merdeka Belajar Kampus Merdeka (MBKM) - Lanjutan - D-III Akuntansi PSDKU Kediri | J7: 36 | K7: 0 | L7: 0 | M7: 0 | N7: 0 | O7: 0 | P7: 0 | Q7: 0
A8: PERNYATAAN RISIKO | B8: : | C8: =VLOOKUP(J7,Kegiatan!$A$3:$K$717,10,TRUE) -> Karena keterbatasan kemampuan SDM dalam mengembangkan kurikulum berbasis MBKM di Prodi D3 Akuntansi Kampus Kediri mungkin proses pengajaran berbasis kurikulum MBKM tidak maksimal, sehingga pengajaran berbasis kurikulum MBKM tidak berjalan
A9: LEVEL RISIKO | B9: : | C9: =VLOOKUP(J7,Kegiatan!$A$3:$K$717,7,TRUE) -> HIGH | E9: RISIKO RESIDUAL | F9: : | G9: Extreme
J10: 1. Apakah kegiatan tersebut sudah selesai di laksanakan ?
A11: PENGENDALIAN | D11: MITIGASI RISIKO | E11: KOMENTAR | J11: 2. Apakah bapak/ibu akan Menerima, Membagi atau Melimpahkan Risiko tersebut?
A12: =VLOOKUP(J7,Kegiatan!$A$3:$K$717,11,TRUE) -> Untuk mengatasi resiko yang mungkin terjadi, maka cara mengendalikan dampaknya adalah: mengikuti sosialisasi online atau menunggu kampus pusat untuk mengadakan sosialisasi tentang kurikulum merdeka belajar. | D12: Menerima Risiko | E12: 1. Sentralisasi Repositori Bukti: Buat penyimpanan digital terpusat dan berindeks untuk semua bukti pendukung. 2. Finalisasi LKPS & Cross-Check: perept penyelesaian draft Laporan Kinerja Program Studi (LKPS) dan lakukan verifikasi silang (cross-check) bahwa semua klaim di laporan didukung bukti yang tersedia. 3. Koordinasi Khusus Keuangan: Lakukan koordinasi intensif dengan Pihak Keuangan untuk mempercepat pencairan dana kegiatan yang hasilnya akan menjadi bukti kritis akreditasi. | J12: STRATEGI MITIGASI
J13: 3. Apa langkah-langkah mitigasi yang telah diterapkan untuk mengurangi dampak atau
J14: kemungkinan terjadinya risiko ?
J15: 4. Bagaimana efektivitas langkah mitigasi yang telah dilakukan sejauh ini?
D16: =IF(D12="Menerima Risiko","","Unit Penerima Risiko") | J16: 5. Mampukan langkah tersebut mengendalikan risiko shingga Resiko Residualnya bisa turun
J17: atau tetap sama
J18: 6. Apakah ada perubahan atau penambahan strategi mitigasi yang perlu dilakukan?
J19: PELAKSANAAN MITIGASI
D20: Status Konfirmasi | J20: 7. Apa langkah-langkah mitigasi yang telah diterapkan untuk mengurangi dampak atau
D21: - | J21: kemungkinan terjadinya risiko?
D22: - | J22: 8. Apakah ada perubahan atau penambahan strategi mitigasi yang perlu dilakukan?
D23: - | J23: MONITORING dan PENGENDALIAN
J24: 9. Bagaimana cara Anda memonitor perkembangan mitigasi risiko secara berkelanjutan?
J25: 10. Apakah pengendalian yang ada cukup efektif untuk menjaga agar risiko tetap terkendali?
G26: Malang, 22/09/ | H26: =G6 -> 2025 | J26: 11. Apakah semua pihak terkait sudah terlibat dan memahami tindakan mitigasi ini ?
C27: Unit. | G27: Pemonev | J27: EVALUASI KINERJA & KEBERHASILAN MITIGASI
J28: 11. Apa indikator yang digunakan untuk mengukur keberhasilan mitigasi risiko?
J29: 12. Apakah ada faktor yang belum teridentifikasi yang mempengaruhi efektivitas mitigasi?
J30: TINDAK LANJUT & PERBAIKAN
J31: 13. Apakah ada kebutuhan memperbarui / memperbaiki langkah mitigasi
G32: =G5 -> Usman Nurhasan, S.Kom., M.T. | J32: berdasarkan evaluasi yang ada?
G33: =IF(G32="Dr. Drs. Sumiadji, Ak., M.SA.","NIP. 196405121993031001",IF(G32="Usman Nurhasan, S.Kom., M.T.","NIP. 198909162014042001",IF(G32="Ir. Wahiddin, S.T., MT.IPM.ASEAN Eng.","NIP. 197312072003121001",IF(G32="Dr. Ir. Azam Muzakhim Imammuddin, M.T.","NIP. 196705041994031004",IF(G32="Dr. Atik Andhayani, S.E., MSA.","NIP. 197505032009032001",IF(G32="Lina Budiarti, S.E., M.M.","NIP. 198609232015041001",IF(G32="Drs. Mufid M.T.","NIP. 196408221994031001",IF(G32="Lis Diana Mustafa, S.T., M.T.","NIP. 197805052001122003")))))))) -> NIP. 198909162014042001 | J33: 14. Apa tindakan korektif yang perlu dilakukan
J34: untuk meningkatkan mitigasi risiko di masa mendatang?
A36: LEMBAR MONITORING DAN EVALUASI MANAJEMEN RISIKO UNIT
A37: SATUAN PENGAWAS INTERNAL
A38: POLITEKNIK NEGERI MALANG
A40: UNIT | B40: : | C40: =VLOOKUP(K42,Kegiatan!$A$3:$K$717,2,TRUE) -> #N/A | E40: PEMONEV | F40: : | G40: Usman Nurhasan, S.Kom., M.T. | J40: No Kegiatan
A41: KODE RISIKO | B41: : | E41: Tahun Anggaran KEGIATAN | F41: : | G41: 2025 | J41: 1 | K41: 2 | L41: 3 | M41: 4 | N41: 5 | O41: 6 | P41: 7 | Q41: 8 | R41: 9
A42: KEGIATAN | B42: : | C42: =VLOOKUP(K42,Kegiatan!$A$3:$K$717,3,TRUE) -> #N/A | J42: =J7 -> 36 | K42: =K7 -> 0 | L42: =L7 -> 0 | M42: =M7 -> 0 | N42: =N7 -> 0 | O42: =O7 -> 0 | P42: =P7 -> 0 | Q42: =Q7 -> 0 | R42: =R7 -> 0
A43: PERNYATAAN RISIKO | B43: : | C43: =VLOOKUP(K42,Kegiatan!$A$3:$K$717,10,TRUE) -> #N/A
A44: LEVEL RISIKO | B44: : | C44: =VLOOKUP(K42,Kegiatan!$A$3:$K$717,7,TRUE) -> #N/A | E44: RISIKO RESIDUAL | F44: : | G44: Extreme
J45: 1. Apakah kegiatan tersebut sudah selesai di laksanakan ?
A46: PENGENDALIAN | D46: MITIGASI RISIKO | E46: KOMENTAR | J46: 2. Apakah bapak/ibu akan Menerima, Membagi atau Melimpahkan Risiko tersebut?
A47: =VLOOKUP(K42,Kegiatan!$A$3:$K$717,11,TRUE) -> #N/A | D47: Menerima Risiko | E47: 1. Inisiasi komuikasi formal intensif berbentuk menjadi MoA Kemitraan. 2. Akselerasi Dana: komunikasi intens kepada keuangan terkait dana kegiatan. | J47: STRATEGI MITIGASI
J48: 3. Apa langkah-langkah mitigasi yang telah diterapkan untuk mengurangi dampak atau
J49: kemungkinan terjadinya risiko ?
J50: 4. Bagaimana efektivitas langkah mitigasi yang telah dilakukan sejauh ini?
D51: =IF(D47="Menerima Risiko","","Unit Penerima Risiko") | J51: 5. Mampukan langkah tersebut mengendalikan risiko shingga Resiko Residualnya bisa turun
J52: atau tetap sama
J53: 6. Apakah ada perubahan atau penambahan strategi mitigasi yang perlu dilakukan?
J54: PELAKSANAAN MITIGASI
D55: Status Konfirmasi | J55: 7. Apa langkah-langkah mitigasi yang telah diterapkan untuk mengurangi dampak atau
D56: - | J56: kemungkinan terjadinya risiko?
D57: - | J57: 8. Apakah ada perubahan atau penambahan strategi mitigasi yang perlu dilakukan?
D58: - | J58: MONITORING dan PENGENDALIAN
J59: 9. Bagaimana cara Anda memonitor perkembangan mitigasi risiko secara berkelanjutan?
J60: 10. Apakah pengendalian yang ada cukup efektif untuk menjaga agar risiko tetap terkendali?
G61: Malang,….................. | H61: =G41 -> 2025 | J61: 11. Apakah semua pihak terkait sudah terlibat dan memahami tindakan mitigasi ini ?
C62: Unit. | G62: Pemonev | J62: EVALUASI KINERJA & KEBERHASILAN MITIGASI
J63: 11. Apa indikator yang digunakan untuk mengukur keberhasilan mitigasi risiko?
J64: 12. Apakah ada faktor yang belum teridentifikasi yang mempengaruhi efektivitas mitigasi?
J65: TINDAK LANJUT & PERBAIKAN
J66: 13. Apakah ada kebutuhan memperbarui / memperbaiki langkah mitigasi
G67: =G40 -> Usman Nurhasan, S.Kom., M.T. | J67: berdasarkan evaluasi yang ada?
G68: =IF(G67="Dr. Drs. Sumiadji, Ak., M.SA.","NIP. 196405121993031001",IF(G67="Usman Nurhasan, S.Kom., M.T.","NIP. 198909162014042001",IF(G67="Ir. Wahiddin, S.T., MT.IPM.ASEAN Eng.","NIP. 197312072003121001",IF(G67="Dr. Ir. Azam Muzakhim Imammuddin, M.T.","NIP. 196705041994031004",IF(G67="Dr. Atik Andhayani, S.E., MSA.","NIP. 197505032009032001",IF(G67="Lina Budiarti, S.E., M.M.","NIP. 198609232015041001",IF(G67="Drs. Mufid M.T.","NIP. 196408221994031001",IF(G67="Lis Diana Mustafa, S.T., M.T.","NIP. 197805052001122003")))))))) -> NIP. 198909162014042001 | J68: 14. Apa tindakan korektif yang perlu dilakukan
J69: untuk meningkatkan mitigasi risiko di masa mendatang?
A71: LEMBAR MONITORING DAN EVALUASI MANAJEMEN RISIKO UNIT
A72: SATUAN PENGAWAS INTERNAL
A73: POLITEKNIK NEGERI MALANG
A75: UNIT | B75: : | C75: =VLOOKUP(L77,Kegiatan!$A$3:$K$717,2,TRUE) -> #N/A | E75: PEMONEV | F75: : | G75: Usman Nurhasan, S.Kom., M.T. | J75: No Kegiatan
A76: KODE RISIKO | B76: : | E76: Tahun Anggaran KEGIATAN | F76: : | G76: 2025 | J76: 1 | K76: 2 | L76: 3 | M76: 4 | N76: 5 | O76: 6 | P76: 7 | Q76: 8 | R76: 9
A77: KEGIATAN | B77: : | C77: =VLOOKUP(L77,Kegiatan!$A$3:$K$717,3,TRUE) -> #N/A | J77: =J7 -> 36 | K77: =K7 -> 0 | L77: =L7 -> 0 | M77: =M7 -> 0 | N77: =N7 -> 0 | O77: =O7 -> 0 | P77: =P7 -> 0 | Q77: =Q7 -> 0 | R77: =R7 -> 0
A78: PERNYATAAN RISIKO | B78: : | C78: =VLOOKUP(L77,Kegiatan!$A$3:$K$717,10,TRUE) -> #N/A
A79: LEVEL RISIKO | B79: : | C79: =VLOOKUP(L77,Kegiatan!$A$3:$K$717,7,TRUE) -> #N/A | E79: RISIKO RESIDUAL | F79: : | G79: Extreme
A81: PENGENDALIAN | D81: MITIGASI RISIKO | E81: KOMENTAR | J81: 1. Apakah kegiatan tersebut sudah selesai di laksanakan ?
A82: =VLOOKUP(L77,Kegiatan!$A$3:$K$717,11,TRUE) -> #N/A | D82: Menerima Risiko | E82: 1. Wajibkan MoA/Perjanjian Kontrak: Ubah komunikasi intensif menjadi Perjanjian Formal yang mencantumkan luaran Tri Dharma spesifik. 2. Pastikan kegiatan implementasi dibagi dan diukur berdasarkan IKU Pendidikan (Exchange), Penelitian (Joint Research), dan Pengabdian. | J82: 2. Apakah bapak/ibu akan Menerima, Membagi atau Melimpahkan Risiko tersebut?
J83: STRATEGI MITIGASI
J84: 3. Apa langkah-langkah mitigasi yang telah diterapkan untuk mengurangi dampak atau
J85: kemungkinan terjadinya risiko ?
D86: =IF(D82="Menerima Risiko","","Unit Penerima Risiko") | J86: 4. Bagaimana efektivitas langkah mitigasi yang telah dilakukan sejauh ini?
J87: 5. Mampukan langkah tersebut mengendalikan risiko shingga Resiko Residualnya bisa turun
J88: atau tetap sama
J89: 6. Apakah ada perubahan atau penambahan strategi mitigasi yang perlu dilakukan?
D90: Status Konfirmasi | J90: PELAKSANAAN MITIGASI
D91: - | J91: 7. Apa langkah-langkah mitigasi yang telah diterapkan untuk mengurangi dampak atau
D92: - | J92: kemungkinan terjadinya risiko?
D93: - | J93: 8. Apakah ada perubahan atau penambahan strategi mitigasi yang perlu dilakukan?
J94: MONITORING dan PENGENDALIAN
J95: 9. Bagaimana cara Anda memonitor perkembangan mitigasi risiko secara berkelanjutan?
G96: Malang,….................. | H96: =G76 -> 2025 | J96: 10. Apakah pengendalian yang ada cukup efektif untuk menjaga agar risiko tetap terkendali?
C97: Unit. | G97: Pemonev | J97: 11. Apakah semua pihak terkait sudah terlibat dan memahami tindakan mitigasi ini ?
J98: EVALUASI KINERJA & KEBERHASILAN MITIGASI
J99: 11. Apa indikator yang digunakan untuk mengukur keberhasilan mitigasi risiko?
J100: 12. Apakah ada faktor yang belum teridentifikasi yang mempengaruhi efektivitas mitigasi?
J101: TINDAK LANJUT & PERBAIKAN
C102: Ahmad Fauzi, S.Kom., M.MT | G102: =G75 -> Usman Nurhasan, S.Kom., M.T. | J102: 13. Apakah ada kebutuhan memperbarui / memperbaiki langkah mitigasi
C103: NIP.197412082005011001 | G103: =IF(G102="Dr. Drs. Sumiadji, Ak., M.SA.","NIP. 196405121993031001",IF(G102="Usman Nurhasan, S.Kom., M.T.","NIP. 198909162014042001",IF(G102="Ir. Wahiddin, S.T., MT.IPM.ASEAN Eng.","NIP. 197312072003121001",IF(G102="Dr. Ir. Azam Muzakhim Imammuddin, M.T.","NIP. 196705041994031004",IF(G102="Dr. Atik Andhayani, S.E., MSA.","NIP. 197505032009032001",IF(G102="Lina Budiarti, S.E., M.M.","NIP. 198609232015041001",IF(G102="Drs. Mufid M.T.","NIP. 196408221994031001",IF(G102="Lis Diana Mustafa, S.T., M.T.","NIP. 197805052001122003")))))))) -> NIP. 198909162014042001 | J103: berdasarkan evaluasi yang ada?
J104: 14. Apa tindakan korektif yang perlu dilakukan
J105: untuk meningkatkan mitigasi risiko di masa mendatang?
A106: LEMBAR MONITORING DAN EVALUASI MANAJEMEN RISIKO UNIT
...

Sheet Unit & Pemonev
B3: PEMONEV | E3: UNIT
B4: NO | C4: NAMA | E4: NO | F4: NAMA UNIT
B5: Q | E5: 1
B6: 1 | C6: Dr. Drs. Sumiadji, Ak., M.SA. | E6: 2 | F6: - DEWAS
B7: 2 | C7: Usman Nurhasan, S.Kom., M.T. | E7: 3 | F7: - Senat
B8: 3 | C8: Ir. Wahiddin, S.T., MT.IPM.ASEAN Eng. | E8: 4 | F8: - WADIR I
B9: 4 | C9: Dr. Ir. Azam Muzakhim Imammuddin, M.T. | E9: 5 | F9: - WADIR II
B10: 5 | C10: Dr. Atik Andhayani, S.E., MSA. | E10: 6 | F10: - WADIR III
B11: 6 | C11: Lina Budiarti, S.E., M.M. | E11: 7 | F11: - WADIR IV
B12: 7 | C12: Drs. Mufid M.T. | E12: 8 | F12: - BAK
B13: 8 | C13: Lis Diana Mustafa, S.T., M.T. | E13: 9 | F13: - BPKU
E14: 10 | F14: - P2MPP
E15: 11 | F15: - P3M
E16: 12 | F16: - SPI
E17: 13 | F17: - UPA Bahasa
E18: 14 | F18: - UPA LUK
E19: 15 | F19: - UPA PKK
E20: 16 | F20: - UPA PP
E21: 17 | F21: - UPA Perpustakaan
E22: 18 | F22: - UPA TIK
E23: 19 | F23: - Jurusan Adiministrasi Niaga
E24: 20 | F24: - D-IV Pengelolaan Arsip dan Rekaman Informasi
E25: 21 | F25: - D-IV Usaha Perjalanan Wisata
... E72: 68 | F72: - PSDKU Kota Pamekasan

Sheet Kegiatan
B1: REKAP IDENTIFIKASI DAN ANALISIS RISIKO SELURUH UNIT TAHUN 2025
B3: Nama Unit & Kode | C3: Usulan Kegiatan | D3: Nilai Usulan | E3: Skor Probabilitas | F3: Skor Dampak | G3: Tingkat Risiko | H3: SPIP | I3: Uraian Dampak | J3: Pernyataan Risiko | K3: Pengendalian
A4: 1 | B4: D-III Teknik Telekomunikasi-1 | C4: FGD dan Inisiasi kerja sama dalam pelaksanaan PKL dan MBKM - D-III Teknik Telekomunikasi | D4: 15790000 | E4: 5 | F4: 5 | G4: EXTREME | I4: Program studi kesulitan untuk mendapatkan mitra dalam upaya meingkatkan keikutsertaan MBKM bagi mahasiswa | J4: Karena kurangnya kepercayaan industri terhadap kompetensi mahasiswa mungkin tidak banyak industri telekomuniikasi yang dapat secara langsung melibatkan mahasiswa melalui MBKM sehingga kurangnya kerjasama prodi dengan mitra untuk menunjang MBKM | K4: Membuat database PT sehingga dapat memetakan mitra/industri yang telah dan belum menyusun dokumen kerjasama dengan Polinema serta menambahkan klausul penelitian dosen dan mahasiswa dalam dokumen kerjasama yang telah/akan dibuat
A5: 2 | B5: D-III Teknik Telekomunikasi-2 | C5: FGD dan Inisiasi Kerjasama dengan Kampus LN - D-III Teknik Telekomunikasi | D5: 8320000 | E5: 5 | F5: 5 | G5: EXTREME | I5: Program studi kesulitan untuk mendapatkan mitra dalam upaya meingkatkan keikutsertaan MBKM bagi mahasiswa | J5: Karena kurangnya kepercayaan industri terhadap kompetensi mahasiswa mungkin tidak banyak industri telekomuniikasi yang dapat secara langsung melibatkan mahasiswa melalui MBKM sehingga kurangnya kerjasama prodi dengan mitra untuk menunjang MBKM | K5: Membuat database PT sehingga dapat memetakan mitra/industri yang telah dan belum menyusun dokumen kerjasama dengan Polinema serta menambahkan klausul penelitian dosen dan mahasiswa dalam dokumen kerjasama yang telah/akan dibuat
A6: 3 | B6: D-IV Jaringan Telekomunikasi Digital-6 | C6: FGD dan Inisiasi Kerjasama dengan Industri dalam Pelaksanaan MBKM - D-IV Jaringan Telekomunikasi Digital - D-IV Jaringan Telekomunikasi Digital | D6: 28817500 | E6: 5 | F6: 5 | G6: EXTREME | I6: Program studi kesulitan untuk mendapatkan mitra dalam upaya meingkatkan keikutsertaan MBKM bagi mahasiswa | J6: Karena kurangnya kepercayaan industri terhadap kompetensi mahasiswa mungkin tidak banyak industri telekomuniikasi yang dapat secara langsung melibatkan mahasiswa melalui MBKM sehingga kurangnya kerjasama prodi dengan mitra untuk menunjang MBKM | K6: Membuat database PT sehingga dapat memetakan mitra/industri yang telah dan belum menyusun dokumen kerjasama dengan Polinema serta menambahkan klausul penelitian dosen dan mahasiswa dalam dokumen kerjasama yang telah/akan dibuat
A7: 4 | B7: D-IV Manajemen Pemasaran-6 | C7: Peningkatan Kerjasama Luar Negeri Prodi D-IV Manajemen Pemasaran | D7: 21845000 | E7: 5 | F7: 5 | G7: EXTREME | I7: 1. Tidak mempunyai kerjasama dengan mitra luar negeri; 2. Peningkatan daya saing global tidak terwujud. | J7: Karena terbatasnya jejaring luar negeri dalam mendukung pembelajaran dan pengembangan internasional, mungkin kurangnya pendekatan kepada mitra luar negeri, sehingga Peningkatan kerjasama luar negeri Prodi D-IV Manajemen Pemasaran tidak berjalan | K7: 1. Melakukan inisiasi kerjasama dengan PT luar negeri. 2. Melakukan perencanaan kegiatan yang mendukung kegiatan kerjasama luar negeri.
A8: 5 | B8: D-IV Manajemen Pemasaran-9 | C8: Rekonstruksi dan Ujicoba Kurikulum Prodi D-IV Manajemen Pemasaran | D8: 13821000 | E8: 5 | F8: 5 | G8: EXTREME | I8: 1.Tidak terlaksananya kegiatan rekonstruksi dan uji coba kurikulum Prodi D-IV Manajemen Pemasaran dengan baik; 2. Tidak adanya kurikulum yang selaras dengan dunia usaha dunia industri. | J8: Karena tidak memiiliki pedoman rekonstruksi dan ujicoba kurikulum yang update sesuai dunia industri, mungkin Terbatasnya data dan informasi rekonstruksi dan ujicoba kurikulum Prodi D-IV Manajemen Pemasaran, sehingga Rekonstruksi dan ujicoba kurikulum Prodi D-IV Manajemen Pemasaran tidak berjalan | K8: Melaksanakan monitoring tepat waktu. Memberikan sosialisasi lebih awal tentang hasil kurikulum. Menyusun kurikulum tepat waktu. Menyusun pedoman kurikulum program studi. Melakukan ujicoba kurikulum.
A9: 6 | B9: D-IV Manajemen Pemasaran-10 | C9: Pembelajaran PBL Semester Ganjil (Pelatihan Table Manner, Praktek E-Commerce & Marketing Event Project) - D-IV Manajemen Pemasaran | D9: 40887000 | E9: 5 | F9: 5 | G9: EXTREME | I9: 1. Pembelajaran PBL Semester Ganjil tidak berjalan sesuai dengan perencanaan; 2. Capaian pembelajaran yang diharapkan tidak dapat terpenuhi. | J9: Karena kurangnya koordinasi antar dosen dalam pelaksanaan pembelajaran semester ganjil, mungkin pelaksanaan pembelajaran PBL tidak sesuai dengan jadwal yang ditetapkan, sehingga Pembelajaran PBL semester Ganjil (pelatihan Table Manner, Praktek E-Commerce & Marketing Event Project) tidak berjalan | K9: Melakukan koordinasi antar dosen dalam pelaksanaan pembelajaran semester ganjil. Memastikan RPS mata kuliah telah tersusun awal perkuliahan. Menjalankan program pembelajaran sesuai dengan yang direncanakan.
A10: 7 | B10: D-IV Manajemen Pemasaran-11 | C10: Pembelajaran PBL Semester Genap (Digital Marketing Project, Pameran Produk Kewirausahaan, dan Riset Pemasaran) - D-IV Manajemen Pemasaran | D10: 44084580 | E10: 5 | F10: 5 | G10: EXTREME | I10: 1. Pembelajaran PBL Semester Genap tidak berjalan sesuai dengan perencanaan; 2. Capaian pembelajaran yang diharapkan tidak dapat terpenuhi. | J10: Karena kurangnya koordinasi antar dosen dalam pelaksanaan pembelajaran semester genap, mungkin pelaksanaan pembelajaran PBL tidak sesuai dengan jadwal yang ditetapkan, sehingga Pembelajaran PBL semester genap (Digital Marketing Project, Pameran Produk Kewirausahaan, dan Riset Pemasaran) - D-IV Manajemen Pemasaran tidak berjalan | K10: Melakukan koordinasi antar dosen dalam pelaksanaan pembelajaran semester genap. Memastikan RPS mata kuliah telah tersusun awal perkuliahan. Menjalankan program pembelajaran sesuai dengan yang direncanakan.
A11: 8 | B11: D-IV Usaha Perjalanan Wisata-3 | C11: Penguatan Kerjasama Prodi dengan Mitra Industri Pariwisata Bandung - D-IV Usaha Perjalanan Wisata | D11: 12760000 | E11: 5 | F11: 5 | G11: EXTREME | I11: Kurangnya informasi terkait industri sasaran kerjasama dan mundurnya jadwal kegiatan kunjungan industri, proses monitoring kurang maksimal | J11: Karena tidak memiliki data base industri sasaran dan industri tempat magang, mungkin industri sasaran yang sesuai untuk pengembangan kerjasama tidak ada dan industri tempat monitoring pelaksanaan magang tidak siap sehingga kunjungan industri pariwisata untuk pengembangan kerjasama dan monitoring pelaksanaan magang tidak berjalan | K11: Membuat database industri sasaran pengembangan kerjasama dan industri tempat magang
A12: 9 | B12: D-IV Usaha Perjalanan Wisata-4 | C12: Peningkatan Kerjasama Program Studi Melalui Praktikum Mahasiswa Pada Mata Kuliah Akomodasi Perhotelan Dan Dan Restoran Ke Hotel Grand Mercure Malang Mirama - D-IV Usaha Perjalanan Wisata | D12: 4095000 | E12: 5 | F12: 5 | G12: EXTREME | I12: proses kegiatan praktikum tidak maksimal dan peserta tidak mendapatkan ilmu yang bisa digunakan pada dunia kerja | J12: karena tidak ada mahasiswa D4 UPW yang melakukan praktikum mahasiswa pada mata kuliah Akomodasi Perhotelan dan Restoran di industri secara riil mungkin karena tidak adanya praktisi dan pendamping minat kegiatan mahasiswa sehingga praktikum tersebut tidak berjalan | K12: melakukan persiapan secara matang untuk mencari narasumber yang sesuai dengan tema dan memiliki pengalaman menjadi pendamping pada program praktikum atau sejenis
A13: 10 | B13: D-IV Usaha Perjalanan Wisata-6 | C13: Workshop Ticketing and Reservation System - D-IV Usaha Perjalanan Wisata | D13: 4595000 | E13: 5 | F13: 5 | G13: EXTREME | J13: Karena terbatasnya industri atau institusi yang membuka program pelatihan ticketing dan reservation yang selaras dengan kebutuhan prodi D4 UPW dan mahasiswa tidak menyesuaikan kurikulum , mungkin karena terhambatnya proses penyusunan pedoman kurikulum khususnya ticketing dan reservation sehingga Workshop Ticketing and Reservation System - D-IV Usaha Perjalanan Wisata tidak berjalan dengan sesuai seperti yang diharapkan | K13: Sosialisasi kurikulum MK Ticketing dan Reservation dengan metode PBL sebelum kegiatan kepada seluruh dosen homebase D4 UPW
A14: 11 | B14: D-IV Usaha Perjalanan Wisata-7 | C14: Forum Group Discussion Tentang Penyusunan Kurikulum Berbasis OBE dengan Industri - D-IV Usaha Perjalanan Wisata | D14: 6455000 | E14: 5 | F14: 5 | G14: EXTREME | I14: Lamanya waktu yang diperlukan untuk telaah dan persiapan draft bahan ajar berbasis OBE | J14: Karena terbatasnya industri yang membuka program MBKM yang selaras dengan Prodi D4 UPW dan mahasiswa tidak menyesuaikan kurikulum dalam mengajukan MBKM mungkin karena terhambatnya proses penyusunan pedoman kurikulum berbasis OBE dengan industri di kantor pusat sehingga FGD tentang Penyusunan Kurikulum Berbasis OBE dengan Industri D-IV Usaha Perjalanan Wisata tidak berjalan sesuai yg seperti diharapkan | K14: Sosialisasi pedoman pembelajaran berbasis OBE sebelum kegiatan kepada seluruh dosen homebase D$ UPW
A15: 12 | B15: Jurusan Teknik Elektro-3 | C15: Inisiasi Kerjasama Dengan Mitra Potensial Dalam Bentuk Focus Group Discussion di Jurusan Teknik Elektro | D15: 17500000 | E15: 5 | F15: 5 | G15: EXTREME | I15: Jurusan Teknik Elektro tidak memiliki mitra untuk dapat meningkatkan kerjasama industri | J15: Karena kurangnya kepercayaan industri terhadap kompetensi Jurusan Teknik Elektro mungkin tidak banyak industri telekomuniikasi yang dapat secara langsung menjalin kerjasama melalui sehingga kurangnya kerjasama prodi dengan mitra untuk menunjang MBKM | K15: Membuat database PT sehingga dapat memetakan mana yang belum MoU dan yang sudah selain itu membuat perjanjian ditambahkan dengan penelitian dosen dan mahasiswa
A16: 13 | B16: P3M-15 | C16: PENELITIAN DIPA KOMPETISI 2025 - P3M | D16: 5440155000 | E16: 5 | F16: 5 | G16: EXTREME | I16: Menggangu ketercapaian kinerja dosen dan IKU Polinema | J16: KARENA terlambat dalam menentukan skema penelitian MUNGKIN sosialisasi perubahan aturan terlambat disampaikan kepada peneliti SEHINGGA Penelitian DIPA KOMPTESI 2025 P3M tidak dapat dilaksanakan | K16: Perlu dilakukan penyusunan panduan dan skema penelitian sebagai petunjuk teknis pelaksanaan. Perlu dilakukan sosialisasi panduan dan penentuan penjadwalan seleksi hingga pelaporan pelaksanaan kepada seluruh civitas akademika Polinema. Perlu dilakukannya monitoring dan koordinasi pelaksanaan kegiatan sehingga luaran penelitian dapat tercapai
A17: 14 | B17: UPA Pengembangan Karir dan Kewirausahaan-4 | C17: INKUBASI WIRAUSAHA MAHASISWA 2025 - UPA Pengembangan Karir dan Kewirausahaan | D17: 77080000 | E17: 5 | F17: 5 | G17: EXTREME | I17: terjadi kemunduran pelaksanaan kegiatan penampingan usaha dari tenant inkubasi. | J17: karena adanya keterlambatan pencairan bantuan modal usaha dan tidak tepat waktu, sehingga menyebabkan kendala di keseluruhan proses pendampingan terutama mundurnya jadwal pelaksanaan kegiatan. | K17: membuat jadwal pelaksanaanan kegiatan, dan kepatuhan terhadap jadwal yang di buat. pencairan modal usaha tepat waktu sehingga membantu proses kelancaran pendampingan dan kegiatan produksi mahasiswa wirausaha.
A18: 15 | B18: UPA Pengembangan Karir dan Kewirausahaan-10 | C18: Program Mahasiswa Wirausaha (PMW) Polinema 2025 - UPA Pengembangan Karir dan Kewirausahaan | D18: 302568000 | E18: 5 | F18: 5 | G18: EXTREME | I18: Karena KETERLAMBATAN DAN SULITNYA PROSES PENCAIRAN BANTUAN MODAL USAHA , sehingga menyebabkan resiko sangat terlambat dalam proses pendampingan dan produksi, yang mengakibatkan mundurnya jadwal kegiatan lainnya sebagai rangkaian kegiatan PMW. ada beberapa kegiatan lain yang pelaksanaan nya hanya bisa dilakukan setelah tenant PMW berjalan proses produksinya, sehingga jika pencairan modal usaha ini terlambata akan menghambat pelaksanaan kegiatan lainnya. perlu di pahami bahwa wirausaha adalah menjalankan usaha yang membutuhkan modal untuk proses produksinya. periode waktu usaha yang seharusnya 1 tahun juga sangat terbatas, karena efektif operasional usahanya hanya 6 bulan (jika pencairan bantuan modal di bulan mei 2025). hal ini sebenar nya kurang efektif untuk progres sebuah usaha. oleh karena itu kami berharap bantuan untuk ketepatan jawal pelaksanaan program. | J18: Karena KETERLAMBATAN DAN SULITNYA PROSES PENCAIRAN BANTUAN MODAL USAHA , sehingga menyebabkan resiko sangat terlambat dalam proses pendampingan dan produksi, yang mengakibatkan mundurnya jadwal kegiatan lainnya sebagai rangkaian kegiatan PMW. | K18: 1. penjadwalan dan pelaksanaan kegiatan sesuai dengan time line yang sudah di tetapkan. 2. koordinasi dengan bagian keuangan dan tim kerja terkait ketepatan waktu pencairan bantuan modal usaha mahasiswa. 3. komunikasi yang baik agar pelaksanaan kegiatan bisa dilakukan dengan baik, efektif, tepat waktu , dan memberikan manfaat bagi mahasiswa wirausaha.
A19: 16 | B19: WADIR II-10 | C19: PEMBANGUNAN GEDUNG DAN BANGUNAN PENDUKUNG PEMBELAJARAN - BLU | D19: 40556300000 | E19: 5 | F19: 5 | G19: EXTREME | I19: Melakukan persiapan data dukung tender secara lengkap dan lebih awal, dan pendampingan proses oleh BPKP Jawa Timur dan Kejaksaan Tinggi Negeri | J19: Karena Data dukung penting untuk pengadaan tidak segera tersedia mungkin Kelengkapan berkas pengadaan terlambat sehingga Pembangunan Gedung dan Bangunan Pendukung Pembelajaran tidak selesai. | K19: Adanya pendampingan dari pihak BPKP Jawa Timur dan Kejaksaan Tinggi Negeri agar pembangunan gedung dan bangunan pendukung pembelajaran dapat selesai tepat waktu.
A20: 17 | B20: WADIR II-25 | C20: PEMBANGUNAN GEDUNG DAN BANGUNAN PENDUKUNG PEMBELAJARAN SBSN - RM - WADIR II | D20: 87468000000 | E20: 5 | F20: 5 | G20: EXTREME | I20: Melakukan persiapan data dukung tender secara lengkap dan lebih awal, dan pendampingan proses oleh BPKP Jawa Timur dan Kejaksaan Tinggi Negeri | J20: Karena Data dukung penting untuk pengadaan tidak segera tersedia mungkin Kelengkapan berkas pengadaan terlambat sehingga Pembangunan Gedung dan Bangunan Pendukung Pembelajaran tidak selesai. | K20: Adanya pendampingan dari pihak BPKP Jawa Timur dan Kejakaan Tinggi Negeri agar pembangunan gedung dan bangunan pendukung pembelajar dapat selesai tepat waktu.
A21: 18 | B21: BPKU-3 | C21: Pembinaan Dan Peningkatan Kualitas Pegawai Dalam Bidang Wawasan Kebangsaan | D21: 204269000 | E21: 4 | F21: 4 | G21: HIGH | I21: Tidak terlaksananya upacara dalam rangka peringatan Dies Natalis dan hari besar nasional | J21: Karena kurangnya koordinasi internai Pokja Protokoler dengan jajaran Pimpinan, mungkin tidak terdapat informasi terkait Pembinaan dan Peningkatan Kualitas Pegawai dalam Bidang Wawasan Kebangsaan sehingga Pembinaan dan Peningkatan Kualitas Pegawai dalam Bidang Wawasan Kebangsaan tidak berjalan | K21: Melaksanakan koordinasi dengan jajaran Pimpinan terkait upacara peringatan Dies Natalis dan hari besar nasional serta mencari informasi terkait pedoman pelaksanaan upacara dengan protokol kementerian.
A22: 19 | B22: BPKU-6 | C22: Pameran untuk keikutsertaan Promosi | D22: 122758000 | E22: 4 | F22: 4 | G22: HIGH | I22: Tidak dapat mengikuti pameran pendidikan yang mengakibatkan Menurunnya kuantitas pendaftarSPMB | J22: Karena masih dalam penyusunan anggaran indikatif mungkin kegiatan pameran dilaksanakan di awal tahun ketika belum ada anggaran dan Anggaran belum ditetapkan sehingga Pameran Pendidikan di Wilayah Jawa Timur mengalami kesulitan | K22: Melakukan koordinasi dengan pimpinan terkait mekanisme penggunaan anggaran di awal tahun sebelum anggaran tahun berjalan ditetapkan Melakukan sosialisasi PMB melalui media sosial resmi POLINEMA, website, dan jaringan alumni sekolah
A23: 20 | B23: D-III Teknik Listrik-2 | C23: Kolaborasi Riset Mahasiswa dan Dosen serta pembinaan mahasiswa berprestasi - D-III Teknik Listrik | D23: 47600000 | E23: 4 | F23: 5 | G23: HIGH | I23: menurunya persentase mahasiswa yang merahih prestasi | J23: Karena Tidak ada SDM untuk koordinasi info berkala terkait lomba kepada mahasiswa mungkin minat mahasiswa untuk ikut serta lomba di tingkat nasional menjadi berkurang sehingga Tidak terdapatnya Peningkatan kualitas mahasiswa melalui keikutsertaan dalam lomba | K23: Memberikan informasi-informasi dan pemndampingan ke mahasiswa berkaitan dengan lomba-lomba
A24: 21 | B24: D-III Teknik Listrik-9 | C24: Pesiapan Proses Audit Mutu Internal (AMI) - D-III Teknik Listrik | D24: 17240000 | E24: 4 | F24: 5 | G24: HIGH | I24: menurunnya jumlah: (1) Jumlah mahasiswa yang terlibat dalam kegiatan penelitian; (2) Jumlah mahasiswa yang terlibat dalam kegiatan PkM; (3) Jumlah prodi terakreditasi Unggul / A. | J24: Karena Tidak adanya database untuk mendukung penyusunan Dokumen yang dibutuhkan untuk Audit Mutu Internal (AMI) mungkin tidak ada SDM untuk menyusun dokumen sehingga tidak tersedianya dokumen kelengkapan audit | K24: Dengan meunjuk tim khusus untuk melakukan pengumpulan data dukung secara terorganisir dan termonitor sehingga memudahkan penyusunan dokumen AMI serta memberikan workshop dan pendampingan dalam AMI
A25: 22 | B25: D-III Teknik Elektronika-1 | C25: Pelaksanaan Monitoring Evaluasi Pembelajaran Semester Ganjil - D-III Teknik Elektronika | D25: 11312000 | E25: 4 | F25: 5 | G25: HIGH | I25: Tidak adanya evaluasi proses belajar mengajar sehingga kekurangan dapat terulang di seriap tahun; Proses layanan pembelajaran kurang maksimal | J25: Karena tidak adanya koordinasi untuk menyusun panduan monitoring pelaksanaan belajar mengajar mungkin tidak ada panduan dalam melakukan monitoring proses belajar mengajar sehingga tidak terdapatnya monitoring pelaksanaan belajar mengajar, dari UTS, UAS dan yudisium. | K25: Membuat tim untuk membentuk SOP, membuat SOP untuk monitoring pembelajaran dengan pengawasan dari kps
... A184: 181 | B184: BAK-6 | C184: Workshop Tata Kelola Operasional dan Maintenance Aplikasi Help Akademik - BAK | D184: 12111000 | E184: 3 | F184: 5 | G184: MIDDLE | I184: Terbengkalainya layanan kepada mahasiswa melalui aplikasi help akademik; Memperlambat layanan kepada mahasiswa dengan offline | J184: Karena pelayanan akademik dilakukan offline mengingat aplikasi yang dioperasikan mungkin belum mendapat kepastian untuk dapat dilaksanakan sesuai kebijakan SI terbaru sehingga operasional dan maintenance aplikasi help akademik belum dapat dilanjutkan | K184: Kebijakan sistem informasi institusi diharapkan dapat mengakomodir sistem lain yang sudah berjalan dengan baik untuk efektivitas pelayanan kepada mahasiswa
A185: 182 | B185: BPKU-4 | C185: Digitalisasi Arsip Surat Keputusan dan Peraturan DIrektur | D185: 40000000 | E185: 3 | F185: 4 | G185: MIDDLE
A186: 183 | B186: BPKU-7 | C186: Pelatihan Keselamatan, Kesehatan Kerja & Lingkungan (K3L) Politeknik Negeri Malang | D186: 35000000 | E186: 3 | F186: 4 | G186: MIDDLE | I186: Risiko kecelakaan kerja dapat terjadi apabila para pegawai yang bertanggungjawab di bidang K3L tidak memahami prinsip-prinsip dan tata cara pelaksanaan Keselamatan, Kesehatan Kerja dan Lingkungan. | J186: Risiko kecelakaan kerja dapat terjadi apabila para pegawai yang bertanggungjawab di bidang K3L tidak memahami prinsip-prinsip dan tata cara pelaksanaan Keselamatan, Kesehatan Kerja dan Lingkungan. | K186: Melaksanakan pelatihan K3L dan melengkapi sarana prasarana penunjang K3L
A187: 184 | B187: BPKU-16 | C187: PERENCANAAN DAN MONEV: Rapat Kerja Program dan Anggaran Definitif 2025 - BPKU | D187: 141185000 | E187: 3 | F187: 5 | G187: MIDDLE | I187: Rapat Kerja Penyusunan Program dan Anggaran Indikatif tahun 2025 POLINEMA yang tidak berjalan dengan baik dapat berpengaruh terhadap ketepatan waktu penetapan pagu definitif institusi | J187: Rapat Kerja Penyusunan Program dan Anggaran Indikatif tahun 2025 Polinema merupakan kegiatan rutin untuk memastikan kualitas perencanaan dan penganggaran di Polinema tersusun dengan baik. Tidak terlaksananya Rapat Kerja Penyusunan Program dan Anggaran Indikatif tahun 2025 Polinema dapat mempengaruhi kualitas perencanaan program dan anggaran tahun 2025 serta menghambat ketercapaian indikator Kinerja Utama dan target kinerja institusi. | K187: 1) Meningkatkan kapasitas SDM; 2.) Menyusun perencanaan yang sesuai dengan prosedur dan kaidah keuangan negara; 3.) Penetapan pagu definitif tepat waktu sebagai acuan pelaksanaan program dan kegiatan
A188: 185 | B188: BPKU-20 | C188: Evaluasi Capaian Kinerja Program dan Anggaran Tahun Anggaran 2025 | D188: 86338000 | E188: 3 | F188: 5 | G188: MIDDLE | I188: Pelaksanaan kegiatan EPA tdk berjalan secara optimal | J188: Karena pelaksanaan kegiatan ini membutuhkan narasumber yang dari Kementerian mungkin akan terkendala pada jadwal narasumber yang kompeten dibiudang monev anggaran sehingga kegiatan EPA tdk berjalan dengan baik | K188: pelaksanaan kegiatan ini membutuhkan narasumber yang dari Kementerian Keuangan perlu adanya koordinasi yang baik agar pelaksanaan EPA dapat berjalan dengan baik
A189: 186 | B189: BPKU-24 | C189: Penyusunan Dokumen Pola Karir Pegawai Politeknik Negeri Malang untuk ASN Dosen dan Tenaga Kependidikan | D189: 11780000 | E189: 3 | F189: 4 | G189: MIDDLE | I189: Jika Kegiatan Pola karir tidak terlaksana maka Dokumen Pola Karir tidak dapet terselesaikan, dan jika tidak ada dokumen Pola Karir maka penataan dan jenjang karir pegawai tidak memiliki pedoman | J189: Apabila dokumen pola karier tidak tersusun pada tahun 2025 maka urutan penempatan dan/atau perpindahan PNS dalam dan antar posisi di setiap jenis Jabatan di lingkungan Polinema akan terkendala dan tidak memiliki dasar acuan yang tepat. | K189: Melaksanakan koordinasi dan timeline penyusunan dokumen pola karier agar dokumen pol karier dapat terselesaikan tepat waktu pada tahun 2025
A190: 187 | B190: BPKU-25 | C190: Penyusunan Dokumen Peta Jalan Pengembangan Kompetensi Pegawai Tenaga Kependidikan yang disesuaikan dengan Renstra Polinema | D190: 12500000 | E190: 3 | F190: 4 | G190: MIDDLE | I190: Kegiatan penyusunan Dokumen Peta Jalan tidak terlaksana, sehingga dapat menyebabkan penataan pegawai dan jenjang karir pegawai tidak memiliki pedoman | J190: Apabila kegiatan penyusunan Peta Jalan Pengembangan Kompetensi Pegawai Tenaga Kependidikan tidak terlksana, maka Polinema tidak memiliki dokumen Peta Jalan Pengembangan Kompetensi Pegawai Tenaga Kependidikan sebagai pedoman penataan jenjang karir pegawai. | K190: Melaksanakan koordinasi dan penyusunan timeline agar target penyusunan dokumen Peta Jalan Pengembangan Kompetensi Pegawai Tenaga Kependidikan dapat tercapai sesuai rencana
A191: 188 | B191: BPKU-28 | C191: Workshop Peningkatan Pengelolaan Kearsipan | D191: 9300000 | E191: 4 | F191: 3 | G191: MIDDLE | I191: Dengan pelaksanaan workshop pengelolaan kearsipan di harapkan layanan surat menyurat di masing-masing jurusan, unit dan bagian dapat lebih berjalan dengan baik | J191: Karena kurangnya data nara sumber yang memiliki kompetensi sesuai dengan yang dibutuhkan mungkin Workshop pengelolaan kearsipan belum dapat dapat dilaksanakan dengan baik sehingga pengelolaan kearsipan belum dapat di laksanakan secara opti mal | K191: Diperlukan layanan yang baik dalam surat menyurat dan pengarsipan
A192: 189 | B192: BPKU-29 | C192: Workshop Sinkronisasi Data di SIMPEG, SINTA, SINERJA dan SIDAKIN Politeknik Negeri Malang | D192: 8980000 | E192: 4 | F192: 3 | G192: MIDDLE | I192: Dapat mengakibatkan tidak tercapainya kinerja Direktur yang telah di targetkan dalam masing-masing IKU sehingga tidak diterimanya reward anggaran kinerja | J192: Ketidaksesuaian data pada aplikasi SIMPEG, SINTA dan SISTER akan terintegrasi pada penilaian kinerja di aplikasi SIDAKIN yang dilaksanakan pada akhir tahun. Data pada aplikasi SIDAKIN yang tidak valid mengakibatkan tidak tercapainya kinerja Direktur yang telah di targetkan dalam masing-masing IKU | K192: pengisian dan update data secara rutin pada apliaksi SIMPEG dan SISTER sehingga data valid
A193: 190 | B193: BPKU-30 | C193: Pelatihan Peningkatan Layanan Prima Bagi Tenaga Kependidikan dalam upaya meningkatkan motivasi dan kualitas layanan di Jajaran BPKU Polinema - BPKU | D193: 91456000 | E193: 3 | F193: 5 | G193: MIDDLE | I193: Tidak terlaksananya kegiatan pemberian motivasi untuk peningkatan kualitas layanan berdapak pada kurangnya motivali layanan prima yang berdampak pada kurang berkualitasnya layanan serta layanan tidak dapat dipercaya. | J193: Karena kurangnya data nara sumber yang memiliki kompetensi sesuai dengan yang dibutuhkan mungkin pelatihan peningkatan layanan prima bagi tenaga kependidikan tidak dapat dilaksanakan dengan baik sehingga layanan tidak dapat dipercaya dan kurang berkualitas. | K193: Diperlukan adanya motivasi dan kualitas layanan terbaik dalam menjalankan tugas di jajaran BPKU
A194: 191 | B194: D-II Perangkat Piranti Lunak Situs-2 | C194: Sinkronisasi Dokumen Kurikulum dengan Capaian - D-II Perangkat Piranti Lunak Situs - D-II Perangkat Piranti Lunak Situs | D194: 8839000 | E194: 4 | F194: 3 | G194: MIDDLE | I194: 1. Data yang diperoleh kurang sesuai 2. Terhambatnya kegiatan penyusunan LKPS dan persiapan Akreditasi | J194: Karena adanya kekurangan data/sumber data yang dikumpulkan, mungkin data yang disampaikan kurang akurat/up to date, sehingga penyusunan LKPS dan persiapan Akreditasi D2 PLS menjadi terhambat. | K194: 1. Memastikan bahwa petugas/tim yang menangani penyusunan LKPS dan persiapan Akreditasi D4 dapat mengumpulkan data sejak awal secara bertahap dan sistematis 2. Memastikan data yang dikumpulkan sudah data terbaru/up to date
A195: 192 | B195: D-III Teknik Listrik-8 | C195: Penyempurnaan Dokumen Kurikulum | D195: 15550000 | E195: 4 | F195: 3 | G195: MIDDLE | I195: tidak adanya Prodi yang telah memiliki kurikulum berbasis DUDI yang telah disusun dan diimplementasikan di kampus | J195: Karena tidak ada acuan (SOP) untuk menyusun Kurikulum, Silabus Berbasis DUDI mungkin tidak ada SDM untuk menyusun Kurikulum, Silabus Berbasis DUDI sehingga Tidak tersedianya Kurikulum, Silabus dan penyusunan kurikulum berbasis DUDI | K195: melakukan workshop serta pendampingan pembuatan kurikulum yang sesuai dengan DUDI
A196: 193 | B196: D-III Teknik Mesin-3 | C196: Monitoring dan Supervisi Pelaksanaan Magang Industri Mahasiswa Program Studi D3 Teknik Mesin | D196: 29851000 | E196: 3 | F196: 5 | G196: MIDDLE | I196: Masukan terhadap perbaikan kurikulum serta rencana pelaksanaan magang/PKL mahasiswa dengan berlakunya kurikulum 4+1+1 (1 smstr PKL di industri) tidak maksimal tersampaikan. | J196: Karena kurangnya komunikasi dan perencanaan jadwal kunjungan yang sesuai mungkin tidak banyak perusahaan yang menerima mahasiswa PKL dapat dikunjungi untuk kegiatan monev sehingga masukan terkait pelaksanaan PKL dan masukan terhadap perbaikan kurikulum belum dapat memperoleh feedback. | K196: Perlu ditingkatkan komunikasi dan perencanaan yang matang terkait rencana monev, supervisi dan kunjungan ke industri tempat mahasiswa PKL sehingga target kegiatan dapat tercapai
A197: 194 | B197: D-III Teknik Telekomunikasi-7 | C197: Pengadaan Alat Pendidikan Penunjang Pembelajaran - D-III Teknik Telekomunikasi | D197: 99073750 | E197: 3 | F197: 5 | G197: MIDDLE | I197: Menurunnya jumlah alat/fasilitas/sarpra yang telah dipelihara dan berfungsi dengan baik | J197: Karena tidak adanya SDM yang dapat mencari alat praktikum dengan kandungan TKDN serta menyusun HPS ditingkat prodi mungkin lamanya waktu yang diperlukan untuk mencari alat praktikum dengan TKDN serta penyusunan HPS sehingga tidak tersedia alat praktikum yang memadai | K197: Menyertakan tim teknis perumus HPS dalam penyusunan HPS untuk memenuhi TKDN mengikuti database yang ada dan minimum 40% dan monitoring proses pengadaan
... A541: 538 | B541: S-2 Sistem Informasi Akuntansi-4 | C541: PENINGKATAN KERJASAMA PROGRAM STUDI MELALUI FGD DENGAN INDUSTRI PRODI S-2 SISTEM INFORMASI AKUNTANSI | D541: 7755000 | E541: 3 | F541: 3 | G541: LOW | I541: tidak memiliki database industri yang akan dikunjungi Kegiatan tidak berjalan sesuai waktu yang telah direncanakan di awal (di simkeu) | J541: Karena objek kunjungan merupakan mitra industri, waktu perlu menyesuaikan dengan kesibukan mitra industri, dan tidak memiliki database industri yang akan dikunjungi mungkin Industri Sasaran yang sesuai untuk Pengembangan Kerjasama belum siap untuk dikunjungi sehingga kegiatan tidak berjalan sesuai skedul yang direncanakan (di simkeu) | K541: menentukan tujuan industri dan menghubungi pihak industri terkait dengan pelaksanaan kegiatan kunjungan industri
A542: 539 | B542: S-2 Teknik Elektro-2 | C542: Implementasi Kerjasama Tri Dharma dengan UTeM - S-2 Teknik Elektro - S-2 Teknik Elektro | D542: 15500000 | E542: 3 | F542: 3 | G542: LOW | I542: menurunnya : (1) Persentase mata kuliah yang menggunakan metode Team-Based Project; (2) Persentase mata kuliah yang menggunakan metode Case Method | J542: karena tidak ada acuan RPS dengan metode pembelajaran CM dan PBL, mungkin tidak ada SDM untuk menyusun RPS, sehingga mengakibatkan tidak tersedianya RPS dengan metode pembelajaran CM dan PBL
A543: 540 | B543: S-2 Teknik Elektro-3 | C543: Workshop Rekonstruksi Kurikulum dan Pembuatan SOP - S-2 Teknik Elektro | D543: 22000000 | E543: 2 | F543: 3 | G543: LOW | I543: tidak adanya Prodi yang telah memiliki kurikulum berbasis DUDI yang telah disusun dan diimplementasikan di kampus | J543: Karena tidak ada acuan (SOP) untuk menyusun Kurikulum, Silabus Berbasis DUDI mungkin tidak ada SDM untuk menyusun Kurikulum, Silabus Berbasis DUDI sehingga Tidak tersedianya Kurikulum, Silabus dan penyusunan kurikulum berbasis DUDI | K543: melakukan workshop serta pendampingan pembuatan kurikulum yang sesuai dengan DUDI
A544: 541 | B544: SENAT-1 | C544: Workshop Tata Kelola Data dan Sistem informasi | D544: 20000000 | E544: 3 | F544: 3 | G544: LOW | I544: pengukuran dampak dari kebijakan baru, terutama jika tidak ada mekanisme evaluasi yang jelas dan berkelanjutan. | J544: Salah satu risiko utama adalah kemungkinan kurangnya adopsi atau implementasi dari kebijakan yang diusulkan karena adanya perbedaan prioritas atau kurangnya dukungan dari pemangku kepentingan lain di institusi. Selain itu, risiko lain meliputi potensi ketidaklengkapan pemahaman peserta terhadap materi yang kompleks, yang dapat menghambat efektivitas kebijakan yang diterapkan. Ada juga risiko terkait dengan pengukuran dampak dari kebijakan baru, terutama jika tidak ada mekanisme evaluasi yang jelas dan berkelanjutan. Sebagai tambahan, risiko operasional seperti logistik atau teknologi selama pelaksanaan workshop juga bisa mempengaruhi pencapaian tujuan kegiatan | K544: Pertama, penting untuk melakukan asesmen risiko awal guna mengidentifikasi potensi kendala, baik dari sisi kesiapan peserta maupun tantangan teknis, dan menyiapkan rencana mitigasi yang sesuai. Memastikan adanya komunikasi yang efektif sebelum dan selama workshop sangat penting untuk menyelaraskan tujuan dan mendapatkan dukungan dari para peserta serta pemangku kepentingan lainnya. Fasilitator workshop harus mampu menyederhanakan materi yang kompleks dan menyediakan sumber daya tambahan untuk mengatasi kesenjangan pemahaman. Pembentukan kelompok kerja atau tim tindak lanjut dapat membantu memperkuat adopsi kebijakan dengan mekanisme evaluasi dan penyesuaian berkelanjutan. Selain itu, memastikan aspek logistik dan teknis berjalan lancar melalui uji coba sebelumnya dapat mengurangi risiko operasional yang dapat mengganggu jalannya kegiatan.
A545: 542 | B545: SENAT-4 | C545: Operasional Kesekretariatan Senat (Tahun 2025) - SENAT - SENAT - SENAT | D545: 8996680 | E545: 2 | F545: 3 | G545: LOW | I545: Tidak tersedianya barang habis pakai di senat akademik dapat menganggu kegiatan yang seharusnya terlaksana | J545: KARENA tidak adanya sdm penyusun hps di Senat Akademik MUNGKIN proses pengadaan bahan habis pakai menjadi terlambat SEHINGGA tidak tersedia bahan habis pakai di Senat Akademik | K545: Mengajukan kegiatan dalam penyusunan hps untuk kebutuhan seperti pelatihan SDM terkait hal tersebut
A546: 543 | B546: SENAT-5 | C546: Benchmarking Polinema Menuju PTNBH ke ITB - SENAT | D546: 35000000 | E546: 3 | F546: 3 | G546: LOW | I546: Benchmarking menuju PTNBH akan memberikan dampak yang signifikan terhadap pengelolaan operasional perguruan tinggi, baik dalam hal peningkatan kinerja administratif, pengelolaan keuangan, pengembangan SDM, maupun pada bidang pendidikan dan riset. | J546: Karena dapat membantu dalam mengidentifikasi dan mengelola potensi masalah yang mungkin terjadi selama pelaksanaan kegiatan benchmarking untuk mencapai tujuan menuju kampus PTNBH dapat berjalan lancar dan memberikan hasil yang optimal. | K546: Dengan pengendalian operasional yang baik, kegiatan benchmarking dapat berjalan sesuai rencana dan menghasilkan keputusan strategis yang mendukung transformasi perguruan tinggi menuju status PTNBH.
A547: 544 | B547: SENAT-6 | C547: Benchmarking Pertimbangan Senat tentang Manajemen Resiko Kegiatan, Institusi, dan Fraud - SENAT | D547: 35000000 | E547: 3 | F547: 3 | G547: LOW | I547: Secara keseluruhan kegiatan benchmarking ini akan membantu memperkuat sistem pengelolaan risiko di institusi dan mendorong perubahan yang lebih baik dalam manajemen risiko terkait kegiatan, institusi, dan fraud, yang pada gilirannya akan berdampak pada peningkatan kinerja dan reputasi organisasi tersebut. | J547: Karen dengan mengidentifikasi dan mengelola risiko operasional ini, kegiatan benchmarking dapat dilaksanakan dengan lebih efektif dan mungkin bisa memberikan masukan yang bermanfaat bagi Senat dalam pengambilan keputusan terkait manajemen risiko kegiatan, institusi, dan fraud. | K547: Pengendalian operasional ini bertujuan untuk memastikan bahwa organisasi tidak hanya memiliki kebijakan yang efektif untuk mengelola risiko, tetapi juga dapat memitigasi potensi fraud dan menjaga kredibilitas serta integritas institusi
A548: 545 | B548: SENAT-7 | C548: Benchmarking Instrumentasi Pengawasan Senat dalam Pelaksanaan Penjaminan Mutu Sesuai Permenristekdikti Nomor 53 Tahun 2023 - SENAT | D548: 35000000 | E548: 3 | F548: 3 | G548: LOW | I548: Benchmarking memberikan data dan informasi yang lebih objektif untuk pengambilan keputusan. | J548: Karena membantu menilai kinerja mereka dengan membandingkan hasil proses, produk, atau layanan mereka dengan yang terbaik di perguruan tinggi lain. Mungkin bis Menganalisis dan membandingkan proses antara organisasi untuk menemukan cara-cara yang lebih baik dalam mengelola atau meningkatkan suatu proses. | K548: Membantu memastikan bahwa benchmarking memberikan nilai yang maksimal bagi organisasi dan bahwa perubahan yang diusulkan benar-benar memberikan perbaikan yang diinginkan.
A549: 546 | B549: SENAT-8 | C549: Benchmarking Instrumen Pengawasan Senat ke PNJ - SENAT - SENAT | D549: 35000000 | E549: 2 | F549: 4 | G549: LOW | I549: Kegiatan benchmarking tidak dilaksanakan | J549: KARENA belum ada kesepakatan tentang jadwal benchmarking, MUNGKIN perguruan tinggi yang dituju akan melakukan pembatalan secara sepihak SEHINGGA benchmarking tidak terlaksana | K549: Menyiapkan beberapa alternatif obyek benchmarking
A550: 547 | B550: SENAT-9 | C550: Benchmark Kebijakan Pengelolaan Lisensi KI Polinema untuk Hilirisasi/Komersialisasi - SENAT | D550: 35000000 | E550: 3 | F550: 3 | G550: LOW | I550: Sangat bergantung pada bagaimana kegiatan ini dijalankan. Jika dilakukan dengan tepat dan bijak, benchmarking bisa menjadi alat yang sangat efektif untuk meningkatkan kinerja. | J550: Karena benchmarking tidak dianalisis dengan tepat atau disalahpahami, ini dapat mengarah pada keputusan yang salah dalam perencanaan atau pelaksanaan. Mungkin Benchmarking sering digunakan untuk meningkatkan inovasi baru, dan menetapkan tujuan kinerja yang lebih baik. | K550: Pastikan bahwa data yang dikumpulkan relevan dan dapat dipercaya.
A551: 548 | B551: SPI-3 | C551: MONITORING DAN EVALUASI PEMUTAKHIRAN SISTEM INFORMASI TATA KELOLA MANAJEMEN SPI POLITEKNIK NEGERI MALANG TAHUN 2025 - SPI | D551: 10007000 | E551: 3 | F551: 3 | G551: LOW | I551: 1. Keterlambatan dalam Penyelesaian Pemutakhiran Sistem: Proses pembaruan sistem informasi menjadi lebih lambat dari jadwal yang telah ditetapkan, yang berpotensi menghambat implementasi kebijakan tata kelola manajemen SPI. 2. Sistem informasi yang tidak diperbarui atau kurang optimal dapat memperlambat proses kerja, meningkatkan beban administrasi manual, dan mengurangi efisiensi operasional secara keseluruhan. 3. Kurangnya pemutakhiran dapat menyebabkan data yang dihasilkan oleh sistem tidak akurat atau tidak terintegrasi dengan baik, sehingga menyulitkan pengambilan keputusan yang berbasis data. | J551: Karena adanya keterbatasan sumber daya manusia yang kompeten dan terlatih dalam pemutakhiran sistem informasi tata kelola manajemen SPI, serta kurangnya koordinasi antar unit terkait, mungkin pemutakhiran sistem informasi tidak berjalan sesuai rencana, terjadi keterlambatan implementasi, atau kualitas pembaruan sistem tidak optimal, sehingga meningkatkan risiko tidak tercapainya tujuan pemutakhiran sistem informasi untuk mendukung tata kelola manajemen SPI yang efektif dan efisien di Politeknik Negeri Malang tahun 2025. | K551: Untuk memitigasi dampak ini, diperlukan penguatan kompetensi SDM melalui pelatihan, peningkatan koordinasi lintas unit, dan pengawasan ketat terhadap setiap tahap pemutakhiran sistem informasi.
A552: 549 | B552: SPI-7 | C552: PENDAMPINGAN PENGENDALIAN INTERNAL PSDKU KOTA KEDIRI TAHUN 2025 - SPI | D552: 9374000 | E552: 2 | F552: 4 | G552: LOW | I552: Ketidaksesuaian antara rencana dengan kondisi lapangan juga dapat menyebabkan kegiatan pendampingan tidak efektif, karena tidak sesuai dengan kebutuhan atau tantangan yang dihadapi oleh PSDKU Kediri. Hal ini dapat mengakibatkan PSDKU Kediri tidak dapat mempertahankan atau meningkatkan kualitas pengendalian internnya, sehingga menimbulkan risiko terjadinya pelanggaran atau kegagalan dalam pengelolaan keuangan dan tidak terpenuhinya opini atas hasil audit Laporan Keuangan | J552: karena ketidaksesuaian antara rencana pengendalian internal dengan kondisi yang sebenarnya di lapangan mungkin akan mengakibatkan tidak terlaksananya kegiatan pendampingan sehingga tidak tercapainya sasaran keberhasilan pendampingan pengendalian internal | K552: 1. Menyusun dan menetapkan rencana pendampingan pengendalian internal yang sesuai dengan kebutuhan dan tantangan yang dihadapi oleh PSDKU Kediri. 2. Menyusun dan menetapkan mekanisme yang jelas untuk mengupdate rencana pendampingan pengendalian internal sesuai dengan perkembangan kondisi lapangan yang terjadi. 3. Memastikan bahwa semua unit kerja yang terkait dengan kegiatan pendampingan pengendalian internal memahami kewajiban dan tanggung jawabnya dalam menyediakan data dan informasi yang dibutuhkan.
A553: 550 | B553: UPA Bahasa-2 | C553: Pengadaan Sarana Pendukung Pengembangan Kursus Bahasa dan Layanan Bahasa Lainnya | D553: 28495280 | E553: 2 | F553: 3 | G553: LOW | I553: 1. Kegiatan tidak terlaksana sehingga menyebabkan kerugian baik moril maupun materiil. | J553: Karena tidak ada SDM yang bertanggungjawab dalam menentukan sarana yang sesuai dengan kebutuhan, dan mungkin tidak ada ketersediaan pendukung sarana yang dibutuhkan membuat kegiatan PENGADAAN SARANA PENDUKUNG PENGEMBANGAN KURSUS BAHASA DAN LAYANAN BAHASA LAINNYA tidak berjalan. | K553: Untuk mengatasi resiko yang mungkin terjadi, maka cara mengendalikan dampak nya adalah: 1) melakukan pendataan kebutuhan peralatan; 2) melakukan pengadaan sarana yang sesuai dengan kebutuhan; 3) melakukan perawatan sarana yang sudah ada.
A554: 551 | B554: UPA Bahasa-3 | C554: PENGEMBANGAN KURSUS BAHASA DAN LAYANAN BAHASA LAINNYA - UPA Bahasa | D554: 44620000 | E554: 2 | F554: 3 | G554: LOW | I554: 1. Kegiatan tidak terlaksana sehingga menyebabkan kerugian baik moril maupun materiil. | J554: Karena tidak ada SDM yang bertanggungjawab dalam memetakan dan membuat database tutor bahasa asing yang potensial dan mumpuni di bidang nya, dan mungkin tidak ada tutor bahasa asing sesuai dengan kebutuhan layanan sehingga kegiatan PENGEMBANGAN KURSUS BAHASA DAN LAYANAN BAHASA LAINNYA tidak berjalan. | K554: Untuk mengatasi resiko yang mungkin terjadi, maka cara mengendalikan dampak nya adalah: 1) mensosialisasikan kegiatan jauh jauh hari baik melalui jurusan, program studi dan media sosial; 2) menghadirkan tutor bahasa asing yang kompeten; 3) merancang kegiatan pembelajaran yang menarik, interaktif, mengimplementasikan metode pembalajaran terkini dan menambah praktek serta mengurangi teori sehingga kursus dapat menarik minat lebih banyak peserta dan meningkatkan keterampilan berbahasa peserta
... A696: 693 | B696: S-2 Sistem Informasi Akuntansi-5 | C696: PENINGKATAN KOMPETENSI DOSEN MELALUI SERTIKOM - S-2 SISTEM INFORMASI AKUNTANSI | D696: 6275000 | E696: 2 | F696: 1 | G696: VERY LOW | I696: Biaya registrasi tidak dapat segera direimburse ke peserta | J696: Karena kegiatan bersifat online, registrasi harus dibayarkan dimuka, dan proses administrasi keuangan membutuhkan waktu untuk pencairan dana registrasi, mungkin biaya registrasi tidak dapat segera direimburse ke peserta, sehingga peserta yang mengikuti dibawah target | K696: menargetkan calon calon peserta utnuk mengikuti online course yang sesuai dengan bidang keahlian dan memastikan proses pembayaran mudah aman dan lancar
A697: 694 | B697: S-2 Teknik Elektro-1 | C697: Implementasi Kerjasama Industri dengan PT Techno Triireka - S-2 Teknik Elektro - S-2 Teknik Elektro | D697: 22608000 | E697: 1 | F697: 4 | G697: VERY LOW | I697: Tidak adanya evaluasi proses belajar mengajar sehingga kekurangan dapat terulang di seriap tahun; Proses layanan pembelajaran kurang maksimal | J697: Karena tidak memiliki database PT yang sesuai untuk dilaksanakan kerjasama, mungkin tidak MoU/SPK dengan PT yang sesuai untuk dilaksanakan kerjasama, sehingga tidak adanya Inisiasi kerjasama dengan PT lain
A698: 695 | B698: SENAT-2 | C698: Workshop Sistem Pemantauan dan Evaluasi Penelitian, Inovasi dan Pengabdian Kepada Masyarakat | D698: 20000000 | E698: 2 | F698: 2 | G698: VERY LOW | I698: pengukuran dampak dari revisi kebijakan, terutama jika tidak ada mekanisme evaluasi yang jelas dan berkelanjutan. | J698: Salah satu risiko utama adalah kemungkinan kurangnya adopsi atau implementasi dari kebijakan yang diusulkan karena adanya perbedaan prioritas atau kurangnya dukungan dari pemangku kepentingan lain di institusi. Selain itu, risiko lain meliputi potensi ketidaklengkapan pemahaman peserta terhadap materi yang kompleks, yang dapat menghambat efektivitas kebijakan yang diterapkan. Ada juga risiko terkait dengan pengukuran dampak dari kebijakan baru, terutama jika tidak ada mekanisme evaluasi yang jelas dan berkelanjutan. Sebagai tambahan, risiko operasional seperti logistik atau teknologi selama pelaksanaan workshop juga bisa mempengaruhi pencapaian tujuan kegiatan. | K698: Pertama, penting untuk melakukan asesmen risiko awal guna mengidentifikasi potensi kendala, baik dari sisi kesiapan peserta maupun tantangan teknis, dan menyiapkan rencana mitigasi yang sesuai. Memastikan adanya komunikasi yang efektif sebelum dan selama workshop sangat penting untuk menyelaraskan tujuan dan mendapatkan dukungan dari para peserta serta pemangku kepentingan lainnya. Fasilitator workshop harus mampu menyederhanakan materi yang kompleks dan menyediakan sumber daya tambahan untuk mengatasi kesenjangan pemahaman. Pembentukan kelompok kerja atau tim tindak lanjut dapat membantu memperkuat adopsi kebijakan dengan mekanisme evaluasi dan penyesuaian berkelanjutan. Selain itu, memastikan aspek logistik dan teknis berjalan lancar melalui uji coba sebelumnya dapat mengurangi risiko operasional yang dapat mengganggu jalannya kegiatan.
A699: 696 | B699: SPI-9 | C699: PENGADAAN PERALATAN PENUNJANG PERKANTORAN SATUAN PENGAWAS INTERNAL (SPI) POLITEKNIK NEGERI MALANG | D699: 15000000 | E699: 1 | F699: 4 | G699: VERY LOW | I699: Polinema mengalami kesulitan dalam menemukan penyedia yang sesuai dan memenuhi persyaratan yang ditentukan, sehingga menyebabkan gagalnya proses pengadaan. | J699: Karena adanya peraturan bahwa pengadaan barang pendukung perkantoran harus berTKDN, mungkin sedikit penyedia yang mencantumkan keterangan barang berTKDN, sehingga pengadaan peralatan pendukung perkantoran gagal diadakan. | K699: 1. Berkoordinasi dengan pemerintah: berkoordinasi dengan pemerintah dan lembaga terkait untuk memastikan ketersediaan dan mempermudah proses pengadaan barang dengan TKDN. 2. Membuat daftar cadangan: membuat daftar cadangan dari penyedia alternatif yang memenuhi persyaratan TKDN jika terjadi kesulitan dalam menemukan penyedia utama.
A700: 697 | B700: UPA Pengembangan Karir dan Kewirausahaan-2 | C700: Edukasi / inklusi kesadaran kewirausahaan melalui Podcast 2025 - UPA Pengembangan Karir dan Kewirausahaan | D700: 10145000 | E700: 2 | F700: 2 | G700: VERY LOW | I700: 1. jadwal mundur | J700: karena penjadwalan yang kurang tepat sehingga mengakibatkan terhadapnya pelaksanaan kegiatan. | K700: 1.berkoordinasi dengan semua narasumber 2. membuat jadwal kegiatan dengan baik
A701: 698 | B701: UPA Pengembangan Karir dan Kewirausahaan-6 | C701: Pelatihan Kewirausahaan di PSDKU Politeknik Negeri Malang - UPA Pengembangan Karir dan Kewirausahaan | D701: 16200000 | E701: 2 | F701: 2 | G701: VERY LOW | I701: mengakibatkan kemunduran jadwal pelaksanaan kegiatan. | J701: karena pendadwalan yang kurang baik sehingga pelaksanaan kegiatan terhambat | K701: membuat jadwal kegiatan dan melaksanakan sesuai dengan perencanaan yang di buat
A702: 699 | B702: UPA Pengembangan Karir dan Kewirausahaan-12 | C702: Workshop pembuatan Proposal Business Plan - UPA Pengembangan Karir dan Kewirausahaan | D702: 10100000 | E702: 2 | F702: 2 | G702: VERY LOW | I702: peminat dan peserta PMW sedikit. | J702: karena informasi yang kurang sehingga menyebabkan peserta yang ikut dalam workshop kurang | K702: melakukan publikasi dan memberikan informasi kepada mahasiswa melalui jurusan maupun media sosial agar peserta banyak.
A703: 700 | B703: UPA Pengembangan Karir dan Kewirausahaan-13 | C703: Workshop penyusunan SOP layanan UPA PKK - UPA Pengembangan Karir dan Kewirausahaan | D703: 28330000 | E703: 1 | F703: 3 | G703: VERY LOW | I703: karena kurangnya koordinasi dan SDM yang kompeten akan menyebabkan kesulitan dalam penyusunan SOP untuk layanan di unit kerja UPA PKK. | J703: karena kurangnya koordinasi dan SDM yang kompeten sehingga menyebabkan kesulitan dalam penyusunan SOP di unit kerja. | K703: melakukan koordinasi bersama tim kerja dan seluruh jajaran unit kerja
A704: 701 | B704: UPA Pengembangan Karir dan Kewirausahaan-15 | C704: Recruitment - UPA Pengembangan Karir dan Kewirausahaan | D704: 29840000 | E704: 2 | F704: 2 | G704: VERY LOW | I704: kesulitan mencari ruangan karena ketersediaan ruangan yang terbatas sehingga harus dilaksanakan sabtu minggu. | J704: karena ketersediaan ruangan yang terbatas dan permintaan stake holders untuk recruitment sesuai urgensi mitra industri sehingga harus dilaksanakan pada hari sabtu minggu. | K704: 1. berkoordinasi dengan pihak stakeholders 2. berkoordinasi dengan intitusi terkait ruangan yang akan di gunakan. 3. pendadwalan yang tepat
A705: 702 | B705: UPA TIK-1 | C705: Evaluasi dan Penyusunan SOP | D705: 34400000 | E705: 1 | F705: 1 | G705: VERY LOW | I705: Sulitnya pengukuran capaian layanan tata kelola TIK | J705: Perkembangan teknologi yang cepat mengharuskan UPA TIK harus mengevaluasi, menyesuaikan dan membuat terobosan dalam SOP TIK | K705: Penyesuaian SOP dengan perkembangan teknologi
A706: 703 | B706: UPA TIK-2 | C706: Focus Group Discussion (FGD) antara UPA TIK dengan Unit kerja Lain | D706: 6851000 | E706: 1 | F706: 1 | G706: VERY LOW | I706: berkurangnya kelancaran pembelajaran dan kinerja institusi | J706: adanya komunikasi yang kurang antar unit kerja terkait TIK mengakibatkan kurang lancarnya pembelajaran dan kegiatan institusi lainnya | K706: Memulai komunikasi, dilanjutkan dengan koordinasi yang meningkatkan kolaborasi
A707: 704 | B707: UPA TIK-5 | C707: Pemeliharaan Jaringan Backbone, Jaringan Gedung dan AC | D707: 62435000 | E707: 1 | F707: 1 | G707: VERY LOW | I707: Terganggunya kinerja perangkat server yang akan mengganggu berjalannya proses bisnis | J707: Karena masing-masing perangkat komputer dan AC memiliki tipikal pemeliharaan berbeda mungkin Kerusakan Perangkat komputer dan AC tidak bisa diprediksi sehingga Pemeliharaan Perangkat Komputer dan AC - UPT PUSKOM Tidak Terjadwal | K707: Terdapat jadwal pemeliharaan perangkat jaringan komputer dan AC
A708: 705 | B708: WADIR I-5 | C708: Internasionalisasi mahasiswa melalui program akademik unggulan - WADIR I | D708: 230275000 | E708: 1 | F708: 5 | G708: VERY LOW | I708: Bidang 1 melakukan upaya dalam rangka internasionalisasi kampus sesuai dengan milestone institusi | J708: Karena rendahnya minat mahasiswa mengikuti student mobility, MUNGKIN tingginya biaya program akademik student mobility ke luar negeri, sehingga kegiatan Internasionalisasi mahasiswa melalui program akademik unggulan - PEMBANTU DIREKTUR I tidak bisa dijalankan. | K708: komunikasi yang baik antara polinema dengan penyelenggara
A709: 706 | B709: WADIR I-9 | C709: Visiting professor - WADIR I | D709: 89905000 | E709: 1 | F709: 3 | G709: VERY LOW | I709: Mengganggu kegiatan pembelajaran karena bahan yang diperlukan belum tersedia | J709: Karena pembelajaran belum ditunjang oleh media belajar digital berbasis PBL mungkin kurang siapnya dosen melaksanakan metode pembelajaran partisipatif SEHINGGA kegiatan Peningkatan Kualitas Pembelajaran melalui Metode Pembelajaran Partisipatif dan Pembelajaran Digital - PEMBANTU DIREKTUR I tidak bisa dijalankan. | K709: Mengajukan Kegiatan Penyusunan Metode Pembelajaran Partisipatif dan Pembelajaran Digital di institusi
... A717: 714 | B717: WADIR IV-1 | C717: HUMAS PPID: Promosi Joint Degree dan Kelas Internasional - WADIR IV | D717: 47535000 | E717: 1 | F717: 1 | G717: VERY LOW | I717: Promosi Joint Degree dan Kelas Internasional belum optimal. | J717: "Karena Kurangnya Promosi Joint Degree dan Kelas Internasional mungkin Tidak adanya perencanaan kebutuhan opeasional pengelola Promosi Joint Degree dan Kelas Internasional sehingga Promosi Joint Degree dan Kelas Internasional belum optimal. | K717: 1) Menyusun perencanaan yang matang;

Sheet Target Unit
B1: REKAP IDENTIFIKASI DAN ANALISIS RISIKO SELURUH UNIT TAHUN 2025
B3: Nama Unit & Kode | C3: Usulan Kegiatan | D3: Nilai Usulan | E3: Skor Probabilitas | F3: Skor Dampak | G3: Tingkat Risiko | H3: SPIP | I3: Uraian Dampak | J3: Pernyataan Risiko | K3: Pengendalian
A4: 18 | B4: BPKU-3 | C4: Pembinaan Dan Peningkatan Kualitas Pegawai Dalam Bidang Wawasan Kebangsaan | D4: 204269000 | E4: 4 | F4: 4 | G4: HIGH | I4: Tidak terlaksananya upacara dalam rangka peringatan Dies Natalis dan hari besar nasional | J4: Karena kurangnya koordinasi internai Pokja Protokoler dengan jajaran Pimpinan, mungkin tidak terdapat informasi terkait Pembinaan dan Peningkatan Kualitas Pegawai dalam Bidang Wawasan Kebangsaan sehingga Pembinaan dan Peningkatan Kualitas Pegawai dalam Bidang Wawasan Kebangsaan tidak berjalan | K4: Melaksanakan koordinasi dengan jajaran Pimpinan terkait upacara peringatan Dies Natalis dan hari besar nasional serta mencari informasi terkait pedoman pelaksanaan upacara dengan protokol kementerian. | L4: 1
A5: 19 | B5: BPKU-6 | C5: Pameran untuk keikutsertaan Promosi | D5: 122758000 | E5: 4 | F5: 4 | G5: HIGH | I5: Tidak dapat mengikuti pameran pendidikan yang mengakibatkan Menurunnya kuantitas pendaftarSPMB | J5: Karena masih dalam penyusunan anggaran indikatif mungkin kegiatan pameran dilaksanakan di awal tahun ketika belum ada anggaran dan Anggaran belum ditetapkan sehingga Pameran Pendidikan di Wilayah Jawa Timur mengalami kesulitan | K5: Melakukan koordinasi dengan pimpinan terkait mekanisme penggunaan anggaran di awal tahun sebelum anggaran tahun berjalan ditetapkan Melakukan sosialisasi PMB melalui media sosial resmi POLINEMA, website, dan jaringan alumni sekolah | L5: 2
A6: 20 | B6: D-III Teknik Listrik-2 | C6: Kolaborasi Riset Mahasiswa dan Dosen serta pembinaan mahasiswa berprestasi - D-III Teknik Listrik | D6: 47600000 | E6: 4 | F6: 5 | G6: HIGH | I6: menurunya persentase mahasiswa yang merahih prestasi | J6: Karena Tidak ada SDM untuk koordinasi info berkala terkait lomba kepada mahasiswa mungkin minat mahasiswa untuk ikut serta lomba di tingkat nasional menjadi berkurang sehingga Tidak terdapatnya Peningkatan kualitas mahasiswa melalui keikutsertaan dalam lomba | K6: Memberikan informasi-informasi dan pemndampingan ke mahasiswa berkaitan dengan lomba-lomba | L6: 3
A7: 21 | B7: D-III Teknik Listrik-9 | C7: Pesiapan Proses Audit Mutu Internal (AMI) - D-III Teknik Listrik | D7: 17240000 | E7: 4 | F7: 5 | G7: HIGH | I7: menurunnya jumlah: (1) Jumlah mahasiswa yang terlibat dalam kegiatan penelitian; (2) Jumlah mahasiswa yang terlibat dalam kegiatan PkM; (3) Jumlah prodi terakreditasi Unggul / A. | J7: Karena Tidak adanya database untuk mendukung penyusunan Dokumen yang dibutuhkan untuk Audit Mutu Internal (AMI) mungkin tidak ada SDM untuk menyusun dokumen sehingga tidak tersedianya dokumen kelengkapan audit | K7: Dengan meunjuk tim khusus untuk melakukan pengumpulan data dukung secara terorganisir dan termonitor sehingga memudahkan penyusunan dokumen AMI serta memberikan workshop dan pendampingan dalam AMI | L7: 4
A8: 22 | B8: D-III Teknik Elektronika-1 | C8: Pelaksanaan Monitoring Evaluasi Pembelajaran Semester Ganjil - D-III Teknik Elektronika | D8: 11312000 | E8: 4 | F8: 5 | G8: HIGH | I8: Tidak adanya evaluasi proses belajar mengajar sehingga kekurangan dapat terulang di seriap tahun; Proses layanan pembelajaran kurang maksimal | J8: Karena tidak adanya koordinasi untuk menyusun panduan monitoring pelaksanaan belajar mengajar mungkin tidak ada panduan dalam melakukan monitoring proses belajar mengajar sehingga tidak terdapatnya monitoring pelaksanaan belajar mengajar, dari UTS, UAS dan yudisium. | K8: Membuat tim untuk membentuk SOP, membuat SOP untuk monitoring pembelajaran dengan pengawasan dari kps | L8: 5
A9: 23 | B9: D-III Teknik Elektronika-3 | C9: Pelaksanaan Monitoring Evaluasi Pembelajaran Semester Genap - D-III Teknik Elektronika | D9: 11312000 | E9: 4 | F9: 5 | G9: HIGH | I9: Tidak adanya evaluasi proses belajar mengajar sehingga kekurangan dapat terulang di seriap tahun; Proses layanan pembelajaran kurang maksimal | J9: Karena tidak adanya koordinasi untuk menyusun panduan monitoring pelaksanaan belajar mengajar mungkin tidak ada panduan dalam melakukan monitoring proses belajar mengajar sehingga tidak terdapatnya monitoring pelaksanaan belajar mengajar, dari UTS, UAS dan yudisium. | K9: Membuat tim untuk membentuk SOP, membuat SOP untuk monitoring pembelajaran dengan pengawasan dari kps | L9: 6
A10: 24 | B10: D-III Teknik Elektronika-4 | C10: Pembekalan Mahasiswa Untuk Peningkatan Prestasi Mahasiswa - D-III Teknik Elektronika | D10: 29470000 | E10: 4 | F10: 5 | G10: HIGH | I10: menurunya persentase mahasiswa yang meraih prestasi | J10: Karena Tidak ada SDM untuk koordinasi info berkala terkait lomba kepada mahasiswa mungkin minat mahasiswa untuk ikut serta lomba di tingkat nasional menjadi berkurang sehingga Tidak terdapatnya Peningkatan kualitas mahasiswa melalui keikutsertaan dalam lomba | K10: Memberikan informasi-informasi dan pendampingan ke mahasiswa berkaitan dengan lomba-lomba | L10: 7
A11: 25 | B11: D-III Teknik Elektronika-7 | C11: Pengadaan Bahan Habis Pakai Laboratorium dan Bengkel - D-III Teknik Elektronika | D11: 139690303 | E11: 4 | F11: 5 | G11: HIGH | I11: Menurunnya jumlah BHP | J11: Karena Tidak adanya SDM yang dapat mencari BHP Praktikum dengan kandungan TKDN dan Menyusun HPS di Prodi DIII Teknik Elektronika mungkin Proses BHP Praktikum di Prodi DIII Teknik ELektronika menjadi Terlambat sehingga Tidak tersedia BHP Praktikum yang berkualitas untuk mahasiswa Prodi DIII Teknik Elektronika. | K11: untuk menyusun HPS Minta bantuan ke Tim Teknis Perumus HPS, untuk memenuhi TKDN mengikuti data base yang ada dan minimum 40 % , dan monitoring proses pengadaan | L11: 8
A12: 193 | B12: D-III Teknik Mesin-3 | C12: Monitoring dan Supervisi Pelaksanaan Magang Industri Mahasiswa Program Studi D3 Teknik Mesin | D12: 29851000 | E12: 3 | F12: 5 | G12: MIDDLE | I12: Masukan terhadap perbaikan kurikulum serta rencana pelaksanaan magang/PKL mahasiswa dengan berlakunya kurikulum 4+1+1 (1 smstr PKL di industri) tidak maksimal tersampaikan. | J12: Karena kurangnya komunikasi dan perencanaan jadwal kunjungan yang sesuai mungkin tidak banyak perusahaan yang menerima mahasiswa PKL dapat dikunjungi untuk kegiatan monev sehingga masukan terkait pelaksanaan PKL dan masukan terhadap perbaikan kurikulum belum dapat memperoleh feedback. | K12: Perlu ditingkatkan komunikasi dan perencanaan yang matang terkait rencana monev, supervisi dan kunjungan ke industri tempat mahasiswa PKL sehingga target kegiatan dapat tercapai | L12: 9
A13: 1 | B13: D-III Teknik Telekomunikasi-1 | C13: FGD dan Inisiasi kerja sama dalam pelaksanaan PKL dan MBKM - D-III Teknik Telekomunikasi | D13: 15790000 | E13: 5 | F13: 5 | G13: EXTREME | I13: Program studi kesulitan untuk mendapatkan mitra dalam upaya meingkatkan keikutsertaan MBKM bagi mahasiswa | J13: Karena kurangnya kepercayaan industri terhadap kompetensi mahasiswa mungkin tidak banyak industri telekomuniikasi yang dapat secara langsung melibatkan mahasiswa melalui MBKM sehingga kurangnya kerjasama prodi dengan mitra untuk menunjang MBKM | K13: Membuat database PT sehingga dapat memetakan mitra/industri yang telah dan belum menyusun dokumen kerjasama dengan Polinema serta menambahkan klausul penelitian dosen dan mahasiswa dalam dokumen kerjasama yang telah/akan dibuat | L13: 10
A14: 2 | B14: D-III Teknik Telekomunikasi-2 | C14: FGD dan Inisiasi Kerjasama dengan Kampus LN - D-III Teknik Telekomunikasi | D14: 8320000 | E14: 5 | F14: 5 | G14: EXTREME | I14: Program studi kesulitan untuk mendapatkan mitra dalam upaya meingkatkan keikutsertaan MBKM bagi mahasiswa | J14: Karena kurangnya kepercayaan industri terhadap kompetensi mahasiswa mungkin tidak banyak industri telekomuniikasi yang dapat secara langsung melibatkan mahasiswa melalui MBKM sehingga kurangnya kerjasama prodi dengan mitra untuk menunjang MBKM | K14: Membuat database PT sehingga dapat memetakan mitra/industri yang telah dan belum menyusun dokumen kerjasama dengan Polinema serta menambahkan klausul penelitian dosen dan mahasiswa dalam dokumen kerjasama yang telah/akan dibuat | L14: 11
A15: 26 | B15: D-III Teknik Telekomunikasi-5 | C15: Pemeliharaan Peralatan dan Mesin | D15: 45000000 | E15: 4 | F15: 5 | G15: HIGH | I15: Menurunnya jumlah alat/fasilitas/prasarana yang telah dipelihara dan berfungsi dengan baik | J15: Karena tidak ada database penyedia jasa pemeliharaan dan perawatan sarana prasarana pembelajaran mungkin tidak adanya pemetaan penyedia jasa pemeliharaan dan perawatan sarana prasarana yang baik sehingga tidak terlaksana pemeliharaan dan perawatan sarana dan prasarana pembelajaran | K15: 1. Membuat database penyedia jasa perawatan 2. Pemilihan penyedia jasa yang sesuai 3. Koordinasi dengan penyedia jasa untuk jadwal pelaksanaan perawatan 4. Melakukan pemantauan, perawatan, dan perbaikan alat dan mesin secara rutin | L15: 12
... A36: 9 | B36: D-IV Usaha Perjalanan Wisata-4 | C36: Peningkatan Kerjasama Program Studi Melalui Praktikum Mahasiswa Pada Mata Kuliah Akomodasi Perhotelan Dan Dan Restoran Ke Hotel Grand Mercure Malang Mirama - D-IV Usaha Perjalanan Wisata | D36: 4095000 | E36: 5 | F36: 5 | G36: EXTREME | I36: proses kegiatan praktikum tidak maksimal dan peserta tidak mendapatkan ilmu yang bisa digunakan pada dunia kerja | J36: karena tidak ada mahasiswa D4 UPW yang melakukan praktikum mahasiswa pada mata kuliah Akomodasi Perhotelan dan Restoran di industri secara riil mungkin karena tidak adanya praktisi dan pendamping minat kegiatan mahasiswa sehingga praktikum tersebut tidak berjalan | K36: melakukan persiapan secara matang untuk mencari narasumber yang sesuai dengan tema dan memiliki pengalaman menjadi pendamping pada program praktikum atau sejenis | L36: 33
A37: 10 | B37: D-IV Usaha Perjalanan Wisata-6 | C37: Workshop Ticketing and Reservation System - D-IV Usaha Perjalanan Wisata | D37: 4595000 | E37: 5 | F37: 5 | G37: EXTREME | J37: Karena terbatasnya industri atau institusi yang membuka program pelatihan ticketing dan reservation yang selaras dengan kebutuhan prodi D4 UPW dan mahasiswa tidak menyesuaikan kurikulum , mungkin karena terhambatnya proses penyusunan pedoman kurikulum khususnya ticketing dan reservation sehingga Workshop Ticketing and Reservation System - D-IV Usaha Perjalanan Wisata tidak berjalan dengan sesuai seperti yang diharapkan | K37: Sosialisasi kurikulum MK Ticketing dan Reservation dengan metode PBL sebelum kegiatan kepada seluruh dosen homebase D4 UPW | L37: 34
A38: 11 | B38: D-IV Usaha Perjalanan Wisata-7 | C38: Forum Group Discussion Tentang Penyusunan Kurikulum Berbasis OBE dengan Industri - D-IV Usaha Perjalanan Wisata | D38: 6455000 | E38: 5 | F38: 5 | G38: EXTREME | I38: Lamanya waktu yang diperlukan untuk telaah dan persiapan draft bahan ajar berbasis OBE | J38: Karena terbatasnya industri yang membuka program MBKM yang selaras dengan Prodi D4 UPW dan mahasiswa tidak menyesuaikan kurikulum dalam mengajukan MBKM mungkin karena terhambatnya proses penyusunan pedoman kurikulum berbasis OBE dengan industri di kantor pusat sehingga FGD tentang Penyusunan Kurikulum Berbasis OBE dengan Industri D-IV Usaha Perjalanan Wisata tidak berjalan sesuai yg seperti diharapkan | K38: Sosialisasi pedoman pembelajaran berbasis OBE sebelum kegiatan kepada seluruh dosen homebase D$ UPW | L38: 35
A39: 12 | B39: Jurusan Teknik Elektro-3 | C39: Inisiasi Kerjasama Dengan Mitra Potensial Dalam Bentuk Focus Group Discussion di Jurusan Teknik Elektro | D39: 17500000 | E39: 5 | F39: 5 | G39: EXTREME | I39: Jurusan Teknik Elektro tidak memiliki mitra untuk dapat meningkatkan kerjasama industri | J39: Karena kurangnya kepercayaan industri terhadap kompetensi Jurusan Teknik Elektro mungkin tidak banyak industri telekomuniikasi yang dapat secara langsung menjalin kerjasama melalui sehingga kurangnya kerjasama prodi dengan mitra untuk menunjang MBKM | K39: Membuat database PT sehingga dapat memetakan mana yang belum MoU dan yang sudah selain itu membuat perjanjian ditambahkan dengan penelitian dosen dan mahasiswa | L39: 36
A40: 112 | B40: P3M-12 | C40: PPM DIPA KOMPETISI 2025 - P3M | D40: 2530154350 | E40: 4 | F40: 5 | G40: HIGH | I40: Menggangu ketercapaian kinerja dosen dan IKU Polinema | J40: KARENA padatnya agenda pada Unit P3M Polinema MUNGKIN sosialisasi kegiatan pengabdian pada masyarakat tidak berjalan efektif SEHINGGA kegiatan PPM DIPA Kompetisi 2025 - P3M tidak mencapai target | K40: Perlu dilakukan penyusunan panduan dan skema pengabdian sebagai petunjuk teknis pelaksanaan. Perlu dilakukan sosialisasi panduan dan penentuan penjadwalan seleksi hingga pelaporan pelaksanaan kepada seluruh civitas akademika Polinema. Perlu dilakukannya monitoring dan koordinasi pelaksanaan kegiatan sehingga luaran pengabdian dapat tercapai | L40: 37
A41: 13 | B41: P3M-15 | C41: PENELITIAN DIPA KOMPETISI 2025 - P3M | D41: 5440155000 | E41: 5 | F41: 5 | G41: EXTREME | I41: Menggangu ketercapaian kinerja dosen dan IKU Polinema | J41: KARENA terlambat dalam menentukan skema penelitian MUNGKIN sosialisasi perubahan aturan terlambat disampaikan kepada peneliti SEHINGGA Penelitian DIPA KOMPTESI 2025 P3M tidak dapat dilaksanakan | K41: Perlu dilakukan penyusunan panduan dan skema penelitian sebagai petunjuk teknis pelaksanaan. Perlu dilakukan sosialisasi panduan dan penentuan penjadwalan seleksi hingga pelaporan pelaksanaan kepada seluruh civitas akademika Polinema. Perlu dilakukannya monitoring dan koordinasi pelaksanaan kegiatan sehingga luaran penelitian dapat tercapai | L41: 38
A42: 505 | B42: PSDKU Kota Kediri-20 | C42: GAJI DAN TUNJANGAN TENAGA KEPENDIDIKAN NON PNS | D42: 1946143150 | E42: 2 | F42: 4 | G42: LOW | I42: 1. keterlambatan pembayaran gaji dan tunjangan tenaga kependidikan 2. Penurunan produktivitas kinerja tenaga kependidikan 3. Proses administrasi perkantoran dan penunjang akademik tidak berjalan dengan lancar | J42: Karena adanya keterlambatan pengajuan pembayaran gaji dan tunjangan tenaga kependidikan mungkin pembayaran gaji dan tunjangan tenaga kependidikan tertunda sehingga menyebabkan penurunan kinerja tenaga kependidikan | K42: Untuk mengatasi risiko yang mungkin terjadi maka cara mengendalikan dampaknya adalah dengan memberikan pembayaran gaji sesuai dengan tanggal yang sudah ditetapkan | L42: 39
A43: 507 | B43: PSDKU Kota Kediri-22 | C43: PEMBAYARAN GAJI DAN TUNJANGAN ASN | D43: 3698315264 | E43: 2 | F43: 4 | G43: LOW | I43: 1. keterlambatan pembayaran gaji dan tunjangan PNS dan PPPK 2. Penurunan produktivitas kinerja PNS dan PPPK 3. Proses administrasi perkantoran dan penunjang akademik tidak berjalan dengan lancar | J43: Karena adanya keterlambatan pengajuan pembayaran gaji dan tunjangan PNS dan PPPK mungkin pembayaran gaji dan tunjangan PNS dan PPPK tertunda sehingga menyebabkan penurunan kinerja PNS dan PPPK | K43: Untuk mengatasi risiko yang mungkin terjadi maka cara mengendalikan dampaknya adalah dengan memberikan pembayaran gaji sesuai dengan tanggal yang sudah ditetapkan | L43: 40
A44: 496 | B44: PSDKU Kota Kediri-5 | C44: BIAYA JASA KEAMANAN, CLEANING SERVICE DAN GARDENER - PSDKU Kota Kediri | D44: 1646400000 | E44: 2 | F44: 4 | G44: LOW | I44: 1. Gaji dan fasilitas tenaga outsourcing berubah setiap tahun 2. Kinerja pegawai outsourcing di bawah standard yang diharapkan institusi 3. Kenyamanan dan kemanan lingkungan kampus dan perkantoran tidak optimal 4. Memerlukan waktu untuk beradaptasi kembali antara instansi PSDKU Kediri dan karyawan outsourcing dengan peraturan vendor baru | J44: Karena sistem pengadaan tenaga outsourcing dengan sistem lelang setiap tahunnya sehingga mungkin gaji dan fasilitas yang diterima tenaga kerja outsourcing berubah - ubah sesuai dengan ketentuan vendor yang memenangkan lelang kontrak, sehingga jika terjadi penurunan gaji dan fasilitas menyebabkan turunnya kinerja tenaga kerja outsourcing | K44: Untuk mengatasi risiko yang mungkin terjadi maka cara mengendalikan dampaknya adalah dengan melakukan koordinasi dengan vendor pemenang lelang untuk memberikan upah sesuai yang berlaku dengan tidak merugikan vendor | L44: 41
A45: 511 | B45: PSDKU Kota Lumajang-5 | C45: Belanja Operasional Penunjang Layanan Pendidikan (HIBAH dan PNBP) | D45: 1761377200 | E45: 2 | F45: 5 | G45: LOW | I45: 1. Layanan Pendidikan Terganggu, Jika dana operasional tidak tersedia, berbagai layanan pendidikan seperti pemeliharaan fasilitas, pengadaan alat pendukung, dan kegiatan akademik bisa terhambat. 2. Menurunnya Kualitas Pendidikan dan Layanan, Tanpa anggaran yang cukup, institusi mungkin kesulitan memberikan layanan yang optimal kepada mahasiswa dan tenaga pendidik. 3. Terhambatnya Kegiatan Akademik dan Kemahasiswaan, Jika dana operasional mencakup kegiatan mahasiswa, maka berbagai program seperti seminar, pelatihan, dan kegiatan ekstrakurikuler bisa mengalami hambatan atau dibatalkan. 4. Risiko Ketidakpatuhan Terhadap Peraturan Keuangan, Jika belanja operasional tidak dilaksanakan sesuai dengan peraturan yang berlaku, bisa timbul masalah administrasi atau bahkan sanksi dari pihak terkait. | J45: Karena Tidak memiliki jumlah tim pelaksana yang memenuhi untuk mengatasi banyaknya penanganan pengajuan realisasi GU/TUP, Mungkin menyebabkan Tidak ada Pemetaan program Rencana Anggaran Biaya yang bersumber dari Hibah Pemerintah Kabupaten Lumajang, Sehingga kegiatan Belanja Operasional Penunjang Layanan Pendidikan (HIBAH dan PNBP) tidak dapat dilaksanakan. | K45: Melakukan Pembayaran Secara Rutin dan berkala sesuai SBM dan Kepatiuhan terhadapa aturan yang berlaku sesuai target capaian Unit Kerja, melakukan koordinasi dengan pihak terkait agar pencairan dana bisa dipercepat, melakukan perencanaan keuangan yang lebih matang, serta memastikan bahwa regulasi dan persyaratan administrasi terpenuhi agar belanja operasional dapat segera direalisasikan. | L45: 42
A46: 553 | B46: UPA Bahasa-5 | C46: UJIAN TOEIC - MALA DAN IISMA 2025 - UPA BAHASA | D46: 1506265000 | E46: 2 | F46: 5 | G46: LOW | I46: 1. Kegiatan tidak terlaksana sehingga menyebabkan kerugian baik moril maupun materiil. | J46: Karena kurang adanya koordinasi dengan masing-masing jurusan baik di kampus utama maupun PSDKU terkait sosialisasi TOEIC untuk MALA, dan mungkin karena tidak ada sosialisasi terstruktur terkait TOEIC kepada MALA sehingga kegiatan ujian TOEIC MALA tidak berjalan. | K46: Untuk mengatasi resiko yang mungkin terjadi, maka cara mengendalikan dampaknya adalah: 1) melakukan koordinasi dengan semua jurusan baik di kampus utama maupun PSDKU; 2) memberikan sosialisasi mengenai ujian TOEIC dan memberikan kesempatan mahasiswa tingkat akhir mempersiapkan diri secara mandiri dengan menyediakan soal-soal latihan TOEIC dengan menggunakan platform seperti google classroom atau moodle. | L46: 43
A47: 15 | B47: UPA Pengembangan Karir dan Kewirausahaan-10 | C47: Program Mahasiswa Wirausaha (PMW) Polinema 2025 - UPA Pengembangan Karir dan Kewirausahaan | D47: 302568000 | E47: 5 | F47: 5 | G47: EXTREME | I47: Karena KETERLAMBATAN DAN SULITNYA PROSES PENCAIRAN BANTUAN MODAL USAHA , sehingga menyebabkan resiko sangat terlambat dalam proses pendampingan dan produksi, yang mengakibatkan mundurnya jadwal kegiatan lainnya sebagai rangkaian kegiatan PMW. ada beberapa kegiatan lain yang pelaksanaan nya hanya bisa dilakukan setelah tenant PMW berjalan proses produksinya, sehingga jika pencairan modal usaha ini terlambata akan menghambat pelaksanaan kegiatan lainnya. perlu di pahami bahwa wirausaha adalah menjalankan usaha yang membutuhkan modal untuk proses produksinya. periode waktu usaha yang seharusnya 1 tahun juga sangat terbatas, karena efektif operasional usahanya hanya 6 bulan (jika pencairan bantuan modal di bulan mei 2025). hal ini sebenar nya kurang efektif untuk progres sebuah usaha. oleh karena itu kami berharap bantuan untuk ketepatan jawal pelaksanaan program. | J47: Karena KETERLAMBATAN DAN SULITNYA PROSES PENCAIRAN BANTUAN MODAL USAHA , sehingga menyebabkan resiko sangat terlambat dalam proses pendampingan dan produksi, yang mengakibatkan mundurnya jadwal kegiatan lainnya sebagai rangkaian kegiatan PMW. | K47: 1. penjadwalan dan pelaksanaan kegiatan sesuai dengan time line yang sudah di tetapkan. 2. koordinasi dengan bagian keuangan dan tim kerja terkait ketepatan waktu pencairan bantuan modal usaha mahasiswa. 3. komunikasi yang baik agar pelaksanaan kegiatan bisa dilakukan dengan baik, efektif, tepat waktu , dan memberikan manfaat bagi mahasiswa wirausaha. | L47: 44
A48: 14 | B48: UPA Pengembangan Karir dan Kewirausahaan-4 | C48: INKUBASI WIRAUSAHA MAHASISWA 2025 - UPA Pengembangan Karir dan Kewirausahaan | D48: 77080000 | E48: 5 | F48: 5 | G48: EXTREME | I48: terjadi kemunduran pelaksanaan kegiatan penampingan usaha dari tenant inkubasi. | J48: karena adanya keterlambatan pencairan bantuan modal usaha dan tidak tepat waktu, sehingga menyebabkan kendala di keseluruhan proses pendampingan terutama mundurnya jadwal pelaksanaan kegiatan. | K48: membuat jadwal pelaksanaanan kegiatan, dan kepatuhan terhadap jadwal yang di buat. pencairan modal usaha tepat waktu sehingga membantu proses kelancaran pendampingan dan kegiatan produksi mahasiswa wirausaha. | L48: 45
A49: 592 | B49: WADIR I-7 | C49: Peningkatan Kuantitas dan Kualitas Lulusan melalui Kegiatan Wisuda - WADIR I | D49: 3618671150 | E49: 2 | F49: 5 | G49: LOW | I49: Bentuk dukungan kepada lulusan dan menggeser status menjadi alumni | J49: Karena jumlah mahasiswa yang lulus di tahun berjalan tidak menentu mungkin akan kesulitan menyesuaikan dengan jadwal yang sudah direncanakan sehingga kegiatan Peningkatan Kualitas Lulusan melalui Kegaiatan Wisuda. - PEMBANTU DIREKTUR I tidak bisa dijalankan. | K49: melibatkan akademik prodi dan akademik pusat serta seluruh civitas untuk bertanggung jawab terhadap kelulusan | L49: 46
... A75: 16 | B75: WADIR II-10 | C75: PEMBANGUNAN GEDUNG DAN BANGUNAN PENDUKUNG PEMBELAJARAN - BLU | D75: 40556300000 | E75: 5 | F75: 5 | G75: EXTREME | I75: Melakukan persiapan data dukung tender secara lengkap dan lebih awal, dan pendampingan proses oleh BPKP Jawa Timur dan Kejaksaan Tinggi Negeri | J75: Karena Data dukung penting untuk pengadaan tidak segera tersedia mungkin Kelengkapan berkas pengadaan terlambat sehingga Pembangunan Gedung dan Bangunan Pendukung Pembelajaran tidak selesai. | K75: Adanya pendampingan dari pihak BPKP Jawa Timur dan Kejaksaan Tinggi Negeri agar pembangunan gedung dan bangunan pendukung pembelajaran dapat selesai tepat waktu. | L75: 72

Sheet Panduan
B1: PANDUAN PENGISIAN
B2: LEMBAR MONITORING DAN EVALUASI MANAJAMENEN RISIKO UNIT
B3: SATUAN PENGAWAS INTERNAL POLITEKNIK NEGERI MALANG
B4: TAHUN 2025
B6: 1. | C6: Pastikan Unit dan No Kegiatan yang akan di reviu sesuai dengan Sheet Distribusi Unit
B7: 2. | C7: Apabila Kegiatan tersebut sudah selesai dilaksanakan, tentukan kegiatan lain unit tersebut yang belum di laksanakan dengan pertimbangan Level Risiko pada Sheet By Level, dengan cara Filter Nama Unit pada Kolom Nama Unit dan Kode, kemudian Filter lagi dengan Tingkat Risiko
B8: 3. | C8: Pilih Nama Reviuer pada Kolom Pemonev
B9: 4. | C9: Entry No Kegiatan yang akan di reviu pada Sheet Lembar Monitoring, mulai dari No Kegiatan 1 - 9 pada baris 7 sheet tersebut
B10: 5. | C10: Pilih Mitigasi Risiko yang diambil oleh Unit Kolom Mitigasi Risiko
C11: - Menerima Risiko
C12: - Membagi Risiko
C13: - Melimpahkan Risiko
B14: 6. | C14: Isikan Mitigasi Risiko yang dipilih Unit dengan ketentuan:
C15: - Jika Membagi Risiko atau Melimpahkan Risiko
C16: ==> Isikan Nama Unit Penerima Risiko (bisa 1 unit atau lebih) pada Kolom Unit Penerima Risiko
C17: - Jika Menerima Risiko
C18: ==> Isikan Blank Cell pada Kolom Unit Penerima Risiko
B19: 7. | C19: Isi Kolom Status Konfirmasi yang sesuai jika:
C20: - Menerima Risiko ==> Status Konfirmasi Blank Cell
C21: - Membagi atau Melimpahkan Risiko ==> Konfirmasi Status (Sudah Konfirmasi / Belum Konfirmasi) Unit Penerima Risiko
B22: 8. | C22: Pilih Risiko Residual sebagai dampak Mitigasi tersebut pada langkah 4
C23: - Extreme
C24: - High
C25: - Middle
C26: - Low
C27: - Very Low
B28: 9. | C28: Beri Komentar pada kolom Komentar:
C29: - Bagaimana mereka memitigasi Risiko kegiatan
C30: - Bagaimana efek mitigasi risiko sehingga Residual Risiko berubah turun atau naik
C31: - Komentar lainnya
B32: 10. | C32: Entry nama lengkap Wakil Unit pada tempatnya
B33: 11. | C33: Lanjutkan cara yang sama pada kegiatan yang lain.
B34: 12. | C34: Klik gambar Dokumen ( ) di samping untuk menuju pada kegiatan selanjutnya. Warna kuning menunjukkan sedang berada pada kegiatan tersebut
B35: 13. | C35: Jika semua kegiatan telah di reviu, Cetak Lembar monitoring sebanyak 2 Exp
B36: 14. | C36: Bubuhkan TTD pada unit dan Reviuer
B37: 15. | C37: Setiap unit dapat 1 Exp Lembar Monitoring dan 1 Exp untuk SPI
B38: 16. | C38: Simpan File dengan Tambahan nama masing2 Reviuer kemudian di Upload ke spi@polinema.ac.id

Sheet Distribusi Unit
B4: No | C4: Nama Unit | D4: Jumlah Kegiatan | E4: NO | F4: Pemonev | G4: WAKTU I | H4: WAKTU II
E5: KEGIATAN
B6: 1 | C6: PSDKU Kediri | D6: 3 | E6: 496, 505, 507 | F6: Dr. Atik Andhayani, S.E., MSA. | G6: 1
B7: 2 | C7: D-III Teknik Elektronika | D7: 4 | E7: 22, 23, 24, 25 | F7: Dr. Atik Andhayani, S.E., MSA. | H7: 1
B8: 3 | C8: BPKU | D8: 2 | E8: 18, 19 | F8: Dr. Atik Andhayani, S.E., MSA. | G8: 1
B9: 4 | C9: D-IV Jaringan Telekomunikasi Digital | D9: 1 | E9: 3 | F9: Dr. Drs. Sumiadji, Ak., M.SA. | H9: 1
B10: 5 | C10: D-III Teknik Listrik | D10: 2 | E10: 20, 21 | F10: Dr. Drs. Sumiadji, Ak., M.SA. | H10: 1
B11: 6 | C11: D-IV Manajemen Pemasaran | D11: 4 | E11: 4, 5, 6 ,7 | F11: Ir. Wahiddin, S.T., MT.IPM.ASEAN Eng. | G11: 1
B12: 7 | C12: D-III Teknik Telekomunikasi | D12: 4 | E12: 1, 2, 26, 27 | F12: Ir. Wahiddin, S.T., MT.IPM.ASEAN Eng. | H12: 1
B13: 8 | C13: D-III Teknik Kimia | D13: 1 | E13: 40 | F13: Ir. Wahiddin, S.T., MT.IPM.ASEAN Eng. | H13: 1
B14: 9 | C14: UPA PKK | D14: 2 | E14: 14, 15 | F14: Drs. Mufid M.T. | H14: 1
B15: 10 | C15: PSDKU Lumajang | D15: 1 | E15: 511 | F15: Drs. Mufid M.T. | G15: 1
B16: 11 | C16: Jurusan Teknik Elektro | D16: 1 | E16: 12 | F16: Drs. Mufid M.T. | H16: 1
B17: 12 | C17: D-IV Teknik Informatika | D17: 1 | E17: 67 | F17: Drs. Mufid M.T. | H17: 1
B18: 13 | C18: D-IV Perjalanan Wisata | D18: 4 | E18: 8, 9, 10, 11 | F18: Drs. Mufid M.T. | G18: 1
B19: 14 | C19: WADIR III | D19: 2 | E19: 179, 311 | F19: Lis Diana Mustafa, S.T., M.T. | G19: 1
B20: 15 | C20: WADIR I | D20: 1 | E20: 592 | F20: Lis Diana Mustafa, S.T., M.T. | G20: 1
B21: 16 | C21: UPA Bahasa | D21: 1 | E21: 553 | F21: Lis Diana Mustafa, S.T., M.T. | G21: 1
B22: 17 | C22: P3M | D22: 2 | E22: 13, 112 | F22: Lis Diana Mustafa, S.T., M.T. | H22: 1
B23: 18 | C23: D-IV Teknik Kimia Industri | D23: 1 | E23: 68 | F23: Lis Diana Mustafa, S.T., M.T. | H23: 1
B24: 19 | C24: D-IV Manajemen Rekayasa Konstruksi | D24: 1 | E24: 402 | F24: Lis Diana Mustafa, S.T., M.T. | H24: 1
B25: 20 | C25: D-III Teknik Mesin | D25: 1 | E25: 193 | F25: Lis Diana Mustafa, S.T., M.T. | H25: 1
B26: 21 | C26: D-III Akuntansi PSDKU Kediri | D26: 1 | E26: 36 | F26: Usman Nurhasan, S.Kom., M.T. | H26: 1
B27: 22 | C27: D-III Administrasi Bisnis | D27: 8 | E27: 28, 29, 30, 31, 32, 33, 34, 35 | F27: Usman Nurhasan, S.Kom., M.T. | G27: 1
B28: 23 | C28: WADIR II | D28: 24 | E28: 16, 17, 54, 157, 161, 162, 164, 166, 169, 170, 171, 179, 306, 308, 311, 599, 602, 603, 605, 607, 608, 615, 617, 710, 711 | F28: Lina Budiarti (9); Dr. Ir. Azam Muzakhim Imammuddin, MT. (9); Dr. Drs. Sumiadji, Ak., M.SA. (6) | G28: 1,1,1
C29: TOTAL KEGIATAN UNIT | D29: =SUM(D6:D28) -> 72

Sheet By Budget
B1: REKAP IDENTIFIKASI DAN ANALISIS RISIKO SELURUH UNIT TAHUN 2025
A3: NO | B3: Nama Unit & Kode | C3: Usulan Kegiatan | D3: Nilai Usulan | E3: Skor Probabilitas | F3: Skor Dampak | G3: Tingkat Risiko | H3: SPIP | I3: Uraian Dampak | J3: Pernyataan Risiko | K3: Pengendalian
A4: 17 | B4: WADIR II-25 | C4: PEMBANGUNAN GEDUNG DAN BANGUNAN PENDUKUNG PEMBELAJARAN SBSN - RM - WADIR II | D4: 87468000000 | E4: 5 | F4: 5 | G4: EXTREME | I4: Melakukan persiapan data dukung tender secara lengkap dan lebih awal, dan pendampingan proses oleh BPKP Jawa Timur dan Kejaksaan Tinggi Negeri | J4: Karena Data dukung penting untuk pengadaan tidak segera tersedia mungkin Kelengkapan berkas pengadaan terlambat sehingga Pembangunan Gedung dan Bangunan Pendukung Pembelajaran tidak selesai. | K4: Adanya pendampingan dari pihak BPKP Jawa Timur dan Kejakaan Tinggi Negeri agar pembangunan gedung dan bangunan pendukung pembelajar dapat selesai tepat waktu. | L4: 1
A5: 16 | B5: WADIR II-10 | C5: PEMBANGUNAN GEDUNG DAN BANGUNAN PENDUKUNG PEMBELAJARAN - BLU | D5: 40556300000 | E5: 5 | F5: 5 | G5: EXTREME | I5: Melakukan persiapan data dukung tender secara lengkap dan lebih awal, dan pendampingan proses oleh BPKP Jawa Timur dan Kejaksaan Tinggi Negeri | J5: Karena Data dukung penting untuk pengadaan tidak segera tersedia mungkin Kelengkapan berkas pengadaan terlambat sehingga Pembangunan Gedung dan Bangunan Pendukung Pembelajaran tidak selesai. | K5: Adanya pendampingan dari pihak BPKP Jawa Timur dan Kejaksaan Tinggi Negeri agar pembangunan gedung dan bangunan pendukung pembelajaran dapat selesai tepat waktu. | L5: 2 | M5: 1
A6: 13 | B6: P3M-15 | C6: PENELITIAN DIPA KOMPETISI 2025 - P3M | D6: 5440155000 | E6: 5 | F6: 5 | G6: EXTREME | I6: Menggangu ketercapaian kinerja dosen dan IKU Polinema | J6: KARENA terlambat dalam menentukan skema penelitian MUNGKIN sosialisasi perubahan aturan terlambat disampaikan kepada peneliti SEHINGGA Penelitian DIPA KOMPTESI 2025 P3M tidak dapat dilaksanakan | K6: Perlu dilakukan penyusunan panduan dan skema penelitian sebagai petunjuk teknis pelaksanaan. Perlu dilakukan sosialisasi panduan dan penentuan penjadwalan seleksi hingga pelaporan pelaksanaan kepada seluruh civitas akademika Polinema. Perlu dilakukannya monitoring dan koordinasi pelaksanaan kegiatan sehingga luaran penelitian dapat tercapai | L6: 3 | M6: 2
A7: 15 | B7: UPA Pengembangan Karir dan Kewirausahaan-10 | C7: Program Mahasiswa Wirausaha (PMW) Polinema 2025 - UPA Pengembangan Karir dan Kewirausahaan | D7: 302568000 | E7: 5 | F7: 5 | G7: EXTREME | I7: Karena KETERLAMBATAN DAN SULITNYA PROSES PENCAIRAN BANTUAN MODAL USAHA , sehingga menyebabkan resiko sangat terlambat dalam proses pendampingan dan produksi, yang mengakibatkan mundurnya jadwal kegiatan lainnya sebagai rangkaian kegiatan PMW. ada beberapa kegiatan lain yang pelaksanaan nya hanya bisa dilakukan setelah tenant PMW berjalan proses produksinya, sehingga jika pencairan modal usaha ini terlambata akan menghambat pelaksanaan kegiatan lainnya. perlu di pahami bahwa wirausaha adalah menjalankan usaha yang membutuhkan modal untuk proses produksinya. periode waktu usaha yang seharusnya 1 tahun juga sangat terbatas, karena efektif operasional usahanya hanya 6 bulan (jika pencairan bantuan modal di bulan mei 2025). hal ini sebenar nya kurang efektif untuk progres sebuah usaha. oleh karena itu kami berharap bantuan untuk ketepatan jawal pelaksanaan program. | J7: Karena KETERLAMBATAN DAN SULITNYA PROSES PENCAIRAN BANTUAN MODAL USAHA , sehingga menyebabkan resiko sangat terlambat dalam proses pendampingan dan produksi, yang mengakibatkan mundurnya jadwal kegiatan lainnya sebagai rangkaian kegiatan PMW. | K7: 1. penjadwalan dan pelaksanaan kegiatan sesuai dengan time line yang sudah di tetapkan. 2. koordinasi dengan bagian keuangan dan tim kerja terkait ketepatan waktu pencairan bantuan modal usaha mahasiswa. 3. komunikasi yang baik agar pelaksanaan kegiatan bisa dilakukan dengan baik, efektif, tepat waktu , dan memberikan manfaat bagi mahasiswa wirausaha. | L7: 4
A8: 162 | B8: WADIR II-20 | C8: BELANJA PEGAWAI : Remunerasi Tenaga Pendidik | D8: 50000000000 | E8: 4 | F8: 5 | G8: HIGH | I8: kepuasan layanan pembayaran remunerasi rendah | J8: Karena Kurang tertib kinerja dari staff kepegawaian menyerahkan data kehadiran dan data dukung individu terbaru mungkin penyerahan/pemutahiran data dukung dalam sistem pembayaran remunerasi terlambat dilakukan sehingga Pembayaran Remunerasi Tenaga Pendidik tidak dibayarkan tepat waktu. | K8: Agar tidak terlambat, dilakukan prosedur supervisi berkala/rutin dalam pemutakhiran basis data kepegawaian | L8: 5
A9: 170 | B9: WADIR II-44 | C9: Remunerasi Tenaga Pendidik | D9: 50000000000 | E9: 4 | F9: 5 | G9: HIGH | I9: kepuasan layanan pembayaran remunerasi rendah | J9: Karena Kurang tertib kinerja dari staff kepegawaian menyerahkan data kehadiran dan data dukung individu terbaru mungkin penyerahan/pemutahiran data dukung dalam sistem pembayaran remunerasi terlambat dilakukan sehingga Pembayaran Remunerasi Tenaga Pendidik tidak dibayarkan tepat waktu. | K9: Agar tidak terlambat, dilakukan prosedur supervisi berkala/rutin dalam pemutakhiran basis data kepegawaian | L9: 6
A10: 161 | B10: WADIR II-19 | C10: BELANJA PEGAWAI : Remunerasi Tenaga Kependidikan | D10: 11000000000 | E10: 4 | F10: 5 | G10: HIGH | I10: kepuasan layanan pembayaran remunerasi rendah | J10: Karena Kurang tertib kinerja dari staff kepegawaian menyerahkan data kehadiran dan data dukung individu terbaru mungkin penyerahan/pemutahiran data dukung dalam sistem pembayaran remunerasi terlambat dilakukan sehingga Pembayaran Remunerasi Tenaga Kependidikan tidak dibayarkan tepat waktu. | K10: Agar tidak terlambat, dilakukan prosedur supervisi berkala/rutin dalam pemutakhiran basis data kepegawaian | L10: 7
A11: 169 | B11: WADIR II-43 | C11: Remunerasi Tenaga Kependidikan | D11: 11000000000 | E11: 4 | F11: 5 | G11: HIGH | I11: kepuasan layanan pembayaran remunerasi rendah | J11: Karena Kurang tertib kinerja dari staff kepegawaian menyerahkan data kehadiran dan data dukung individu terbaru mungkin penyerahan/pemutahiran data dukung dalam sistem pembayaran remunerasi terlambat dilakukan sehingga Pembayaran Remunerasi Tenaga Kependidikan tidak dibayarkan tepat waktu. | K11: Agar tidak terlambat, dilakukan prosedur supervisi berkala/rutin dalam pemutakhiran basis data kepegawaian | L11: 8
A12: 157 | B12: WADIR II-6 | C12: DUKUNGAN OPERASIONAL LAYANAN PENDIDIKAN | D12: 5827086050 | E12: 4 | F12: 4 | G12: HIGH | I12: Biaya layanan pendidikan yang dibutuhkan tidak dapat cair pada saat pelaksanaan kegiatan, sehingga pembayarannya akan tertunda. | J12: Karena Tidak adanya kepastian jadwal pelaksanaan kegiatan yang dilakukan oleh unit kerja mungkin pengajuan biaya layanan pendidikan terlambat sehingga pencairan biaya layanan pendidikan terlambat. | K12: Memasukan pengajuan pencairan dana pada timeline jauh hari sebelum pelaksanaan kegiatan sehingga pada saat pelaksanan kegiatan biaya layanan pendidikan sudah siap untuk digunakan. | L12: 9
A13: 112 | B13: P3M-12 | C13: PPM DIPA KOMPETISI 2025 - P3M | D13: 2530154350 | E13: 4 | F13: 5 | G13: HIGH | I13: Menggangu ketercapaian kinerja dosen dan IKU Polinema | J13: KARENA padatnya agenda pada Unit P3M Polinema MUNGKIN sosialisasi kegiatan pengabdian pada masyarakat tidak berjalan efektif SEHINGGA kegiatan PPM DIPA Kompetisi 2025 - P3M tidak mencapai target | K13: Perlu dilakukan penyusunan panduan dan skema pengabdian sebagai petunjuk teknis pelaksanaan. Perlu dilakukan sosialisasi panduan dan penentuan penjadwalan seleksi hingga pelaporan pelaksanaan kepada seluruh civitas akademika Polinema. Perlu dilakukannya monitoring dan koordinasi pelaksanaan kegiatan sehingga luaran pengabdian dapat tercapai | L13: 10
A14: 166 | B14: WADIR II-29 | C14: SEMINAR DAN PELATIHAN SERTA WORKSHOP PENJAMINAN MUTU KELEMBAGAAN DAN ORGANISASI - WADIR II - WADIR II | D14: 2091125000 | E14: 4 | F14: 4 | G14: HIGH | I14: FGD di lingkungan Bidang II dan BPKU untuk menentukan kebutuhan pelatihan tendik dan dokumen wajib organisasi dan mapping untuk pemenuhan dan perbaikannya | J14: Karena Telaah atas kebutuhan pelatihan tendik dan kebutuhan dokumen wajib organisasi belum tersedia mungkin Institusi belum menetapkan gap atas kebutuhan pelatihan tendik dan pemenuhan dokumen wajib untuk meningkatkan mutu kelembagaan dan organisasi sehingga Kegiatan Seminar/Pelatihan | K14: Pemberian informasi yang lengkap dan detil secara periodik kepada tenaga kependidikan untuk mengikuti seminar/sertifikasi/workshop yang dapat meningkatkan performa kerjanya | L14: 11
A15: 179 | B15: WADIR III-15 | C15: Program Pengiriman Mahasiswa ke Perlombaan - WADIR III - WADIR III - WADIR III | D15: 1891000000 | E15: 4 | F15: 4 | G15: HIGH | I15: 1. Kontribusi ke IKU 2 sedikit (<1%) (jumlah mahasiswa berprestasi tingkat nasional atau internasional) 2. Kontribusi ke IKU 3 belum maksimal, masih bisa ditingkatkan (jumlah pembimbing mahasiswa berprestasi tingkat nasional atau internasional) | J15: KARENA Tidak memiliki data base Mahasiswa yang kompenten sesuai dengan jenis lomba dan data jenis lomba yang akan dilesenggarakan oleh Penyelenggara, MUNGKIN Tidak ada Pemetaan kompetensi mahasiswa yang sesuai dengan jenis lomba yang akan diikuti dan Tidak ada data jenis lomba yang akan diselenggarakan oleh pihak Penyelengara, SEHINGGA Pengiriman Mahasiswa Ke Perlombaan tidak berjalan optimal | K15: KARENA belum maksimalnya (< 1%) jumlah mahasiswa yang mengikuti ajang perlombaan tingkat nasional atau internasional, MAKA ALTERNATIF SOLUSINYA ADALAH: 1. Sosialisasi secara lebih intensif dan menyeluruh kepada mahasiswa dan dosen (calon pembimbing) tentang program pengiriman mahasiswa ke ajang perlombaan tingkat nasional dan internasional 2. Sosialisasi secara lebih intensif dan menyeluruh kepada mahasiswa dan dosen (calon pembimbing) tentang program rewards terhadap prestasi mahasiswa dan pembimbingnya tingkat nasional dan internasional 3. Meningkatkan intensitas pencarian informasi tentang lomba dan menyebarluaskan kepada mahasiswa dan dosen calon pembimbing 4. Meningkatkan intensitas kegiatan penulusuran calon mahasiswa berprestasi ke sekolah-sekolah 5. Meningkatkan pembinaan kemampuan mahasiswa yang berbakat untuk berprestasi lebih tinggi | L15: 12
A16: 171 | B16: WADIR II-45 | C16: PENGADAAN ALAT PENGOLAH DATA DAN INFORMASI PENDUKUNG PEMBELAJARAN - WADIR II | D16: 1825639730 | E16: 4 | F16: 5 | G16: HIGH | I16: Melakukan analisis kebutuhan pengembangan sistem dengan personil yang mempunyai kualifikasi yang memadahi | J16: Karena kurangnya pengembangan staff yang cukup untuk kepentingan kajian aplikasi yang tepat mungkin analisis Sistem dan infrastruktur tidak direncanakan secara baik sehingga Pengadaan Alat pengolah data dan informasi pendukung pembelajaran tidak berfungsi secara efektif. | K16: Membuat hasil analisis kebutuhan pengembangan sistem dan menyiapkan personil yang kualified dan kompeten | L16: 13
A17: 164 | B17: WADIR II-24 | C17: PEMELIHARAAN DAN PERAWATAN JARINGAN - WADIR II | D17: 1500000000 | E17: 5 | F17: 4 | G17: HIGH | I17: Melakukan pemantauan melalui daftar permintaan dan tindakan pemeliharaan dan perawatan jaringan | J17: Karena Rapat koordinasi antara user, rumah tangga dan PPK tidak dilakukan pada awal tahun anggaran mungkin Analisis kebutuhan perbaikan dan perawatan jaringan tidak mempertimbangkan identifikasi sehingga Pemeliharaan dan perawatan jaringan dilakukan tidak sesuai dengan prioritas. | K17: Selalu menyiapkan daftar perawatan dari user dan menyusun time line agar pelaksanaan pemeliharaan dan perawatan jaringan tidak sampai terlewatkan | L17: 14
A18: 151 | B18: WADIR I-2 | C18: Peningkatan Kualitas Lulusan melalui Kualitas Input (MABA) - WADIR I | D18: 1185384800 | E18: 4 | F18: 5 | G18: HIGH | I18: kebutuhan dalam penerimaan MABA tidak dapat terfasilitasi | J18: Karena terdapat perubahan sistem dalam penerimaan mahasiswa baru , mungkin hasil perencanaan pelaksanaan kegiatan menjadi tidak baik, sehingga kegiatan Peningkatan Kualitas Lulusan melalui Kualitas Input (MABA). - PEMBANTU DIREKTUR I tidak bisa dijalankan | K18: updating sistem penerimaan mahasiswa baru agar fit and proper | L18: 15
... A36: 507 | B36: PSDKU Kota Kediri-22 | C36: PEMBAYARAN GAJI DAN TUNJANGAN ASN | D36: 3698315264 | E36: 2 | F36: 4 | G36: LOW | I36: 1. keterlambatan pembayaran gaji dan tunjangan PNS dan PPPK 2. Penurunan produktivitas kinerja PNS dan PPPK 3. Proses administrasi perkantoran dan penunjang akademik tidak berjalan dengan lancar | J36: Karena adanya keterlambatan pengajuan pembayaran gaji dan tunjangan PNS dan PPPK mungkin pembayaran gaji dan tunjangan PNS dan PPPK tertunda sehingga menyebabkan penurunan kinerja PNS dan PPPK | K36: Untuk mengatasi risiko yang mungkin terjadi maka cara mengendalikan dampaknya adalah dengan memberikan pembayaran gaji sesuai dengan tanggal yang sudah ditetapkan | L36: 33
A37: 592 | B37: WADIR I-7 | C37: Peningkatan Kuantitas dan Kualitas Lulusan melalui Kegiatan Wisuda - WADIR I | D37: 3618671150 | E37: 2 | F37: 5 | G37: LOW | I37: Bentuk dukungan kepada lulusan dan menggeser status menjadi alumni | J37: Karena jumlah mahasiswa yang lulus di tahun berjalan tidak menentu mungkin akan kesulitan menyesuaikan dengan jadwal yang sudah direncanakan sehingga kegiatan Peningkatan Kualitas Lulusan melalui Kegaiatan Wisuda. - PEMBANTU DIREKTUR I tidak bisa dijalankan. | K37: melibatkan akademik prodi dan akademik pusat serta seluruh civitas untuk bertanggung jawab terhadap kelulusan | L37: 34 | M37: 3
A38: 603 | B38: WADIR II-15 | C38: PENYELENGGARAAN OPERASIONAL PERKANTORAN - WADIR II | D38: 3217922425 | E38: 2 | F38: 3 | G38: LOW | I38: Kepuasan Penyelenggaraan operasional perkantoran rendah | J38: Karena tidak adanya SOP yang jelas untuk setiap kegiatan operasional perkantoran mungkin jalannya kegiatan operasional perkantoran tidak terawasi dengan baik sehingga Penyelenggaraan Operasional Perkantoran tidak berjalan dengan tertib. | K38: Agar segera dibuatkan dan diterbitkan SOP yang sesuai sehingga semua berjalan dengan lancar | L38: 35 | M38: 4
A39: 617 | B39: WADIR II-54 | C39: Bantuan Beasiswa Mahasiswa | D39: 3162000000 | E39: 2 | F39: 4 | G39: LOW | I39: Kurangnya koordinasi antara pihak akademik, kemahasiswaan dan keuangan sehingga mengakibatkan terjadinya keterlambatan pembayaran dan adanya permasalahan kelebihan bayar | J39: Karena Tidak ada koordinasi yang bagus antara pihak akademik dan kemahasiswaan mungkin akan terjadi keterlambatan pembayaran dan adanya permasalahan kelebihan bayar karena keabsahannya | K39: Adanya kontrol dan koordinasi antara pihak akademik, kemahasiswaan dan keuangan akan mencegah adanya keterlambatan pembayaran dan adanya permasalahan kelebihan bayar | L39: 36
A40: 605 | B40: WADIR II-22 | C40: BELANJA PEGAWAI : Pembayaran Gaji Tendik Kontrak Non PPNPN | D40: 3070000000 | E40: 2 | F40: 5 | G40: LOW | I40: kepuasan layanan pembayaran honor Tendik Non PNS Satker rendah | J40: Karena Kurang tertib kinerja dari staff kepegawaian menyerahkan data kehadiran dan data dukung individu terbaru mungkin penyerahan/pemutahiran data dukung dalam sistem pembayaran honor Tendik Non-PNS menjadi terlambat sehingga Pembayarannya tidak tepat waktu. | K40: Agar tidak terlambat, dilakukan prosedur supervisi berkala/rutin dalam pemutakhiran basis data kepegawaian | L40: 37
A41: 607 | B41: WADIR II-35 | C41: Pembayaran Gaji Tendik Kontrak Non PPNPN | D41: 3070000000 | E41: 2 | F41: 5 | G41: LOW | I41: kepuasan layanan pembayaran honor Tendik Non PNS Satker rendah | J41: Karena Kurang tertib kinerja dari staff kepegawaian menyerahkan data kehadiran dan data dukung individu terbaru mungkin penyerahan/pemutahiran data dukung dalam sistem pembayaran honor Tendik Non-PNS menjadi terlambat sehingga Pembayarannya tidak tepat waktu. | K41: Agar tidak terlambat, dilakukan prosedur supervisi berkala/rutin dalam pemutakhiran basis data kepegawaian | L41: 38
A42: 505 | B42: PSDKU Kota Kediri-20 | C42: GAJI DAN TUNJANGAN TENAGA KEPENDIDIKAN NON PNS | D42: 1946143150 | E42: 2 | F42: 4 | G42: LOW | I42: 1. keterlambatan pembayaran gaji dan tunjangan tenaga kependidikan 2. Penurunan produktivitas kinerja tenaga kependidikan 3. Proses administrasi perkantoran dan penunjang akademik tidak berjalan dengan lancar | J42: Karena adanya keterlambatan pengajuan pembayaran gaji dan tunjangan tenaga kependidikan mungkin pembayaran gaji dan tunjangan tenaga kependidikan tertunda sehingga menyebabkan penurunan kinerja tenaga kependidikan | K42: Untuk mengatasi risiko yang mungkin terjadi maka cara mengendalikan dampaknya adalah dengan memberikan pembayaran gaji sesuai dengan tanggal yang sudah ditetapkan | L42: 39
A43: 511 | B43: PSDKU Kota Lumajang-5 | C43: Belanja Operasional Penunjang Layanan Pendidikan (HIBAH dan PNBP) | D43: 1761377200 | E43: 2 | F43: 5 | G43: LOW | I43: 1. Layanan Pendidikan Terganggu, Jika dana operasional tidak tersedia, berbagai layanan pendidikan seperti pemeliharaan fasilitas, pengadaan alat pendukung, dan kegiatan akademik bisa terhambat. 2. Menurunnya Kualitas Pendidikan dan Layanan, Tanpa anggaran yang cukup, institusi mungkin kesulitan memberikan layanan yang optimal kepada mahasiswa dan tenaga pendidik. 3. Terhambatnya Kegiatan Akademik dan Kemahasiswaan, Jika dana operasional mencakup kegiatan mahasiswa, maka berbagai program seperti seminar, pelatihan, dan kegiatan ekstrakurikuler bisa mengalami hambatan atau dibatalkan. 4. Risiko Ketidakpatuhan Terhadap Peraturan Keuangan, Jika belanja operasional tidak dilaksanakan sesuai dengan peraturan yang berlaku, bisa timbul masalah administrasi atau bahkan sanksi dari pihak terkait. | J43: Karena Tidak memiliki jumlah tim pelaksana yang memenuhi untuk mengatasi banyaknya penanganan pengajuan realisasi GU/TUP, Mungkin menyebabkan Tidak ada Pemetaan program Rencana Anggaran Biaya yang bersumber dari Hibah Pemerintah Kabupaten Lumajang, Sehingga kegiatan Belanja Operasional Penunjang Layanan Pendidikan (HIBAH dan PNBP) tidak dapat dilaksanakan. | K43: Melakukan Pembayaran Secara Rutin dan berkala sesuai SBM dan Kepatiuhan terhadapa aturan yang berlaku sesuai target capaian Unit Kerja, melakukan koordinasi dengan pihak terkait agar pencairan dana bisa dipercepat, melakukan perencanaan keuangan yang lebih matang, serta memastikan bahwa regulasi dan persyaratan administrasi terpenuhi agar belanja operasional dapat segera direalisasikan. | L43: 40
A44: 496 | B44: PSDKU Kota Kediri-5 | C44: BIAYA JASA KEAMANAN, CLEANING SERVICE DAN GARDENER - PSDKU Kota Kediri | D44: 1646400000 | E44: 2 | F44: 4 | G44: LOW | I44: 1. Gaji dan fasilitas tenaga outsourcing berubah setiap tahun 2. Kinerja pegawai outsourcing di bawah standard yang diharapkan institusi 3. Kenyamanan dan kemanan lingkungan kampus dan perkantoran tidak optimal 4. Memerlukan waktu untuk beradaptasi kembali antara instansi PSDKU Kediri dan karyawan outsourcing dengan peraturan vendor baru | J44: Karena sistem pengadaan tenaga outsourcing dengan sistem lelang setiap tahunnya sehingga mungkin gaji dan fasilitas yang diterima tenaga kerja outsourcing berubah - ubah sesuai dengan ketentuan vendor yang memenangkan lelang kontrak, sehingga jika terjadi penurunan gaji dan fasilitas menyebabkan turunnya kinerja tenaga kerja outsourcing | K44: Untuk mengatasi risiko yang mungkin terjadi maka cara mengendalikan dampaknya adalah dengan melakukan koordinasi dengan vendor pemenang lelang untuk memberikan upah sesuai yang berlaku dengan tidak merugikan vendor | L44: 41
A45: 553 | B45: UPA Bahasa-5 | C45: UJIAN TOEIC - MALA DAN IISMA 2025 - UPA BAHASA | D45: 1506265000 | E45: 2 | F45: 5 | G45: LOW | I45: 1. Kegiatan tidak terlaksana sehingga menyebabkan kerugian baik moril maupun materiil. | J45: Karena kurang adanya koordinasi dengan masing-masing jurusan baik di kampus utama maupun PSDKU terkait sosialisasi TOEIC untuk MALA, dan mungkin karena tidak ada sosialisasi terstruktur terkait TOEIC kepada MALA sehingga kegiatan ujian TOEIC MALA tidak berjalan. | K45: Untuk mengatasi resiko yang mungkin terjadi, maka cara mengendalikan dampaknya adalah: 1) melakukan koordinasi dengan semua jurusan baik di kampus utama maupun PSDKU; 2) memberikan sosialisasi mengenai ujian TOEIC dan memberikan kesempatan mahasiswa tingkat akhir mempersiapkan diri secara mandiri dengan menyediakan soal-soal latihan TOEIC dengan menggunakan platform seperti google classroom atau moodle. | L45: 42
A46: 615 | B46: WADIR II-52 | C46: TUNJANGAN TENDIK NON-ASN | D46: 1464000000 | E46: 2 | F46: 5 | G46: LOW | I46: kepuasan layanan pembayaran tunjuangan Tendik Non ASN satker rendah | J46: Karena kurang tertib kinerja dari Staf Kepegawaian menyerahkan data kehadiran dan data dukung individu terbaru mungkin penyerahan/pemutahiran data dukung tunjangan Tendik Non-ASN menjadi terlambat sehingga pembayaran tidak tepat waktu | K46: Agar tidak terlambat, dilakukan prosedur supervisi berkala/rutin dalam pemutahiran basis data kepegawaian | L46: 43
A47: 506 | B47: PSDKU Kota Kediri-21 | C47: GAJI DAN TUNJANGAN TENAGA PENDIDIK NON PNS | D47: 1292986606 | E47: 2 | F47: 4 | G47: LOW | I47: 1. keterlambatan pembayaran gaji dan tunjangan bagi tenaga pendidik 2. Penurunan produktivitas kinerja tenaga pendidik 3. Proses pelaksanaan tridharma perguruan tinggi tidak berjalan dengan lancar | J47: Karena adanya keterlambatan pengajuan pembayaran gaji dan tunjangan tenaga pendidik mungkin pembayaran gaji dan tunjangan tenaga pendidik tertunda sehingga menyebabkan penurunan kinerja tenaga dosen | K47: Untuk mengatasi risiko yang mungkin terjadi maka cara mengendalikan dampaknya adalah dengan memberikan pembayaran gaji sesuai dengan tanggal yang sudah ditetapkan | L47: 44
A48: 604 | B48: WADIR II-17 | C48: PENYUSUNAN DOKUMEN DAN LAPORAN SISTEM TATA KELOLA DAN KELEMBAGAAN - WADIR II | D48: 1289000000 | E48: 2 | F48: 4 | G48: LOW | I48: Dokumen/Laporan Sistem Tata Kelola dan Kelembagaan tidak tersusun dengan baik | J48: Karena kurang adanya kontrol kinerja dari pimpinan mungkin pengumpulan data dukung tidak berjalan dengan baik sehingga Penyusunan Dokumen/Laporan Sistem Tata Kelola dan Kelembagaan tidak terlaksana dengan baik. | K48: Adanya kontrol kinerja staf sehingga pengumpulan data dukung tidak terlambat dan dokumen bisa tersusun dengan tepat | L48: 45
A49: 601 | B49: WADIR II-13 | C49: PENGADAAAN KENDARAAN BERMOTOR | D49: 950000000 | E49: 2 | F49: 4 | G49: LOW | I49: Mendapatkan persetujuan usulan pemanfaatan saldo awal kepada dewan pengawas untuk pengadaan penggantian penghapusan kendaraan dinas tahun 2022. | J49: Karena kurangnya koordinasi antara perencanaan dan tim teknis untuk pengadaan kendaraan dinas konvensional (bukan kendaraan listrik), mungkin ijin pemanfaatan dana saldo awal oleh dewas belum mendapat persetujuan sehingga pengadaan kendaraan operasional tidak sesuai ketentuan. | K49: Kontrol kesiapan RAB, HPS dan vendor penyedia kendaraan dinas agar Pengadaan Kendaraan Dinas dapat segera terealisasi | L49: 46
A50: 598 | B50: WADIR II-5 | C50: BELANJA PEGAWAI : Dosen Luar Biasa (NIDN) | D50: 930000000 | E50: 2 | F50: 5 | G50: LOW | I50: kepuasan layanan pembayaran honor Pendidik Non-PNS rendah | J50: Karena Kurang tertib kinerja dari staff kepegawaian menyerahkan data kehadiran dan data dukung individu terbaru mungkin penyerahan/pemutahiran data dukung dalam sistem pembayaran honor oeprasional satker menjadi terlambat sehingga Pembayarannya tidak tepat waktu. | K50: Agar tidak terlambat, dilakukan prosedur supervisi berkala/rutin dalam pemutakhiran basis data kepegawaian | L50: 47
... A76: 634 | B76: WADIR IV-11 | C76: KERJA SAMA: Pengembangan Kerja Sama Dalam dan Luar Negeri - WADIR IV | D76: 299700000 | E76: 3 | F76: 2 | G76: LOW | I76: Pengembangan kerja sama dalam dan luar negeri mungkin tidak optimal | J76: Karena Keterbatasan sumberdaya Manusia dan Finansial mungkin kurangnya keterlibatan pihak terkait sehingga Pengembangan kerja sama dalam dan luar negeri mungkin tidak optimal | K76: 1) Memastikan dokumen program dan anggaran sesuai dengan pedoman yang berlaku; 2) melaksanakan sosialisaasi dalam penyusunan Dokumen perencanaan | L76: 73
A77: 126 | B77: PSDKU Kota Pamekasan-6 | C77: Belanja Jasa Penyedia Keamanan (Outsorcing) PSDKU Polinema Kabupaten Pamekasan | D77: 297360100 | E77: 4 | F77: 5 | G77: HIGH | I77: Aset negara dan kegiatan institusi tidak terjaga dengan baik | J77: Karena Tidak terdapatnya Penyedia jasa yang sesuai ketentuan untuk melaksanakan Pengadaan Jasa Keamanan di Daerah Pamekasan, mungkin menyebabkan Lamanya Penetapan/penunjukan penyedia untuk kontrak jasa keamanan , sehingga Tidak terealisasinya kegiatan / Terhambatnya Belanja Honorarium Satuan Petugas Keamanan (Outsorcing) PSDKU Pamekasan | K77: Melaksanakan tender jasa penyedia keamanan (outsorcing) sesuai waktu yang direncanakan
A78: 412 | B78: D-IV Sistem Kelistrikan-7 | C78: Pembelian Persedian BHP Penunjang Praktikum D-IV Sistem Kelistrikan | D78: 285248955 | E78: 2 | F78: 5 | G78: LOW | I78: Menurunnya jumlah BHP | J78: Karena Tidak adanya SDM yang dapat mencari BHP Praktikum dengan kandungan TKDN dan Menyusun HPS di Prodi DIII sistem kelistrikan mungkin Proses BHP Praktikum di Prodi DIII sistem kelistrikan menjadi Terlambat sehingga Tidak tersedia BHP Praktikum yang berkualitas untuk mahasiswa Prodi DIII sistem kelistrikan. | K78: untuk menyusun HPS Minta bantuan ke Tim Teknis Perumus HPS, untuk memenuhi TKDN mengikuti data base yang ada dan minimum 40 % , dan monitoring proses pengadaan
A79: 117 | B79: P3M-23 | C79: BANTUAN TATA KELOLA DAN AKREDITASI JURNAL - P3M | D79: 281092900 | E79: 5 | F79: 4 | G79: HIGH | I79: Peningkatan kualitas jurnal dan akreditasi jurnal polinema dapat terhambat Keterkaitan dengan ([IKU 2.3] Jumlah keluaran penelitian dan pengabdian kepada masyarakat yang berhasil mendapat rekognisi internasional atau diterapkan oleh masyarakat per jumlah dosen) | J79: KARENA pemahaman pengelola jurnal di Polinema kurang MUNGKIN terkait pemahaman mengenai tata kelola jurnal dan peningkatan kualitas jurnal yang ada di Polinema SEHINGGA proses akreditasi dan indexing jurnal yang ada di Polinema terhambat | K79: Memberikan pelatihan dan pendampingan kepada pengelola jurnal untuk perbaikan tata kelola dan pengajuan proses akreditasi jurnal pada Arjuna
A80: 149 | B80: UPA Percetakan dan Penerbitan-7 | C80: PROGRAM PENERBITAN BUKU AJAR DAN REFERENSI - UPA Percetakan dan Penerbitan | D80: 276265000 | E80: 4 | F80: 4 | G80: HIGH | I80: Tidak dapat memenuhi target penerbitan buku ajar ber-ISBN dengan jumlah dan waktu yang telah ditentukan. | J80: Karena tidak ada percetakan yang dapat mencetak buku dalam jumlah besar dan waktu yang singkat, mungkin jumlah penulis yang memiliki karya yang memenuhi syarat rendah, sehingga jumlah buku yang ditargetkan tidak dapat diterbitkan sesuai rencana. | K80: Pada kegiatan PROGRAM PENERBITAN BUKU AJAR, ada beberapa penyebab masalah (karena tidak ada percetakan yang dapat mencetak buku dalam jumlah besar dan waktu yang singkat, mungkin jumlah penulis yang memiliki karya yang memenuhi syarat rendah, dan penulis tidak tahu cara menulis buku yang baik), maka alternatif solusinya: 1. Mencari informasi tentang penyedia jasa percetakan yang dapat mencetak buku dalam jumlah besar dan waktu yang singkat. 2. Melakukan sosialisasi lebih awal kepada para penulis (dosen Polinema). 3. Memberi pelatihan bagi calon penulis (dosen Polinema). 4. Memberi pelatihan calon penyunting
A81: 314 | B81: WADIR III-17 | C81: Peningkatan Pemberdayaan Unit Kegiatan Mahasiswa (UKM) - WADIR III - WADIR III | D81: 269100000 | E81: 4 | F81: 3 | G81: MIDDLE | I81: 1. Pelaporan keuangan yang menyulitkan bagian keuangan di akhir tahun 2. Adanya kegiatan yang tidak terlaksana | J81: KARENA Periode kepengurusan Unit Kegiatan Mahasiswa (UKM) dimulai pada triwulan kedua, MUNGKIN Pelaksanaan program kerja Unit Kegiatan Mahasiswa (UKM) pada umumnya diselenggarakan pada akhir tahun anggaran, SEHINGGA Program kerja Peningkatan Peningkatan Pemberdayaan Unit Kegiatan Mahasiswa (UKM) tidak dapat berjalan dengan baik | K81: KARENA pelaksanaan program kerja organisasi kemahasiswaan pada umumnya diselenggarakan pada akhir tahun anggaran, MAKA ALTERNATIF SOLUSINYA ADALAH: 1. Mengarahkan agar program kerja organisasi kemahasiswaan pelaksanaannya disebar ke awal dan pertengahan tahun. 2. Program kerja yang tidak dapat dilaksanakan selain di akhir tahun, diminta untuk tidak menggunakan dana dari anggaran bidang 3.
A82: 497 | B82: PSDKU Kota Kediri-7 | C82: BIAYA PERJALANAN DINAS | D82: 268425000 | E82: 2 | F82: 4 | G82: LOW | I82: perjalanan dinas tidak mendapatkan hasil sesuai dengan tujuan perjalanan dinas | J82: karena terlalu banyak perjalanan dinas yang dilakukan karyawan mungkin produktivitas absensi kehadiran karyawan di kantor kurang optimal sehingga pekerjaan di kantor terbengkalai sehingga tujuan dari perjalanan dinas tidak tercapai optimal | K82: Untuk mengatasi resiko yang mungkin terjadi maka cara mengendalikan dampaknya adalah dengan cara Memberikan batasan perjalanan dinas kepada pegawai berdasarkan skala prioritas.
A83: 328 | B83: BPKU-13 | C83: Publikasi di Media Online dan Bantuan Transportasi Liputan Wartawan | D83: 267300000 | E83: 2 | F83: 3 | G83: LOW | I83: Promosi untuk meningkatkan jumlah pendaftar mahasiswa baru tidak berjalan dengan baik | J83: Karena tidak ada publikasi di media online mungkin hubungan dengan pihak stakholder dan data yang disajikan sebagai bahan publikasi belum ada sehingga promosi untuk meningkatkan jumlah pendaftar mahasiswa baru tidak berjalan dengan baik | K83: Melaksanakan koordinasi dengan Jurusan, Prodi dan Unit terkait kegiatan yang dapat dipublikasikan Memaksimalkan penyampaian informasi melalui media sosial resmi POLINEMA, website, dan WA Center Humas
A84: 510 | B84: PSDKU Kota Lumajang-4 | C84: Belanja Jasa Kebersihan Kampus PSDKU Lumajang | D84: 264000000 | E84: 3 | F84: 3 | G84: LOW | I84: "Dampak yang terjadi apabila belanja jasa kebersihan kampus PSDKU Lumajang tidak dapat dilaksanakan: 1. Lingkungan kampus bisa menjadi kotor dan tidak terawat. Ini dapat mengganggu kenyamanan mahasiswa, dosen, dan staf yang berada di kampus. Ruang kelas, toilet, koridor, dan area umum yang tidak bersih bisa menurunkan kualitas belajar dan layanan operasional kampus. 2. Lingkungan yang kotor dan tidak terawat dapat meningkatkan risiko penyebaran penyakit, seperti flu, infeksi saluran pernapasan, atau penyakit kulit. Debu dan sampah yang menumpuk juga bisa menyebabkan alergi atau masalah kesehatan lainnya. 3. Kondisi kampus yang kotor atau tidak terawat dapat merusak citra kampus di mata calon mahasiswa, orang tua, dan pihak luar. Kampus yang terlihat kotor bisa dianggap tidak profesional atau tidak peduli terhadap kesejahteraan mahasiswa, dosen dan staf. 4. Lingkungan yang tidak bersih bisa menyebabkan ketidaknyamanan selama kegiatan perkuliahan atau kegiatan kampus lainnya. Mahasiswa dan dosen mungkin merasa terganggu dengan bau tidak sedap, sampah yang berserakan, atau fasilitas yang tidak terawat." | J84: Karena keterbatasan anggaran dan perubahan regulasi dari Kemensaintek terkait penggunaan jasa kebersihan dari pihak ketiga terjadi. Mungkin dapat mengubah kebijakan atau prosedur yang telah direncanakan instansi terkait jasa kebersihan kampus PSDKU Lumajang, salah satunya adalah meniadakan jasa kebersihan kampus PSDKU Lumajang dari pihak ketiga. Sehingga belanja jasa kebersihan kampus PSDKU Lumajang tidak dapat dilaksanakan. | K84: Perlu adanya sumber daya manusia yang menangani khusus pengarsipan dan yang mengerti manajemen arsip , sangat diperlukan penyediaan arsip yang aman dan penyimpan arsip Pembayaran Secara Rutin dan berkala sesuai SBM dan Kepatiuhan terhadap aturan yang berlaku sesuai target capaian Unit Kerja
A85: 163 | B85: WADIR II-23 | C85: PENGADAAN ALAT PENGOLAH DATA DAN INFORMASI PENDUKUNG PERKANTORAN | D85: 249956000 | E85: 4 | F85: 4 | G85: HIGH | I85: Melakukan analisis kebutuhan pengembangan sistem dengan personil yang mempunyai kualifikasi yang memadahi | J85: Karena kurangnya pengembangan staff yang cukup untuk kepentingan kajian aplikasi yang tepat mungkin analisis Sistem dan infrastruktur tidak direncanakan secara baik sehingga Pengadaan Alat pengolah data dan informasi pendukung perkantoran tidak berfungsi secara efektif. | K85: membuat rekapan hasil analis kebutuhan dan membuat daftar pekerjaan yang disesuaikan dengan tenaga yang kualified dan kompeten agar pelaksanaan Pengadaan Alat Pengolah Data dan Informasi Pendukung Perkantoran dapat berjalan dengan efektif dan efisien
A86: 152 | B86: WADIR I-4 | C86: BEASISWA MAHASISWA S2, S3, KELAS INTERNASIONAL DAN BEASISWA PII LEVEL ADVANCE - WADIR I | D86: 234000000 | E86: 4 | F86: 5 | G86: HIGH | I86: program profesi PII tidak dapat didirikan di Polinema | J86: Karena keterbatasan SDM dalam penyusunan borang pendirian PII mungkin tim penyusun yang menyelesaikan tidak bisa menyelesaikan tepat waktu dan terdapat syarat yang belum terpenuhi sehingga pendirian program profesi PII tidak dapat dilakukan dengan baik | K86: membentuk tim ad hoc yang solid untuk pendirian program profesi PII
A87: 705 | B87: WADIR I-5 | C87: Internasionalisasi mahasiswa melalui program akademik unggulan - WADIR I | D87: 230275000 | E87: 1 | F87: 5 | G87: VERY LOW | I87: Bidang 1 melakukan upaya dalam rangka internasionalisasi kampus sesuai dengan milestone institusi | J87: Karena rendahnya minat mahasiswa mengikuti student mobility, MUNGKIN tingginya biaya program akademik student mobility ke luar negeri, sehingga kegiatan Internasionalisasi mahasiswa melalui program akademik unggulan - PEMBANTU DIREKTUR I tidak bisa dijalankan. | K87: komunikasi yang baik antara polinema dengan penyelenggara
A88: 178 | B88: WADIR III-14 | C88: Penyelenggaraan INHOUSE RECRUITMENT dan Campus-Company Fit and Hiring (JOB FAIR) - WADIR III | D88: 228475000 | E88: 4 | F88: 4 | G88: HIGH | I88: 1. Kurangnya peserta (mahasiswa atau alumni) yang menghadiri Campus-Company Fit and Hiring (JOB FAIR). 2. Kurang maksimalnya jumlah mahasiswa atau alumni yang diterima bekerja melalui Campus-Company Fit and Hiring (JOB FAIR) | J88: KARENA kurangnya sosialisasi Campus-Company Fit and Hiring (JOB FAIR) dan kurangnya kesiapan mahasiswa atau alumni dalam mengikuti rekrutmen, MUNGKIN program kerja penyelenggaraan Campus HIring tidak dapat berjalan dengan maksimal SEHINGGA mahasiswa atau alumni kurang menerima manfaat Campus-Company Fit and Hiring (JOB FAIR) untuk memperoleh pekerjaan. | K88: "KARENA kurangnya sosialisasi Campus-Company Fit and Hiring (JOB FAIR) dan kurangnya kesiapan mahasiswa atau alumni dalam mengikuti rekrutmen, MAKA ALTERNATIF SOLUSINYA ADALAH: 1. Melakukan sosialisasi Campus-Company Fit and Hiring (JOB FAIR) secara intensif kepada mahasiswa tingkat akhir dan alumni 2. Memberikan pembekalan kesiapan rekrutmen kepada mahasiswa tingkat akhir dan alumni"
... A306: 137 | B306: UPA Pengembangan Karir dan Kewirausahaan-5 | C306: Magang Kewirausahaan - UPA Pengembangan Karir dan Kewirausahaan | D306: 40000000 | E306: 4 | F306: 4 | G306: HIGH | I306: 1. peserta lebih memilih MBKM 2. peserta sedikit | J306: karena adanya program MBKM dimana peserta berbarengan melaksanakan kegiatan MBKM dari jurusan, sehingga peserta lebih memilih melaksanakan MBKM lebih dulu dan pelaksanaan magang kewirausahaan terhambat | K306: mengupayakan kegiatan magang kewirausahaan mendapatkan dukungan dari institusi dan jurusan untuk mendapatkan konversi mata kuliah dan menjadi MBKM internal, sehingga pelaksanaan magang bisa dilaksanakan dengan baik.
A307: 182 | B307: BPKU-4 | C307: Digitalisasi Arsip Surat Keputusan dan Peraturan DIrektur | D307: 40000000 | E307: 3 | F307: 4 | G307: MIDDLE
A308: 520 | B308: PSDKU Kota Lumajang-21 | C308: Pengadaan dan Instalasi CCTV di Lingkungan Kampus PSDKU Lumajang (HIBAH) | D308: 40000000 | E308: 2 | F308: 4 | G308: LOW | I308: Karena dapat memberikan rasa aman dan nyaman bagi semua yang ada didalam lingkungan kampus karena dengan adanya CCTV dapat membantu mencegah tindakan kejahatan seperti pencurian dan vandalisme dengan memberikan pengawasan,selain itu dalam kasus insiden atau kejahatan rekaman CCTV dapat menjadi bukti yang kuat. | J308: Karena Kendala Administrasi dan Regulasi Proses perencanaan dan pengadaan yang tidak sesuai dengan prosedur atau regulasi, Mungkin gagalnya proses pengadaan seperti penawaran yang tidak sesuai dengan standar atau harga yang jauh di atas anggaran, Sehingga Pengadaan dan Instalasi CCTV di Lingkungan Kampus PSDKU Lumajang tidak dapat dilaksanakan. | K308: Melaksanakan Kegiatan Pengadaan dan Instalasi CCTV di Kampus PSDKU Lumajang Sesuai Waktu Yang Sudah Di Rencanakan
A309: 446 | B309: DEWAS-2 | C309: Penyusunan Laporan Dewan Pengawas Semester I Tahun 2025 | D309: 39919000 | E309: 2 | F309: 5 | G309: LOW | I309: Keterlambatan Penyajian Laporan Dewas Tersebut Dapat Menyebabkan Keterlambatan Penyajian Informasi Tentang Penilaian Kinerja Akademik dan Non-Akademik yang Digunakan sebagai Dasar untuk Memberikan Rekomendasi Perbaikan dan Peningkatan Kualitas yang Harus Dilakukan oleh Direktur dan Jajarannya. | J309: Karena Keterlambatan Sumber Data dari Unit Kerja, Akademik, dan Non Akdemik yang Belum Siap, Mungkin Penyajian Laporan Dewas Mengenai Informasi Tentang Penilaian Kinerja Akademik dan Non-Akademik yang Digunakan Sebagai Dasar untuk Memberikan Rekomendasi Tersebut Menjadi Terlambat, Sehingga Penyampaian dan Pelaporan untuk Laporan Dewas ke Kementerian Keuangan dalam Aplikasi BIOS G2 (BLU Integrated Online System) Akan Mundur dari Jadwal dan Batas Waktu yang Sudah Ditentukan | K309: Pengumpulan Data dari Seluruh Unit Kerja (Akademik dan Non Akademik) Harus Dilakukan Secara Lebih Dini
A310: 447 | B310: DEWAS-3 | C310: Penyusunan Laporan Dewan Pengawas Semester II Tahun 2025 | D310: 39919000 | E310: 2 | F310: 4 | G310: LOW | I310: Keterlambatan Penyajian Laporan Dewas Tersebut Dapat Menyebabkan Keterlambatan Penyajian Informasi Tentang Penilaian Kinerja Akademik dan Non-Akademik yang Digunakan sebagai Dasar untuk Memberikan Rekomendasi Perbaikan dan Peningkatan Kualitas yang Harus Dilakukan oleh Direktur dan Jajarannya. | J310: Karena Keterlambatan Sumber Data dari Unit Kerja, Akademik, dan Non Akdemik yang Belum Siap, Mungkin Penyajian Laporan Dewas Mengenai Informasi Tentang Penilaian Kinerja Akademik dan Non-Akademik yang Digunakan Sebagai Dasar untuk Memberikan Rekomendasi Tersebut Menjadi Terlambat, Sehingga Penyampaian dan Pelaporan untuk Laporan Dewas ke Kementerian Keuangan dalam Aplikasi BIOS G2 (BLU Integrated Online System) Akan Mundur dari Jadwal dan Batas Waktu yang Sudah Ditentukan | K310: Pengumpulan Data dari Seluruh Unit Kerja (Akademik dan Non Akademik) Harus Dilakukan Secara Lebih Dini
A311: 657 | B311: D-III Teknik Mesin PSDKU Kediri-1 | C311: BENCHMARKING PROGRAM STUDI SEJENIS GUNA PENYELARASAN KURIKULUM DAN TATA KELOLA PRODI | D311: 39669000 | E311: 1 | F311: 3 | G311: VERY LOW | I311: 1) Kegiatan tidak terlaksana sehingga menyebabkan kerugian baik moril maupun materiil. 2) Tidak terlaksananya Kegiatan Benchmarking Program Studi D-3 Teknik Mesin Kampus Kediri, 3) Kegiatan Benchmarking tidak terlaksana dengan baik dan mutu/kualitas Prodi. tidak tercapai. | J311: Karena Tidak banyak Program studi yang sejenis yang berkerjasama dengan Prodi terkait, Mungkin pelaksanaan Kegiatan Benchmarking D3 Teknik Mesin Kampus Kediri - Tidak dapat berjalan dengan lancar, Sehingga dapat menghambat proses penyelarasan kurikulum Prodi D3 Teknik Mesin Kampus Kediri. | K311: Untuk mengatasi resiko yang mungkin terjadi, maka cara mengendalikan dampaknya adalah: 1) merencanakan kegiatan Benchmarking jauh jauh hari lebih paa Prodi yang akan dituju; 2) Membuat database yang relevan/sesuai dengan kebutuhan terkait DUDI yang ber MOU dengan Polinema yang menjadi tujuan Benchmarking ; 3) Melaksanakan Benchmarking serta kerjasama yang berkesinambunan supaya prodi. semakin berkualitas dan dapat memberikan pelayanan Prima melalui Kuirkulum prodi.; 4)Menyesuaikan kurikulum dengan kebutuhan DUDI dan maukan Prodi sejenis sehingga Prodi dapat Sustainable dan memiliki lulusan yang kompeten dan unggul;
A312: 73 | B312: Jurusan Administrasi Niaga-2 | C312: Peningkatan Kualitas Operasional Perkantoran - Jurusan Administrasi Niaga | D312: 39500000 | E312: 4 | F312: 5 | G312: HIGH | I312: Alat perkantoran tidak dapat digunakan dalam pelayanan karena alat rusak. | J312: Karena tidak ada cukup dana untuk melakukan perawatan alat perkantoran secara reguler, maka perawatan tidak dilakukan sehingga alat perkantoran mengalami kerusakan dan pelayan pembelajaran di jurusan tidak dapat berjalan dengan baik. | K312: Menyusun jadwal perawatan alat perkantoran secara regular dan menyiapkan dana yang cukup.
A313: 402 | B313: D-IV Manajemen Rekayasa Konstruksi-1 | C313: MONEV AKHIR PBM - D-IV Manajemen Rekayasa Konstruksi | D313: 38395000 | E313: 2 | F313: 4 | G313: LOW | I313: Tidak terlaksananya Monev Akhir PBM akan berdampak : 1. Kurangnya pengukuran kemajuan mahasiswa, 2. Kurangnya identifikasi kekurangan mahasiswa&dosen, 3. Kurangnya perbaikan proses PBM | J313: Karena tidak adanya koordinasi untuk menyusun panduan monitoring dan evaluasi Akhir proses pembelajaran mungkin tidak ada panduan dalam melakukan monitoring dan evaluasi Akhir proses pembelajaran sehingga tidak terdapatnya monitoring dan evaluasi Akhir Proses Pembelajaran | K313: "1. Membuat tim untuk membentuk SOP 2. Membuat SOP 3. Monitoring dan evaluasi Akhir Proses Pembelajaran dengan pengawasan dari KPS D-IV Manajemen Rekayasa Konstruksi"
A314: 30 | B314: D-III Administrasi Bisnis-3 | C314: Penguatan Kerjasama Mitra Luar Negeri dalam Pelaksanaan Tri Dharma Perguruan Tinggi - D-III Administrasi Bisnis | D314: 37675000 | E314: 4 | F314: 4 | G314: HIGH | I314: Kerjasama Mitra Luar Negeri dalam Pelaksanaan Tri Dharma Perguruan Tinggi tidak berjalan dengan maksimal dan berpengaruh kepada Akreditasi | J314: KARENA Tidak maksimalnya Kerjasama dengan Mitra Luar Negeri dalam Pelaksanaan Tri Dharma Perguruan Tinggi , MUNGKIN Tidak ada upaya peningkatan Kerjasama dan implementasi Kerjasama dengan mitra luar negeri, SEHINGGA Kerjasama Mitra Luar Negeri dalam Pelaksanaan Tri Dharma Perguruan Tinggi belum maksimal | K314: Untuk mengatasi resiko yang mungkin terjadi, maka cara mengendalikan dampaknya adalah: 1). Membuat Kerjsama yang inten dengan mitra luar Negeri yang sejenis. 2). Melakukan implementasi kerjasama dalam bentuk kegiatan bersama
A315: 211 | B315: D-IV Bahasa Inggris untuk KomBis & Profesional-10 | C315: PENYELENGGARAAN INTERNATIONAL CONFERENCE ICALCOM 2025 - D-IV Bahasa Inggris untuk KomBis & Profesional - D-IV Bahasa Inggris untuk KomBis & Profesional - D-IV Bahasa Inggris untuk KomBis & Profesional | D315: 37625000 | E315: 4 | F315: 3 | G315: MIDDLE | I315: - Keterbatasan narasumber dengan kepakaran yang sesuai - Kendala komunikasi dan ketepatan waktu pengumpulan artikel dari peserta seminar - Kendala penyesuaian waktu seminar dengan perbedaan zona waktu peserta dan pemateri | J315: Karena keterbatasan SDM dengan kepakaran tertentu yang sesuai dengan tema seminar dan berada di zona waktu yang sama, mungkin narasumber yang dapat hadir secara offline tidak dapat ditemukan, sehingga kegiatan seminar ini tidak dapat terlaksana berdasarkan rencana. | K315: Membuat pemetaan narasumber/pemateri dengan kepakaran yang sesuai dengan tema besar seminar internasional. Mengundang dan berkolaborasi dengan pakar baik dari dalam negeri maupun luar negeri. Melakukan penelitian bersama dengan pakar bahasa. Melakukan pendekatan komunikasi dengan baik.
A316: 77 | B316: Jurusan Akuntansi-14 | C316: PENGADAAN MEBEULAIR DAN PERALATAN MULTIMEDIA UNTUK JURUSAN AKUNTANSI | D316: 37500000 | E316: 4 | F316: 5 | G316: HIGH | I316: Terhambatnya proses pembelajaran | J316: Karena keterbatasan peralatan yang sesuai dengan TKDN mungkin penyusunan BA HPS akan terhambat sehingga proses pengadaan peralatan jurusan akuntansi tidak berjalan. | K316: Melakukan survey secara menyeluruh, memonitoring pengadaan peralatan dan meubelair di ULP
A317: 303 | B317: UPA TIK-4 | C317: Pelatihan Pengelolaan Website Jurusan - UPA TIK | D317: 37500000 | E317: 3 | F317: 4 | G317: MIDDLE | I317: Konten dan keamanan website jarang update | J317: Perbedaan platform website di unit kerja dan pengelola yang sering berganti-ganti | K317: Penyamaan template dan platform mempermudah pengelolaan website
A318: 237 | B318: DEWAS-1 | C318: Penyempurnaan dan Penguatan SOP Aspek Tata Kelola Dewas - DEWAS | D318: 37471000 | E318: 3 | F318: 4 | G318: MIDDLE | I318: Keterlambatan Penyajian Laporan Dewas Tersebut Dapat Menyebabkan Keterlambatan Penyajian Informasi Tentang Penilaian Kinerja Akademik dan Non-Akademik yang Digunakan sebagai Dasar untuk Memberikan Rekomendasi Perbaikan dan Peningkatan Kualitas yang Harus Dilakukan oleh Direktur dan Jajarannya | J318: Karena Keterlambatan Sumber Data dari Unit Kerja, Akademik, dan Non Akdemik yang Belum Siap, Mungkin Penyajian Laporan Dewas Mengenai Informasi Tentang Penilaian Kinerja Akademik dan Non-Akademik yang Digunakan Sebagai Dasar untuk Memberikan Rekomendasi Tersebut Menjadi Terlambat, Sehingga Penyampaian dan Pelaporan untuk Laporan Dewas ke Kementerian Keuangan dalam Aplikasi BIOS G2 (BLU Integrated Online System) Akan Mundur dari Jadwal dan Batas Waktu yang Sudah Ditentukan | K318: Pengumpulan Data dari Seluruh Unit Kerja (Akademik dan Non Akademik) Harus Dilakukan Secara Lebih Dini
A319: 352 | B319: D-III Manajemen Informatika PSDKU Kediri-1 | C319: Benchmarking Program Studi - D-III Manajemen Informatika PSDKU Kediri | D319: 36975000 | E319: 2 | F319: 3 | G319: LOW | I319: 1. Kerjasama dengan industri atau PT lain gagal dibuat 2. Program untuk mahasiswa gagal diinisiasi | J319: KARENA komunikasi antara Prodi dengan industri dan PT lainnya kurang, MUNGKIN tidak tercapainya kesepakatan antara Prodi dengan Industri dan PT lainnya, SEHINGGA kegiatan Benchmarking Prodi D3 Manajemen Informatika Kampus Kediri tidak bisa dilaksanakan. | K319: 1. Memberikan pelatihan terhadap SDM dalam bernegosiasi 2. Memberikan strategi agar industri dan PT lain menerima penawaran negosiasi
... A419: 81 | B419: Jurusan Teknik Elektro-9 | C419: Pengembangan Apilkasi Digitalisasi dan Publikasi Peralatan Laboratorium di Jurusan Teknik Elektro | D419: 22665000 | E419: 5 | F419: 4 | G419: HIGH | I419: tidak adanya database atau narasumber, sehingga pengenalan atau kerjasama tentang Workshop Digitalisasi dan Publikasi Peralatan Laboratorium di Jurusan Teknik Elektro tidak berjalan | J419: Karena tidak adanya database narasumber/industri untuk mendukung kegiatan Workshop Digitalisasi dan Publikasi Peralatan Laboratorium di Jurusan Teknik Elektrodengan tema yang di tentukani mungkin kurangnya informasi untuk menyusun narasumber/industri yang relevan sehingga sehingga kegiatan tidak berjalan. | K419: Dengan membentuk TIM untuk membuat Digitalisasi dan Publikasi Peralatan Laboratorium di Jurusan Teknik Elektro yang akan di hasilkan atau di kenalkan ke khalayak umum.
A420: 694 | B420: S-2 Teknik Elektro-1 | C420: Implementasi Kerjasama Industri dengan PT Techno Triireka - S-2 Teknik Elektro - S-2 Teknik Elektro | D420: 22608000 | E420: 1 | F420: 4 | G420: VERY LOW | I420: Tidak adanya evaluasi proses belajar mengajar sehingga kekurangan dapat terulang di seriap tahun; Proses layanan pembelajaran kurang maksimal | J420: Karena tidak memiliki database PT yang sesuai untuk dilaksanakan kerjasama, mungkin tidak MoU/SPK dengan PT yang sesuai untuk dilaksanakan kerjasama, sehingga tidak adanya Inisiasi kerjasama dengan PT lain
A421: 97 | B421: P2MPP-15 | C421: PENYEMPURNAAN PEDOMAN MBKM BERDASARKAN PERMENDIKBUD 53 TAHUN 2023 | D421: 22593000 | E421: 4 | F421: 4 | G421: HIGH | I421: kualitas penyelenggaraan MBKM tidak sama antara prodi | J421: Karena belum adanya SDM sebagai penyusun pedoman pelaksanaan MBKM, mungkin tidak ada yang bertanggung jawab menyusun pedoman tersebut, sehingga kegiatanpenyusunan pedoman MBKM tidak terlaksana dengan baik | K421: Membentuk tim penyusun pedoman MBKM sesuai dengan kebutuhan
A422: 27 | B422: D-III Teknik Telekomunikasi-6 | C422: Pendampingan Mahasiswa Berkompetisi dan Berprestasi - D-III Teknik Telekomunikasi | D422: 22190700 | E422: 4 | F422: 5 | G422: HIGH | I422: menurunya persentase mahasiswa yang merahih prestasi | J422: Karena Tidak ada SDM untuk koordinasi info berkala terkait lomba kepada mahasiswa mungkin minat mahasiswa untuk ikut serta lomba di tingkat nasional menjadi berkurang sehingga Tidak terdapatnya Peningkatan kualitas mahasiswa melalui keikutsertaan dalam lomba | K422: Memberikan informasi-informasi dan pemndampingan ke mahasiswa berkaitan dengan lomba-lomba
A423: 534 | B423: S-2 Rekayasa Teknologi Informasi-2 | C423: Sinkronisasi Dokumen Kurikulum dengan Capaian - S-2 Rekayasa Teknologi Informasi - S-2 Rekayasa Teknologi Informasi | D423: 22100000 | E423: 2 | F423: 4 | G423: LOW | I423: Penyusunan LKPS dan persiapan Akreditasi S2 MRTI menjadi terhambat. | J423: Karena adanya kekurangan data/sumber data yang dikumpulkan, mungkin data yang disampaikan tidak akurat/up-to-date, sehingga penyusunan LKPS dan persiapan Akreditasi menjadi terhambat. | K423: 1. Memastikan bahwa petugas/tim yang menangani penyusunan LKPS dan persiapan Akreditasi S2 dapat mengumpulkan data sejak awal secara bertahap dan sistematis 2. Memastikan data yang dikumpulkan sudah data terbaru/up to date
A424: 540 | B424: S-2 Teknik Elektro-3 | C424: Workshop Rekonstruksi Kurikulum dan Pembuatan SOP - S-2 Teknik Elektro | D424: 22000000 | E424: 2 | F424: 3 | G424: LOW | I424: tidak adanya Prodi yang telah memiliki kurikulum berbasis DUDI yang telah disusun dan diimplementasikan di kampus | J424: Karena tidak ada acuan (SOP) untuk menyusun Kurikulum, Silabus Berbasis DUDI mungkin tidak ada SDM untuk menyusun Kurikulum, Silabus Berbasis DUDI sehingga Tidak tersedianya Kurikulum, Silabus dan penyusunan kurikulum berbasis DUDI | K424: melakukan workshop serta pendampingan pembuatan kurikulum yang sesuai dengan DUDI
A425: 4 | B425: D-IV Manajemen Pemasaran-6 | C425: Peningkatan Kerjasama Luar Negeri Prodi D-IV Manajemen Pemasaran | D425: 21845000 | E425: 5 | F425: 5 | G425: EXTREME | I425: 1. Tidak mempunyai kerjasama dengan mitra luar negeri; 2. Peningkatan daya saing global tidak terwujud. | J425: Karena terbatasnya jejaring luar negeri dalam mendukung pembelajaran dan pengembangan internasional, mungkin kurangnya pendekatan kepada mitra luar negeri, sehingga Peningkatan kerjasama luar negeri Prodi D-IV Manajemen Pemasaran tidak berjalan | K425: 1. Melakukan inisiasi kerjasama dengan PT luar negeri. 2. Melakukan perencanaan kegiatan yang mendukung kegiatan kerjasama luar negeri.
A426: 136 | B426: UPA Pengembangan Karir dan Kewirausahaan-1 | C426: Bootcamp Kewirausahaan - UPA Pengembangan Karir dan Kewirausahaan | D426: 21820000 | E426: 4 | F426: 5 | G426: HIGH | I426: program pendampingan kewirausahaan merupakan rangkaian kegiatan dari beberapa aktivitas program kewirausahaan yang harus dilaksanakan secara berurutan dan menyambung. sehingga jika terjadi keterlambatan pada pencairan modal usaha maka akan terjadi kemunduran jadwal pelaksanaan boothcamp ini. Karena kegiatan ini tidak bisa dilaksanakan jika kegiatan PMW belum berjalan. maka pelaksanaan jadwal kegiatan harus sesuai dengan yang dijadwalkan. | J426: Karena terjadi kemunduran pencairan modal usaha pada kegiatan PMW ( dari kegiatan sebelumnya) sehingga akan berdampak mundurnya jawal kegiatan boothcamp ini. | K426: 1. Ketepatan waktu dan jadwal pelaksanaan kegiatan semua program kewirausahaan. 2. memastikan pencairan bantuan modal usaha pada kegiatan PMW dibantu oleh bagian keuangan bisa dilaksanakan tepat waktu. 3. melakukan koordinasi secara efektif dengan tim kerja, koordinasi dengan jurusan, dan koordinasi dengan bagian keuangan.
A427: 398 | B427: D-IV Keuangan PSDKU Kediri-7 | C427: "Forum Group Discussion" tentang Penyusunan Bahan Ajar Berbasis Kegiatan MBKM Bidang Keuangan Di D-IV Keuangan PSDKU Kediri | D427: 21700089 | E427: 2 | F427: 5 | G427: LOW | I427: Kegiatan FGD tentang Implementasi MBKM tidak berjalan tidak berjalan. | J427: Karena kurangnya sosialisasi mengenai MBKM bagi tenaga pendidik maupun tenaga kependidikan di Prodi D-IV Keuangan Polinema Kampus Kediri, mungkin menyebabkan kurangnya ketersediaan SDM yang berwawasan tentang MBKM dan pengimplementasiannya secara tepat, sehingga FGD tentang Implementasi MBKM tidak berjalan | K427: Untuk mengatasi resiko yang mungkin terjadi, maka cara mengendalikan dampaknya adalah: 1) Membuat forum diskusi informal dengan internal Polinema atau pejabat yang terkait implementasi kurikulum MBKM/menugaskan SDM untuk studi banding dengan politeknik sejenis atau universitas lain dalam menjalankan kuriulum OBE MBKM.
A428: 376 | B428: D-III Teknologi Pertambangan-1 | C428: Pelaksanaan Praktikum Matakuliah kebumian Mahasiswa Tambang diluar Kampus - D-III Teknologi Pertambangan | D428: 21600000 | E428: 2 | F428: 4 | G428: LOW | I428: Tidak terlaksananya Pelaksanaan Praktikum Mata kuliah Kebumian Mahasiswa Tambang diluar Kampus akan berdampak : 1. Tidak ada MoU/PKS dengan mitra industri, 2. Mengurangi peluang mahasiswa dalam mendapatkan tempat magang industri, 3. Mengurangi peluang mahasiswa dalam mendapatkan tempat bekerja | J428: Karena Tidak ada Koordinasi dengan Industri mungkin tidak ada Pemetaan Industri Sasaran yang sesuai untuk Orientasi Lapangan sehingga kurang maksimalnya kunjungan Monitoring ke lokasi industri | K428: 1. Membuat database industri sasaran untuk Orientasi Lapangan sehingga dapat merata dan optimal 2. Penugasan koordinator lapangan untuk pemetaan industri sasaran 3. Melakukan kunjungan dan monitoring ke lokasi industri
A429: 663 | B429: D-IV Jaringan Telekomunikasi Digital-1 | C429: Kunjungan Industri Dalam Rangka Monitoring Magang Mahasiswa | D429: 21550000 | E429: 1 | F429: 3 | G429: VERY LOW | I429: Program studi tidak mendapat informasi mengenai perkembangan teknologi terkini yang dipelajari mahasiswa di industri | J429: Karena kurangnya komunikasi dan koordinasi dengan industri tempat pelaksanaan PKL/magang, mungkin tidak tersedianya database industri sasaran yang sesuai dengan profil lulusan dan berpotensi menghasilkan dokumen kerjasama MoU/SPK sehingga kurang maksimalnya kunjungan ke industri untuk menghasilkan MoU dan SPK | K429: Menyusun database lengkap tentang mitra/industri yang digunakan sebagai lokasi magang mahasiswa dan menjajagi kerjasama lebih jauh
A430: 438 | B430: D-IV Teknik Otomotif Elektronik-4 | C430: Penguatan Pembelajaran Berbasis Proyek (PBL) & Case Method (CM) yang terintegrasi dengan TEFA (Teaching Factory)- DIV-Teknik Otomotif Elektronik - D-IV Teknik Otomotif Elektronik - D-IV Teknik Otomotif Elektronik | D430: 21545000 | E430: 3 | F430: 3 | G430: LOW | I430: Kegiatan tidak terlaksana sehingga menyebabkan kerugian baik moril maupun materiil. | J430: Karena tidak adanya masukan dari DU/DI tentang kemampuan yang harus dimiliki alumni utk masa mendatang dan aturan pemerintah tentang persentase mata kuliah yang menggunakan metode PBL dan CM, mungkin perangkat kurikulum saat ini masih belum sepenuhnya selaras dengan kebutuhan DU/DI dan belum tercapainya persentase mata kuliah yang menggunakan metode PBL dan CM utk kelas reguler maupun kelas internasional, sehingga proses PBM tidak berjalan maksimal | K430: Karena kurangnya pengetahuan dosen mengenai DU/DI, PBL/CM & MBKM & target kompetensi alumni utk masa mendatang maka diperlukan kegiatan workshop rekonstruksi kurikulum , agar terakomodasi kebijakan MBKM dan Permendikbudristek no 53 Tahun 2023 tentang SN Dikti terbaru guna menghasilkan kompetensi lulusan yang selaras dengan kebutuhan DU/DI.
A431: 642 | B431: D-III Teknik Listrik-1 | C431: INISIASI KERJASAMA DAN KUNJUNGAN DOSEN KE INDUSTRI | D431: 21332000 | E431: 1 | F431: 4 | G431: VERY LOW | I431: Tidak adanya evaluasi proses belajar mengajar sehingga kekurangan dapat terulang di seriap tahun; Proses layanan pembelajaran kurang maksimal | J431: Karena Tidak memiliki database PT yang sesuai untuk dilaksanakan kerjasama mungkin Tidak MoU/SPK dengan PT yang sesuai untuk dilaksanakan kerjasama sehingga Tidak adanya Inisiasi kerjasama dengan PT lain | K431: membuat database PT sehingga dapat memetakan mana yang belum MoU dan yang sudah selain itu membuat perjanjian ditambahkan dengan penelitian dosen dan mahasiswa
A432: 318 | B432: BAK-4 | C432: Penyusunan Dokumen Pemutakhiran Informasi Akademik Baseline Tahun 2025 - BAK | D432: 21245000 | E432: 2 | F432: 4 | G432: LOW | I432: Proses identifikasi data yang diperlukan dapat berjalan mundur; Proses editing sampai penggadaan dapat melebihi waktu jika dibutuhkan oleh prodi utk mendukung proses akreditasi | J432: Karena jumlah tim akademik sebagai penyusun pemutakhiran data sangat terbatas mungkin proses identifikasi data statistik akademik tidak dapat dilakukan cepat sehingga penyusunan dokumen pemutakhiran informasi data akademik baseline 2024 dapat melebihi waktu yang ditentukan | K432: Usulan penambahan tenaga administratif yang cekatan dan memenuhi kebutuhan untuk adaptasi teknologi sehingga penyusunan data statistik akademik lebih mudah
... A496: 192 | B496: D-III Teknik Listrik-8 | C496: Penyempurnaan Dokumen Kurikulum | D496: 15550000 | E496: 4 | F496: 3 | G496: MIDDLE | I496: tidak adanya Prodi yang telah memiliki kurikulum berbasis DUDI yang telah disusun dan diimplementasikan di kampus | J496: Karena tidak ada acuan (SOP) untuk menyusun Kurikulum, Silabus Berbasis DUDI mungkin tidak ada SDM untuk menyusun Kurikulum, Silabus Berbasis DUDI sehingga Tidak tersedianya Kurikulum, Silabus dan penyusunan kurikulum berbasis DUDI | K496: melakukan workshop serta pendampingan pembuatan kurikulum yang sesuai dengan DUDI
A497: 539 | B497: S-2 Teknik Elektro-2 | C497: Implementasi Kerjasama Tri Dharma dengan UTeM - S-2 Teknik Elektro - S-2 Teknik Elektro | D497: 15500000 | E497: 3 | F497: 3 | G497: LOW | I497: menurunnya : (1) Persentase mata kuliah yang menggunakan metode Team-Based Project; (2) Persentase mata kuliah yang menggunakan metode Case Method | J497: karena tidak ada acuan RPS dengan metode pembelajaran CM dan PBL, mungkin tidak ada SDM untuk menyusun RPS, sehingga mengakibatkan tidak tersedianya RPS dengan metode pembelajaran CM dan PBL
A498: 206 | B498: D-IV Bahasa Inggris untuk Industri Pariwisata-2 | C498: KUNJUNGAN INDUSTRI DAN MAHASISWA MAGANG / PKL DI JAWA TIMUR UNTUK PROGRAM STUDI D4 BAHASA INGGRIS UNTUK INDUSTRI PARIWISATA TAHUN 2024 - D-IV Bahasa Inggris untuk Industri Pariwisata | D498: 15190000 | E498: 3 | F498: 5 | G498: MIDDLE | I498: 1. Prodi tidak dapat memperoleh masukan terkait kompetensi mahasiswa selama melaksanakan kegiatan PKL 2. Prodi tidak mempunyai mitra industri untuk tempat magang/PKL mahasiswa | J498: Karena tidak ada database industri atau mitra kerja yang sesuai dengan yang dibutuhkan Prodi D4 Bahasa Inggris untuk Industri Pariwisata yang dapat dikunjungi, tidak ada pemetaan industri atau mitra kerja yang sesuai dengan kebutuhan Prodi D4 Bahasa Inggris Komunikasi Bisnis dan Profesional yang dapat dikunjungi, dan mungkin tidak ada industri atau mitra kerja yang sesuai dengan kebutuhan Prodi D4 Bahasa Inggris untuk Industri Pariwisatayang dapat dikunjungi, sehingga kunjungan Industri tidak terlaksana. | K498: (1) Membuat basis data (database) industri dan mitra kerja yang sesuai dengan profil lulusan prodi (2) Melakukan komunikasi dengan pihak industri (tempat PKL mahasiswa) dengan baik untuk memastikan waktu kunjungan yang paling baik untuk kedua belah pihak.
A499: 584 | B499: UPA Pengembangan Karir dan Kewirausahaan-8 | C499: Pembinaan karir dan konseling mahasiswa - UPA Pengembangan Karir dan Kewirausahaan | D499: 15190000 | E499: 3 | F499: 3 | G499: LOW | I499: 1. mengakibatkan kegiatan ini tidak efektif. 2. terhambat pelaksanaan kegiatan | J499: karena koordinasi dengan jurusan terhambat sehingga menyebabkan pelaksanaan kegiatan konseling tidak berjalan dengan baik | K499: membangun komunikasi yang baik antar unit dan membuat perencanaan dengan jurusan melalui koordinator / administasi jurusan.
A500: 264 | B500: P3M-2 | C500: WORKSHOP PENYUSUNAN METODOLOGI RISET | D500: 15180000 | E500: 4 | F500: 3 | G500: MIDDLE | I500: peserta workshop belum memiliki draft proposal yang dilengkapi dengan metodologi riset untuk didampingi dalam penyusunannya | J500: KARENA draft dokumen yang belum siap dari peserta MUNGKIN kurangnya pemahaman dari peserta mengenai metodologi riset SEHINGGA kegiatan workshop penyusunan metodologi riset tidak dapat berjalan dengan baik | K500: Memberikan sosialisasi pelaksananaan workshop pada dosen dan membuka pendaftaran peserta workshop
A501: 222 | B501: D-IV Sistem Kelistrikan-1 | C501: evaluasi Kelas Internasional - D-IV Sistem Kelistrikan | D501: 15160000 | E501: 3 | F501: 5 | G501: MIDDLE | I501: menurunnya : (1) Persentase mata kuliah yang menggunakan metode Team-Based Project; (2) Persentase mata kuliah yang menggunakan metode Case Method | J501: Karena tidak adanya koordinasi untuk menyusun panduan monitoring pelaksanaan belajar mengajar kelas internasional mungkin karena tidak ada panduan dalam melakukan monitoring proses belajar mengajar pada kelas internasional sehingga tidak terdapatnya monitoring pelaksanaan belajar mengajar. | K501: Membuat tim untuk membentuk SOP, membuat SOP untuk monitoring pembelajaran dengan pengawasan dari kps
A502: 442 | B502: D-IV Teknologi Rekayasa Konstruksi Jalan dan Jembatan-4 | C502: MONEV PBM DAN KURIKULUM - D-IV Teknologi Rekayasa Konstruksi Jalan dan Jembatan | D502: 15155000 | E502: 2 | F502: 4 | G502: LOW | I502: 1. Tidak adanya perbaikan proses PBM 2. Tidak tercapainya IKU | J502: Karena tidak adanya koordinasi untuk menyusun panduan monitoring pelaksanaan belajar mengajar mungkin tidak ada panduan dalam melakukan monitoring proses belajar mengajar sehingga tidak terdapatnya monitoring pelaksanaan belajar mengajar, dari UTS, UAS dan yudisium. | K502: "1. Membuat tim untuk membentuk SOP 2. Membuat SOP 3. Monitoring pembelajaran dengan pengawasan dari KPS D-IV Teknologi Rekayasa Konstruksi Jalan dan Jembatan"
A503: 390 | B503: D-IV Bahasa Inggris untuk KomBis & Profesional-6 | C503: KUNJUNGAN INDUSTRI DAN MAHASISWA MAGANG/PKL OLEH DOSEN TAHUN 2025 - D-IV Bahasa Inggris untuk KomBis & Profesional | D503: 15150000 | E503: 3 | F503: 3 | G503: LOW | I503: - Tidak ada database industri atau mitra kerja yang sesuai dengan kebutuhan Prodi D4 Bahasa Inggris Komunikasi Bisnis dan Profesional yang dapat dikunjungi - Tidak ada pemetaan industri atau mitra kerja yang sesuai dengan kebutuhan Prodi D4 Bahasa Inggris Komunikasi Bisnis dan Profesional yang dapat dikunjungi -Tidak ada industri atau mitra kerja yang sesuai dengan kebutuhan Prodi D4 Bahasa Inggris Komunikasi Bisnis dan Profesional yang dapat dikunjungi -Kunjungan industri tidak terlaksana | J503: Karena tidak ada database industri atau mitra kerja yang sesuai dengan yang dibutuhkan Prodi D4 Bahasa Inggris Komunikasi Bisnis dan Profesional yang dapat dikunjungi, mungkin tidak ada pemetaan industri atau mitra kerja yang sesuai dengan kebutuhan Prodi D4 Bahasa Inggris Komunikasi Bisnis dan Profesional yang dapat dikunjungi, dan tidak ada industri atau mitra kerja yang sesuai dengan kebutuhan Prodi D4 Bahasa Inggris Komunikasi Bisnis dan Profesional yang dapat dikunjungi, sehingga kunjungan Industri tidak terlaksana. | K503: Menyediakan database industri atau mitra kerja yang sesuai dengan yang dibutuhkan Prodi D4 Bahasa Inggris Komunikasi Bisnis dan Profesional yang dapat dikunjungi, membuat pemetaan industri atau mitra kerja yang sesuai dengan kebutuhan Prodi D4 Bahasa Inggris Komunikasi Bisnis dan Profesional yang dapat dikunjungi, dan bekerja sama dengan industri atau mitra kerja yang sesuai dengan kebutuhan Prodi D4 Bahasa Inggris Komunikasi Bisnis dan Profesional untuk melaksanakan Kunjungan Industri untuk Dosen.
A504: 443 | B504: D-IV Teknologi Rekayasa Konstruksi Jalan dan Jembatan-5 | C504: PELATIHAN MENGIKUTI LOMBA NASIONAL - D-IV Teknologi Rekayasa Konstruksi Jalan dan Jembatan | D504: 15150000 | E504: 2 | F504: 4 | G504: LOW | I504: Tidak terlaksananya Pelatihan Lomba akan berdampak : 1. Kurangnya kemampuan mahasiswa untuk berkompetisi, 2. Mahasiswa tidak memiliki kesempatan untuk mengembangkan ketrampilan&kemampuan yang diperlukan untuk berkompetisi, 3. Berkurangnya peluang untuk mendapatkan juara | J504: Karena Tidak ada SDM untuk koordinasi info berkala terkait lomba kepada mahasiswa mungkin minat mahasiswa untuk ikut serta lomba di tingkat nasional/internasional menjadi berkurang sehingga Tidak terdapatnya Peningkatan kualitas mahasiswa melalui keikutsertaan dalam lomba | K504: Memberikan informasi-informasi dan pendampingan ke mahasiswa berkaitan dengan lomba-lomba
A505: 686 | B505: PSDKU Kota Lumajang-28 | C505: Bakti Karya Mahasiswa PSDKU Lumajang - PSDKU Kota Lumajang | D505: 15150000 | E505: 2 | F505: 1 | G505: VERY LOW | I505: Jika Bakti Karya Mahasiswa di lingkungan PSDKU Lumjang tidak dapat dilaksanakan, maka akan kehilangan manfaaf sosial bagi masyarakat, penurunan reputasi, menurunnya keterlibatan mahasiswa, penurunan semangat kolaborasi, dan tertundanya pembelajaran berbasis pengalaman untuk mahasiswa dan tenaga pendidik di PSDKU Lumajang. | J505: Karena keterbatasan sumber daya manusia seperti jumlah mahasiswa dan tenaga pengajar yang terlibat dikegiatan Bakti Karya Mahasiswa, Mungkin fasilitas yang tidak memadai, kendala aksesibilitas lokasi yang dituju untuk kegiatan tersebut, Sehingga Kegiatan Bakti Karya Mahasiswa PSDKU Lumajang tidak dapat dilaksanakan. | K505: Agar Bakti Karya Mahasiswa bisa tetap berjalan, perlu ada solusi seperti mencari alternatif pendanaan, melakukan koordinasi lebih awal dengan pihak terkait, serta memilih lokasi dan waktu yang lebih fleksibel. Melaksanakan Kegiatan Dialog Dosen dan Mahasiswa sesuai dengan jadwal dan rencana
A506: 108 | B506: P2MPP-28 | C506: Workshop Penyusunan Perangkat Ajar Elektronik/Digital (Open Course) | D506: 15080000 | E506: 4 | F506: 4 | G506: HIGH | I506: tidak memiliki perangkat ajar digital untuk keperluan open course yang berkualitas | J506: Karena belum adanya SDM sebagai penyusun perangkat ajar digital, mungkin tidak ada yang bertanggung jawab menyusun perangkat ajar tersebut, sehingga kegiatan penyusunan perangkat bahan ajar digital untuk keperluan open course tidak terlaksana dengan baik | K506: Membentuk tim penyusun perangkat bahan ajar elektronik sesuai dengan kebutuhan
A507: 689 | B507: PSDKU Kota Lumajang-35 | C507: Pengadaan Alat Praktikum Prodi D-III Teknologi Sipil - PSDKU Kota Lumajang - PSDKU Kota Lumajang | D507: 15074000 | E507: 1 | F507: 5 | G507: VERY LOW | I507: Karena Keterbatasan Penguasaan Kompetensi Mahasiswa Ketiadaan alat praktikum akan menyebabkan mahasiswa kesulitan dalam menguasai keterampilan teknis yang dibutuhkan di dunia industri dan konstruksi, mungkin juga akan Kesulitan dalam Implementasi Kurikulum Merdeka Belajar-Kampus Merdeka (MBKM). Program MBKM menekankan pembelajaran berbasis praktik dan proyek nyata. Jika pengadaan alat praktikum tidak terlaksana, maka implementasi program ini akan terhambat, mengurangi kesempatan mahasiswa untuk mendapatkan pengalaman belajar yang optimal serta Motivasi dan Kepuasan Mahasiswa Menurun | J507: Karena Kendala Administrasi dan Regulasi Proses perencanaan dan pengadaan yang tidak sesuai dengan prosedur atau regulasi, Mungkin gagalnya proses pengadaan seperti penawaran yang tidak sesuai dengan standar atau harga yang jauh di atas anggaran, Sehingga Pengadaan Alat Praktikum Prodi D-III Teknologi Sipil tidak dapat dilaksanakan. | K507: Melaksanakan Kegiatan Pengadaan Alat Praktikum Prodi D-III Teknologi Sipil Sesuai Waktu Yang Sudah Ditentukan
A508: 586 | B508: UPA Pengembangan Karir dan Kewirausahaan-11 | C508: Sosialisasi PMW (Program Mahasiswa Wirausaha) Polinema 2025 - UPA Pengembangan Karir dan Kewirausahaan | D508: 15020000 | E508: 3 | F508: 3 | G508: LOW | I508: karena jawal dan pelaksanaan kegiatan tiak sesuai jadwal sehingga dampaknya menyebabkan mundur nya jadwal kegiatan dan beberapa kegiatan lain yang berkaitan juga akan terlambat. | J508: karena penjadwalan tidak tepat sehingga menyebabkan pelaksanaan kegiatan tidak sesuai (terlambat) yang berakibat kegiatan lain juga akan terlambat pelaksanaannya. | K508: 1. membuat jadwal kegiatan dengan baik 2. pelaksanaan kegiatan sesuai jadwal 3. selalu koordinasi
A509: 63 | B509: D-IV Pengelolaan Arsip dan Rekaman Informasi-6 | C509: Penguatan Kerjasama Program Studi dengan Mitra Industri untuk Kegiatan Magang Mandiri MBKM - D-IV Pengelolaan Arsip dan Rekaman Informasi | D509: 15004000 | E509: 4 | F509: 4 | G509: HIGH | I509: Mengganggu kegiatan pembelajaran di semester ganjil dan genap karena tidak adanya mitra industri untuk kegiatan magang mahasiswa | J509: Karena Tidak ada mitra yang siap mungkin karena tidak adanya mitra yang dapat diajak bekerjasama sehingga Penguatan Kerjasama dengan Mitra Industri untuk kegiatan Magang Mandiri Tidak Berjalan | K509: "Membuat database mitra industri Menjalin kerjasama dengan praktisi narasumber"
... A686: 235 | B686: D-IV Teknik Mesin Produksi dan Perawatan PSDKU Kediri-7 | C686: Monitoring dan Evaluasi Proses Belajar Mengajar Semester Genap 2024/2025 | D686: 4740400 | E686: 4 | F686: 3 | G686: MIDDLE | I686: 1. Tidak terlaksananya Monitoring dan Evaluasi Proses Pembelajaran Semester Genap 2024/2025 2. Mahasiswa tidak lulus tepat waktu dan Keberhasilan studi mahasiswa terhambat | J686: Karena tidak adanya SDM yang bertanggungjawab terhadap Monitoring dan Evaluasi Proses Pembelajaran Semester Genap 2024/2025 mungkin Tidak adanya sosialisasi terkait Monitoring dan Evaluasi Proses Pembelajaran SEMESTER GENAP 2024/2025 sehingga Monitoring dan Evaluasi Proses Pembelajaran Semester Genap 2024/2025 tidak berjalan | K686: Menugaskan SDM untuk melakukan sosialisasi dan bertanggungjawab terhadap Monitoring dan Evaluasi Proses Pembelajaran Semester Genap 2024/2025
A687: 10 | B687: D-IV Usaha Perjalanan Wisata-6 | C687: Workshop Ticketing and Reservation System - D-IV Usaha Perjalanan Wisata | D687: 4595000 | E687: 5 | F687: 5 | G687: EXTREME | J687: Karena terbatasnya industri atau institusi yang membuka program pelatihan ticketing dan reservation yang selaras dengan kebutuhan prodi D4 UPW dan mahasiswa tidak menyesuaikan kurikulum , mungkin karena terhambatnya proses penyusunan pedoman kurikulum khususnya ticketing dan reservation sehingga Workshop Ticketing and Reservation System - D-IV Usaha Perjalanan Wisata tidak berjalan dengan sesuai seperti yang diharapkan | K687: Sosialisasi kurikulum MK Ticketing dan Reservation dengan metode PBL sebelum kegiatan kepada seluruh dosen homebase D4 UPW
A688: 423 | B688: D-IV Teknik Elektronika PSDKU Kediri-2 | C688: Kunjungan Industri Untuk Inisiasi Tempat Magang Mahasiswa Dan Tindak Lanjut Kerjasama - D4 Teknik Elektronika Kampus Kediri | D688: 4592000 | E688: 3 | F688: 3 | G688: LOW | I688: 1. MoU dengan industri gagal dibuat 2. Program untuk mahasiswa gagal diinisiasi | J688: KARENA komunikasi antara Prodi dengan tempat kunjungan industri kurang, MUNGKIN tidak tercapainya kesepakatan jadwal antara Prodi dan Industri, SEHINGGA kegiatan Kunjungan Industri Prodi D4 Teknik Elektronika Kampus Kediri tidak bisa dilaksanakan. | K688: 1. Memberikan pelatihan terhadap SDM dalam bernegosiasi 2. Memberikan strategi agar industri menerima penawaran negosiasi
A689: 58 | B689: D-IV Pengelolaan Arsip dan Rekaman Informasi-1 | C689: Penyusunan DKPS Program Studi D4 Pengelolaan Arsip dan Rekaman Informasi - D-IV Pengelolaan Arsip dan Rekaman Informasi | D689: 4298000 | E689: 4 | F689: 4 | G689: HIGH | I689: Mengganggu kegiatan audit mutu internal program studi karena dokumen DKPS tidak tersedia | J689: Karena Tidak ada DKPS yang siap mungkin karena tidak adanya mitra industri/narasumber yang dapat memberikan pendampingan Penyusunan DKPS sehingga Penyusunan DKPS Tidak Berjalan | K689: "Membuat database praktisi narasumber berdasarkan bidang kajian Menjalin kerjasama dengan praktisi narasumber"
A690: 692 | B690: S-2 Sistem Informasi Akuntansi-2 | C690: PROGRAM MAGANG MAHASISWA S-2 Sistem Informasi Akuntansi | D690: 4275000 | E690: 2 | F690: 1 | G690: VERY LOW | I690: Jumlah peserta magang yang ikut dibawah target | J690: Karena kegiatan magang di mitra industri bersifat sukarela dan menyerupai pelatihan yang berbayar, mungkin membuat mahasiswa tidak berminat untuk mengikuti magang tersebut sehingga peserta yang ikut di bawah target | K690: membeikan pemahaman kepada mahasiswa untuk mengikuti magang dengan mitra industri dan memonitoring kegiatan magang berkala
A691: 282 | B691: PSDKU Kota Pamekasan-2 | C691: Promosi dan Sosialisasi Penerimaan Mahasiswa Baru PSDKU Polinema Kabupaten Pamekasan - PSDKU Kota Pamekasan | D691: 4160000 | E691: 3 | F691: 4 | G691: MIDDLE | I691: Menurunnya minat pendaftar mahasiswa kuliah pada perguruan tinggi kita karena minimnya informasi yang diterima | J691: Karena tidak memiliki tim penggerak untuk memulai persiapan kegiatan promosi, mungkin menyebabkan lamanya tim pelaksana merumuskan bentuk promosi yang menyesuaikan dengan jadwal kegiatan siswa kelas XII SMA/SMK, sehingga kurang maksimalnya kegiatan promosi mahasiswa baru di PSDKU Pamekasan | K691: Melaksanakan pembentukan tim penggerak untuk kegiatan promosi penerimaan mahasiswa baru kepada sekolah-sekolah atau mengikuti kegiatan Kampus Expo dalam pengenalan kampus kepada masyarakat
A692: 9 | B692: D-IV Usaha Perjalanan Wisata-4 | C692: Peningkatan Kerjasama Program Studi Melalui Praktikum Mahasiswa Pada Mata Kuliah Akomodasi Perhotelan Dan Dan Restoran Ke Hotel Grand Mercure Malang Mirama - D-IV Usaha Perjalanan Wisata | D692: 4095000 | E692: 5 | F692: 5 | G692: EXTREME | I692: proses kegiatan praktikum tidak maksimal dan peserta tidak mendapatkan ilmu yang bisa digunakan pada dunia kerja | J692: karena tidak ada mahasiswa D4 UPW yang melakukan praktikum mahasiswa pada mata kuliah Akomodasi Perhotelan dan Restoran di industri secara riil mungkin karena tidak adanya praktisi dan pendamping minat kegiatan mahasiswa sehingga praktikum tersebut tidak berjalan | K692: melakukan persiapan secara matang untuk mencari narasumber yang sesuai dengan tema dan memiliki pengalaman menjadi pendamping pada program praktikum atau sejenis
A693: 422 | B693: D-IV Teknik Elektronika PSDKU Kediri-1 | C693: FGD Mitra Strategis Prodi D4 Teknik Elektronika Kampus Kediri Untuk Kerjasama dengan Kampus di Lingkungan Kota Kediri dan Sekitarnya - D-IV Teknik Elektronika PSDKU Kediri | D693: 4073000 | E693: 3 | F693: 3 | G693: LOW | I693: 1. MoU / PKS dengan kampus gagal dibuat 2. Program untuk dosen berkegiatan di luar kampus gagal diinisiasi | J693: KARENA komunikasi antara Prodi dengan perwakilan FGD kurang, MUNGKIN tidak tercapainya kesepakatan jadwal antara Prodi dan Kampus Kerjasama FGD, SEHINGGA kegiatan FGD Prodi D4 Teknik Elektronika Kampus Kediri tidak bisa dilaksanakan. | K693: 1. Memberikan pelatihan terhadap SDM dalam bernegosiasi 2. Memberikan strategi agar kampus kerjasama menerima penawaran negosiasi
A694: 533 | B694: PSDKU Kota Pamekasan-10 | C694: Pembinaaan mahasiswa untuk mengikuti Lomba Akuntansi Tingkat Nasional (SNAV) - PSDKU Kota Pamekasan | D694: 4000000 | E694: 3 | F694: 2 | G694: LOW | I694: tidak bisa mempersiapkan mahasiswa dengan baik karena tergantung dengan kesiapan mahasiswa yang akan mengikuti lomba | J694: Karena kegiatan ini yidak terlaksana mungkin tidak ada mahasiswa yang berminat sehingga memiliki kompetensi di bidang yang dilombakan. | K694: dilakukan sosialisasi awal kepada mahasiswa, lomba apa saja yang bisa diikuti dan menyesuaikan dengan minat dan kompetensi mahasiswa dengan lomba yang akan diikuti.
A695: 681 | B695: PSDKU Kota Lumajang-15 | C695: Pelaksanaan Yudisium Semester Ganjil dan Genap PSDKU Kota Lumajang | D695: 4000000 | E695: 1 | F695: 1 | G695: VERY LOW | I695: Jika yudisium tidak dilaksanakan tanpa alasan yang jelas, bisa menimbulkan ketidakpuasan dari mahasiswa yang sudah menantikan acara ini sebagai bentuk penghargaan atas pencapaian akademik mereka. | J695: Karena belum selesainya proses akademik, Mungkin tertundanya proses validasi data mahasiswa, sehingga Tidak terlaksananya kegiatan Yudisium Semester Ganjil dan Genap PSDKU Lumajang | K695: Melaksanakan kegiatan yudisium sesuai jadwal atau Melaksanakan Yudisium Secara Daring.
A696: 687 | B696: PSDKU Kota Lumajang-29 | C696: Dialog Dosen dengan Mahasiswa PSDKU Kota Lumajang - PSDKU Kota Lumajang | D696: 4000000 | E696: 2 | F696: 2 | G696: VERY LOW | I696: Komunikasi antara Dosen dan Mahasiswa Berkurang, Tanpa forum resmi, mahasiswa mungkin kesulitan menyampaikan aspirasi, pertanyaan akademik, atau permasalahan yang mereka hadapi secara langsung kepada dosen. Dialog ini bisa menjadi salah satu cara untuk meningkatkan keterlibatan mahasiswa dalam lingkungan akademik. Jika tidak ada, interaksi antara dosen dan mahasiswa bisa menjadi lebih formal dan terbatas. | J696: Karena kurangnya minat atau partisipasi mahasiswa dan dosen, mungkin tidak tersedianya tempat fasilitas yang memadai. Sehingga Kegiatan Dialog Dosen dengan Mahasiswa PSDKU Kota Lumajang tidak dapat dilaksanakan. | K696: Memanfaatkan Platform Online, Jika pertemuan langsung sulit dilakukan, kampus bisa menggunakan platform daring seperti Zoom atau Google Meet untuk memfasilitasi diskusi. Meningkatkan Sosialisasi agar Partisipasi Lebih Baik &#8594; Jika minat mahasiswa rendah, maka perlu ada upaya lebih dalam mengedukasi mereka tentang manfaat dan pentingnya dialog ini.
A697: 349 | B697: D-III Akuntansi-5 | C697: PENINGKATAN KERJASAMA PROGRAM STUDI DENGAN INDUSTRI - D-III AKUNTANSI | D697: 3655000 | E697: 2 | F697: 3 | G697: LOW | I697: sasaran industri yang kurang tepat dan kerjasama industri bisa jadi tidak terlaksana | J697: Karena tidak memiliki database industri yang lengkap mungkin tidak ada kerjasama yang bisa dilakukan dengan industri yang tepat, sehingga kegiatan kerjasama industri bisa jadi tidak terlaksana | K697: merencanakan target sasaran industri yang tepat dan di list sesuai dengan kebutuhan prodi
A698: 229 | B698: D-IV Teknik Elektronika PSDKU Kediri-8 | C698: Workshop Implementasi Kurikulum MBKM Prodi D4 Teknik Elektronika Kampus Kediri | D698: 3548000 | E698: 3 | F698: 5 | G698: MIDDLE | I698: 1. Waktu bertambah dalam penyusunan dokumen pendukung kurikulum 2. Implementasi kurikulum MBKM mengalami hambatan | J698: KARENA kurangnya pemahaman dosen dalam menerapkan kurikulum MBKM, MUNGKIN waktu penyusunan dokumen melebihi dari waktu yang direncanakan, SEHINGGA Implementasi Kurikulum MBKM D4 Teknik Elektronika Kampus Kediri tidak bisa dilaksanakan. | K698: 1. Memberikan batas waktu pengerjaan dokumen pendukung kurikulum 2. Menyediakan narasumber yang tepat tentang implementasi kurikulum MBKM
...

Sheet By Level
B1: REKAP IDENTIFIKASI DAN ANALISIS RISIKO SELURUH UNIT TAHUN 2025
A3: NO | B3: Nama Unit & Kode | C3: Usulan Kegiatan | D3: Nilai Usulan | E3: Skor Probabilitas | F3: Skor Dampak | G3: Tingkat Risiko | H3: SPIP | I3: Uraian Dampak | J3: Pernyataan Risiko | K3: Pengendalian
A4: 1 | B4: D-III Teknik Telekomunikasi-1 | C4: FGD dan Inisiasi kerja sama dalam pelaksanaan PKL dan MBKM - D-III Teknik Telekomunikasi | D4: 15790000 | E4: 5 | F4: 5 | G4: EXTREME | I4: Program studi kesulitan untuk mendapatkan mitra dalam upaya meingkatkan keikutsertaan MBKM bagi mahasiswa | J4: Karena kurangnya kepercayaan industri terhadap kompetensi mahasiswa mungkin tidak banyak industri telekomuniikasi yang dapat secara langsung melibatkan mahasiswa melalui MBKM sehingga kurangnya kerjasama prodi dengan mitra untuk menunjang MBKM | K4: Membuat database PT sehingga dapat memetakan mitra/industri yang telah dan belum menyusun dokumen kerjasama dengan Polinema serta menambahkan klausul penelitian dosen dan mahasiswa dalam dokumen kerjasama yang telah/akan dibuat
A5: 2 | B5: D-III Teknik Telekomunikasi-2 | C5: FGD dan Inisiasi Kerjasama dengan Kampus LN - D-III Teknik Telekomunikasi | D5: 8320000 | E5: 5 | F5: 5 | G5: EXTREME | I5: Program studi kesulitan untuk mendapatkan mitra dalam upaya meingkatkan keikutsertaan MBKM bagi mahasiswa | J5: Karena kurangnya kepercayaan industri terhadap kompetensi mahasiswa mungkin tidak banyak industri telekomuniikasi yang dapat secara langsung melibatkan mahasiswa melalui MBKM sehingga kurangnya kerjasama prodi dengan mitra untuk menunjang MBKM | K5: Membuat database PT sehingga dapat memetakan mitra/industri yang telah dan belum menyusun dokumen kerjasama dengan Polinema serta menambahkan klausul penelitian dosen dan mahasiswa dalam dokumen kerjasama yang telah/akan dibuat
A6: 3 | B6: D-IV Jaringan Telekomunikasi Digital-6 | C6: FGD dan Inisiasi Kerjasama dengan Industri dalam Pelaksanaan MBKM - D-IV Jaringan Telekomunikasi Digital - D-IV Jaringan Telekomunikasi Digital | D6: 28817500 | E6: 5 | F6: 5 | G6: EXTREME | I6: Program studi kesulitan untuk mendapatkan mitra dalam upaya meingkatkan keikutsertaan MBKM bagi mahasiswa | J6: Karena kurangnya kepercayaan industri terhadap kompetensi mahasiswa mungkin tidak banyak industri telekomuniikasi yang dapat secara langsung melibatkan mahasiswa melalui MBKM sehingga kurangnya kerjasama prodi dengan mitra untuk menunjang MBKM | K6: Membuat database PT sehingga dapat memetakan mitra/industri yang telah dan belum menyusun dokumen kerjasama dengan Polinema serta menambahkan klausul penelitian dosen dan mahasiswa dalam dokumen kerjasama yang telah/akan dibuat
A7: 4 | B7: D-IV Manajemen Pemasaran-6 | C7: Peningkatan Kerjasama Luar Negeri Prodi D-IV Manajemen Pemasaran | D7: 21845000 | E7: 5 | F7: 5 | G7: EXTREME | I7: 1. Tidak mempunyai kerjasama dengan mitra luar negeri; 2. Peningkatan daya saing global tidak terwujud. | J7: Karena terbatasnya jejaring luar negeri dalam mendukung pembelajaran dan pengembangan internasional, mungkin kurangnya pendekatan kepada mitra luar negeri, sehingga Peningkatan kerjasama luar negeri Prodi D-IV Manajemen Pemasaran tidak berjalan | K7: 1. Melakukan inisiasi kerjasama dengan PT luar negeri. 2. Melakukan perencanaan kegiatan yang mendukung kegiatan kerjasama luar negeri.
A8: 5 | B8: D-IV Manajemen Pemasaran-9 | C8: Rekonstruksi dan Ujicoba Kurikulum Prodi D-IV Manajemen Pemasaran | D8: 13821000 | E8: 5 | F8: 5 | G8: EXTREME | I8: 1.Tidak terlaksananya kegiatan rekonstruksi dan uji coba kurikulum Prodi D-IV Manajemen Pemasaran dengan baik; 2. Tidak adanya kurikulum yang selaras dengan dunia usaha dunia industri. | J8: Karena tidak memiiliki pedoman rekonstruksi dan ujicoba kurikulum yang update sesuai dunia industri, mungkin Terbatasnya data dan informasi rekonstruksi dan ujicoba kurikulum Prodi D-IV Manajemen Pemasaran, sehingga Rekonstruksi dan ujicoba kurikulum Prodi D-IV Manajemen Pemasaran tidak berjalan | K8: Melaksanakan monitoring tepat waktu. Memberikan sosialisasi lebih awal tentang hasil kurikulum. Menyusun kurikulum tepat waktu. Menyusun pedoman kurikulum program studi. Melakukan ujicoba kurikulum.
A9: 6 | B9: D-IV Manajemen Pemasaran-10 | C9: Pembelajaran PBL Semester Ganjil (Pelatihan Table Manner, Praktek E-Commerce & Marketing Event Project) - D-IV Manajemen Pemasaran | D9: 40887000 | E9: 5 | F9: 5 | G9: EXTREME | I9: 1. Pembelajaran PBL Semester Ganjil tidak berjalan sesuai dengan perencanaan; 2. Capaian pembelajaran yang diharapkan tidak dapat terpenuhi. | J9: Karena kurangnya koordinasi antar dosen dalam pelaksanaan pembelajaran semester ganjil, mungkin pelaksanaan pembelajaran PBL tidak sesuai dengan jadwal yang ditetapkan, sehingga Pembelajaran PBL semester Ganjil (pelatihan Table Manner, Praktek E-Commerce & Marketing Event Project) tidak berjalan | K9: Melakukan koordinasi antar dosen dalam pelaksanaan pembelajaran semester ganjil. Memastikan RPS mata kuliah telah tersusun awal perkuliahan. Menjalankan program pembelajaran sesuai dengan yang direncanakan.
A10: 7 | B10: D-IV Manajemen Pemasaran-11 | C10: Pembelajaran PBL Semester Genap (Digital Marketing Project, Pameran Produk Kewirausahaan, dan Riset Pemasaran) - D-IV Manajemen Pemasaran | D10: 44084580 | E10: 5 | F10: 5 | G10: EXTREME | I10: 1. Pembelajaran PBL Semester Genap tidak berjalan sesuai dengan perencanaan; 2. Capaian pembelajaran yang diharapkan tidak dapat terpenuhi. | J10: Karena kurangnya koordinasi antar dosen dalam pelaksanaan pembelajaran semester genap, mungkin pelaksanaan pembelajaran PBL tidak sesuai dengan jadwal yang ditetapkan, sehingga Pembelajaran PBL semester genap (Digital Marketing Project, Pameran Produk Kewirausahaan, dan Riset Pemasaran) - D-IV Manajemen Pemasaran tidak berjalan | K10: Melakukan koordinasi antar dosen dalam pelaksanaan pembelajaran semester genap. Memastikan RPS mata kuliah telah tersusun awal perkuliahan. Menjalankan program pembelajaran sesuai dengan yang direncanakan.
A11: 8 | B11: D-IV Usaha Perjalanan Wisata-3 | C11: Penguatan Kerjasama Prodi dengan Mitra Industri Pariwisata Bandung - D-IV Usaha Perjalanan Wisata | D11: 12760000 | E11: 5 | F11: 5 | G11: EXTREME | I11: Kurangnya informasi terkait industri sasaran kerjasama dan mundurnya jadwal kegiatan kunjungan industri, proses monitoring kurang maksimal | J11: Karena tidak memiliki data base industri sasaran dan industri tempat magang, mungkin industri sasaran yang sesuai untuk pengembangan kerjasama tidak ada dan industri tempat monitoring pelaksanaan magang tidak siap sehingga kunjungan industri pariwisata untuk pengembangan kerjasama dan monitoring pelaksanaan magang tidak berjalan | K11: Membuat database industri sasaran pengembangan kerjasama dan industri tempat magang
A12: 9 | B12: D-IV Usaha Perjalanan Wisata-4 | C12: Peningkatan Kerjasama Program Studi Melalui Praktikum Mahasiswa Pada Mata Kuliah Akomodasi Perhotelan Dan Dan Restoran Ke Hotel Grand Mercure Malang Mirama - D-IV Usaha Perjalanan Wisata | D12: 4095000 | E12: 5 | F12: 5 | G12: EXTREME | I12: proses kegiatan praktikum tidak maksimal dan peserta tidak mendapatkan ilmu yang bisa digunakan pada dunia kerja | J12: karena tidak ada mahasiswa D4 UPW yang melakukan praktikum mahasiswa pada mata kuliah Akomodasi Perhotelan dan Restoran di industri secara riil mungkin karena tidak adanya praktisi dan pendamping minat kegiatan mahasiswa sehingga praktikum tersebut tidak berjalan | K12: melakukan persiapan secara matang untuk mencari narasumber yang sesuai dengan tema dan memiliki pengalaman menjadi pendamping pada program praktikum atau sejenis
A13: 10 | B13: D-IV Usaha Perjalanan Wisata-6 | C13: Workshop Ticketing and Reservation System - D-IV Usaha Perjalanan Wisata | D13: 4595000 | E13: 5 | F13: 5 | G13: EXTREME | J13: Karena terbatasnya industri atau institusi yang membuka program pelatihan ticketing dan reservation yang selaras dengan kebutuhan prodi D4 UPW dan mahasiswa tidak menyesuaikan kurikulum , mungkin karena terhambatnya proses penyusunan pedoman kurikulum khususnya ticketing dan reservation sehingga Workshop Ticketing and Reservation System - D-IV Usaha Perjalanan Wisata tidak berjalan dengan sesuai seperti yang diharapkan | K13: Sosialisasi kurikulum MK Ticketing dan Reservation dengan metode PBL sebelum kegiatan kepada seluruh dosen homebase D4 UPW
A14: 11 | B14: D-IV Usaha Perjalanan Wisata-7 | C14: Forum Group Discussion Tentang Penyusunan Kurikulum Berbasis OBE dengan Industri - D-IV Usaha Perjalanan Wisata | D14: 6455000 | E14: 5 | F14: 5 | G14: EXTREME | I14: Lamanya waktu yang diperlukan untuk telaah dan persiapan draft bahan ajar berbasis OBE | J14: Karena terbatasnya industri yang membuka program MBKM yang selaras dengan Prodi D4 UPW dan mahasiswa tidak menyesuaikan kurikulum dalam mengajukan MBKM mungkin karena terhambatnya proses penyusunan pedoman kurikulum berbasis OBE dengan industri di kantor pusat sehingga FGD tentang Penyusunan Kurikulum Berbasis OBE dengan Industri D-IV Usaha Perjalanan Wisata tidak berjalan sesuai yg seperti diharapkan | K14: Sosialisasi pedoman pembelajaran berbasis OBE sebelum kegiatan kepada seluruh dosen homebase D$ UPW
A15: 12 | B15: Jurusan Teknik Elektro-3 | C15: Inisiasi Kerjasama Dengan Mitra Potensial Dalam Bentuk Focus Group Discussion di Jurusan Teknik Elektro | D15: 17500000 | E15: 5 | F15: 5 | G15: EXTREME | I15: Jurusan Teknik Elektro tidak memiliki mitra untuk dapat meningkatkan kerjasama industri | J15: Karena kurangnya kepercayaan industri terhadap kompetensi Jurusan Teknik Elektro mungkin tidak banyak industri telekomuniikasi yang dapat secara langsung menjalin kerjasama melalui sehingga kurangnya kerjasama prodi dengan mitra untuk menunjang MBKM | K15: Membuat database PT sehingga dapat memetakan mana yang belum MoU dan yang sudah selain itu membuat perjanjian ditambahkan dengan penelitian dosen dan mahasiswa
A16: 13 | B16: P3M-15 | C16: PENELITIAN DIPA KOMPETISI 2025 - P3M | D16: 5440155000 | E16: 5 | F16: 5 | G16: EXTREME | I16: Menggangu ketercapaian kinerja dosen dan IKU Polinema | J16: KARENA terlambat dalam menentukan skema penelitian MUNGKIN sosialisasi perubahan aturan terlambat disampaikan kepada peneliti SEHINGGA Penelitian DIPA KOMPTESI 2025 P3M tidak dapat dilaksanakan | K16: Perlu dilakukan penyusunan panduan dan skema penelitian sebagai petunjuk teknis pelaksanaan. Perlu dilakukan sosialisasi panduan dan penentuan penjadwalan seleksi hingga pelaporan pelaksanaan kepada seluruh civitas akademika Polinema. Perlu dilakukannya monitoring dan koordinasi pelaksanaan kegiatan sehingga luaran penelitian dapat tercapai
A17: 14 | B17: UPA Pengembangan Karir dan Kewirausahaan-4 | C17: INKUBASI WIRAUSAHA MAHASISWA 2025 - UPA Pengembangan Karir dan Kewirausahaan | D17: 77080000 | E17: 5 | F17: 5 | G17: EXTREME | I17: terjadi kemunduran pelaksanaan kegiatan penampingan usaha dari tenant inkubasi. | J17: karena adanya keterlambatan pencairan bantuan modal usaha dan tidak tepat waktu, sehingga menyebabkan kendala di keseluruhan proses pendampingan terutama mundurnya jadwal pelaksanaan kegiatan. | K17: membuat jadwal pelaksanaanan kegiatan, dan kepatuhan terhadap jadwal yang di buat. pencairan modal usaha tepat waktu sehingga membantu proses kelancaran pendampingan dan kegiatan produksi mahasiswa wirausaha.
A18: 15 | B18: UPA Pengembangan Karir dan Kewirausahaan-10 | C18: Program Mahasiswa Wirausaha (PMW) Polinema 2025 - UPA Pengembangan Karir dan Kewirausahaan | D18: 302568000 | E18: 5 | F18: 5 | G18: EXTREME | I18: Karena KETERLAMBATAN DAN SULITNYA PROSES PENCAIRAN BANTUAN MODAL USAHA , sehingga menyebabkan resiko sangat terlambat dalam proses pendampingan dan produksi, yang mengakibatkan mundurnya jadwal kegiatan lainnya sebagai rangkaian kegiatan PMW. ada beberapa kegiatan lain yang pelaksanaan nya hanya bisa dilakukan setelah tenant PMW berjalan proses produksinya, sehingga jika pencairan modal usaha ini terlambata akan menghambat pelaksanaan kegiatan lainnya. perlu di pahami bahwa wirausaha adalah menjalankan usaha yang membutuhkan modal untuk proses produksinya. periode waktu usaha yang seharusnya 1 tahun juga sangat terbatas, karena efektif operasional usahanya hanya 6 bulan (jika pencairan bantuan modal di bulan mei 2025). hal ini sebenar nya kurang efektif untuk progres sebuah usaha. oleh karena itu kami berharap bantuan untuk ketepatan jawal pelaksanaan program. | J18: Karena KETERLAMBATAN DAN SULITNYA PROSES PENCAIRAN BANTUAN MODAL USAHA , sehingga menyebabkan resiko sangat terlambat dalam proses pendampingan dan produksi, yang mengakibatkan mundurnya jadwal kegiatan lainnya sebagai rangkaian kegiatan PMW. | K18: 1. penjadwalan dan pelaksanaan kegiatan sesuai dengan time line yang sudah di tetapkan. 2. koordinasi dengan bagian keuangan dan tim kerja terkait ketepatan waktu pencairan bantuan modal usaha mahasiswa. 3. komunikasi yang baik agar pelaksanaan kegiatan bisa dilakukan dengan baik, efektif, tepat waktu , dan memberikan manfaat bagi mahasiswa wirausaha.
A19: 16 | B19: WADIR II-10 | C19: PEMBANGUNAN GEDUNG DAN BANGUNAN PENDUKUNG PEMBELAJARAN - BLU | D19: 40556300000 | E19: 5 | F19: 5 | G19: EXTREME | I19: Melakukan persiapan data dukung tender secara lengkap dan lebih awal, dan pendampingan proses oleh BPKP Jawa Timur dan Kejaksaan Tinggi Negeri | J19: Karena Data dukung penting untuk pengadaan tidak segera tersedia mungkin Kelengkapan berkas pengadaan terlambat sehingga Pembangunan Gedung dan Bangunan Pendukung Pembelajaran tidak selesai. | K19: Adanya pendampingan dari pihak BPKP Jawa Timur dan Kejaksaan Tinggi Negeri agar pembangunan gedung dan bangunan pendukung pembelajaran dapat selesai tepat waktu.
A20: 17 | B20: WADIR II-25 | C20: PEMBANGUNAN GEDUNG DAN BANGUNAN PENDUKUNG PEMBELAJARAN SBSN - RM - WADIR II | D20: 87468000000 | E20: 5 | F20: 5 | G20: EXTREME | I20: Melakukan persiapan data dukung tender secara lengkap dan lebih awal, dan pendampingan proses oleh BPKP Jawa Timur dan Kejaksaan Tinggi Negeri | J20: Karena Data dukung penting untuk pengadaan tidak segera tersedia mungkin Kelengkapan berkas pengadaan terlambat sehingga Pembangunan Gedung dan Bangunan Pendukung Pembelajaran tidak selesai. | K20: Adanya pendampingan dari pihak BPKP Jawa Timur dan Kejakaan Tinggi Negeri agar pembangunan gedung dan bangunan pendukung pembelajar dapat selesai tepat waktu.
A21: 18 | B21: BPKU-3 | C21: Pembinaan Dan Peningkatan Kualitas Pegawai Dalam Bidang Wawasan Kebangsaan | D21: 204269000 | E21: 4 | F21: 4 | G21: HIGH | I21: Tidak terlaksananya upacara dalam rangka peringatan Dies Natalis dan hari besar nasional | J21: Karena kurangnya koordinasi internai Pokja Protokoler dengan jajaran Pimpinan, mungkin tidak terdapat informasi terkait Pembinaan dan Peningkatan Kualitas Pegawai dalam Bidang Wawasan Kebangsaan sehingga Pembinaan dan Peningkatan Kualitas Pegawai dalam Bidang Wawasan Kebangsaan tidak berjalan | K21: Melaksanakan koordinasi dengan jajaran Pimpinan terkait upacara peringatan Dies Natalis dan hari besar nasional serta mencari informasi terkait pedoman pelaksanaan upacara dengan protokol kementerian.
A22: 19 | B22: BPKU-6 | C22: Pameran untuk keikutsertaan Promosi | D22: 122758000 | E22: 4 | F22: 4 | G22: HIGH | I22: Tidak dapat mengikuti pameran pendidikan yang mengakibatkan Menurunnya kuantitas pendaftarSPMB | J22: Karena masih dalam penyusunan anggaran indikatif mungkin kegiatan pameran dilaksanakan di awal tahun ketika belum ada anggaran dan Anggaran belum ditetapkan sehingga Pameran Pendidikan di Wilayah Jawa Timur mengalami kesulitan | K22: Melakukan koordinasi dengan pimpinan terkait mekanisme penggunaan anggaran di awal tahun sebelum anggaran tahun berjalan ditetapkan Melakukan sosialisasi PMB melalui media sosial resmi POLINEMA, website, dan jaringan alumni sekolah
A23: 20 | B23: D-III Teknik Listrik-2 | C23: Kolaborasi Riset Mahasiswa dan Dosen serta pembinaan mahasiswa berprestasi - D-III Teknik Listrik | D23: 47600000 | E23: 4 | F23: 5 | G23: HIGH | I23: menurunya persentase mahasiswa yang merahih prestasi | J23: Karena Tidak ada SDM untuk koordinasi info berkala terkait lomba kepada mahasiswa mungkin minat mahasiswa untuk ikut serta lomba di tingkat nasional menjadi berkurang sehingga Tidak terdapatnya Peningkatan kualitas mahasiswa melalui keikutsertaan dalam lomba | K23: Memberikan informasi-informasi dan pemndampingan ke mahasiswa berkaitan dengan lomba-lomba
A24: 21 | B24: D-III Teknik Listrik-9 | C24: Pesiapan Proses Audit Mutu Internal (AMI) - D-III Teknik Listrik | D24: 17240000 | E24: 4 | F24: 5 | G24: HIGH | I24: menurunnya jumlah: (1) Jumlah mahasiswa yang terlibat dalam kegiatan penelitian; (2) Jumlah mahasiswa yang terlibat dalam kegiatan PkM; (3) Jumlah prodi terakreditasi Unggul / A. | J24: Karena Tidak adanya database untuk mendukung penyusunan Dokumen yang dibutuhkan untuk Audit Mutu Internal (AMI) mungkin tidak ada SDM untuk menyusun dokumen sehingga tidak tersedianya dokumen kelengkapan audit | K24: Dengan meunjuk tim khusus untuk melakukan pengumpulan data dukung secara terorganisir dan termonitor sehingga memudahkan penyusunan dokumen AMI serta memberikan workshop dan pendampingan dalam AMI
A25: 22 | B25: D-III Teknik Elektronika-1 | C25: Pelaksanaan Monitoring Evaluasi Pembelajaran Semester Ganjil - D-III Teknik Elektronika | D25: 11312000 | E25: 4 | F25: 5 | G25: HIGH | I25: Tidak adanya evaluasi proses belajar mengajar sehingga kekurangan dapat terulang di seriap tahun; Proses layanan pembelajaran kurang maksimal | J25: Karena tidak adanya koordinasi untuk menyusun panduan monitoring pelaksanaan belajar mengajar mungkin tidak ada panduan dalam melakukan monitoring proses belajar mengajar sehingga tidak terdapatnya monitoring pelaksanaan belajar mengajar, dari UTS, UAS dan yudisium. | K25: Membuat tim untuk membentuk SOP, membuat SOP untuk monitoring pembelajaran dengan pengawasan dari kps
... A184: 181 | B184: BAK-6 | C184: Workshop Tata Kelola Operasional dan Maintenance Aplikasi Help Akademik - BAK | D184: 12111000 | E184: 3 | F184: 5 | G184: MIDDLE | I184: Terbengkalainya layanan kepada mahasiswa melalui aplikasi help akademik; Memperlambat layanan kepada mahasiswa dengan offline | J184: Karena pelayanan akademik dilakukan offline mengingat aplikasi yang dioperasikan mungkin belum mendapat kepastian untuk dapat dilaksanakan sesuai kebijakan SI terbaru sehingga operasional dan maintenance aplikasi help akademik belum dapat dilanjutkan | K184: Kebijakan sistem informasi institusi diharapkan dapat mengakomodir sistem lain yang sudah berjalan dengan baik untuk efektivitas pelayanan kepada mahasiswa
A185: 182 | B185: BPKU-4 | C185: Digitalisasi Arsip Surat Keputusan dan Peraturan DIrektur | D185: 40000000 | E185: 3 | F185: 4 | G185: MIDDLE
A186: 183 | B186: BPKU-7 | C186: Pelatihan Keselamatan, Kesehatan Kerja & Lingkungan (K3L) Politeknik Negeri Malang | D186: 35000000 | E186: 3 | F186: 4 | G186: MIDDLE | I186: Risiko kecelakaan kerja dapat terjadi apabila para pegawai yang bertanggungjawab di bidang K3L tidak memahami prinsip-prinsip dan tata cara pelaksanaan Keselamatan, Kesehatan Kerja dan Lingkungan. | J186: Risiko kecelakaan kerja dapat terjadi apabila para pegawai yang bertanggungjawab di bidang K3L tidak memahami prinsip-prinsip dan tata cara pelaksanaan Keselamatan, Kesehatan Kerja dan Lingkungan. | K186: Melaksanakan pelatihan K3L dan melengkapi sarana prasarana penunjang K3L
A187: 184 | B187: BPKU-16 | C187: PERENCANAAN DAN MONEV: Rapat Kerja Program dan Anggaran Definitif 2025 - BPKU | D187: 141185000 | E187: 3 | F187: 5 | G187: MIDDLE | I187: Rapat Kerja Penyusunan Program dan Anggaran Indikatif tahun 2025 POLINEMA yang tidak berjalan dengan baik dapat berpengaruh terhadap ketepatan waktu penetapan pagu definitif institusi | J187: Rapat Kerja Penyusunan Program dan Anggaran Indikatif tahun 2025 Polinema merupakan kegiatan rutin untuk memastikan kualitas perencanaan dan penganggaran di Polinema tersusun dengan baik. Tidak terlaksananya Rapat Kerja Penyusunan Program dan Anggaran Indikatif tahun 2025 Polinema dapat mempengaruhi kualitas perencanaan program dan anggaran tahun 2025 serta menghambat ketercapaian indikator Kinerja Utama dan target kinerja institusi. | K187: 1) Meningkatkan kapasitas SDM; 2.) Menyusun perencanaan yang sesuai dengan prosedur dan kaidah keuangan negara; 3.) Penetapan pagu definitif tepat waktu sebagai acuan pelaksanaan program dan kegiatan
A188: 185 | B188: BPKU-20 | C188: Evaluasi Capaian Kinerja Program dan Anggaran Tahun Anggaran 2025 | D188: 86338000 | E188: 3 | F188: 5 | G188: MIDDLE | I188: Pelaksanaan kegiatan EPA tdk berjalan secara optimal | J188: Karena pelaksanaan kegiatan ini membutuhkan narasumber yang dari Kementerian mungkin akan terkendala pada jadwal narasumber yang kompeten dibiudang monev anggaran sehingga kegiatan EPA tdk berjalan dengan baik | K188: pelaksanaan kegiatan ini membutuhkan narasumber yang dari Kementerian Keuangan perlu adanya koordinasi yang baik agar pelaksanaan EPA dapat berjalan dengan baik
A189: 186 | B189: BPKU-24 | C189: Penyusunan Dokumen Pola Karir Pegawai Politeknik Negeri Malang untuk ASN Dosen dan Tenaga Kependidikan | D189: 11780000 | E189: 3 | F189: 4 | G189: MIDDLE | I189: Jika Kegiatan Pola karir tidak terlaksana maka Dokumen Pola Karir tidak dapet terselesaikan, dan jika tidak ada dokumen Pola Karir maka penataan dan jenjang karir pegawai tidak memiliki pedoman | J189: Apabila dokumen pola karier tidak tersusun pada tahun 2025 maka urutan penempatan dan/atau perpindahan PNS dalam dan antar posisi di setiap jenis Jabatan di lingkungan Polinema akan terkendala dan tidak memiliki dasar acuan yang tepat. | K189: Melaksanakan koordinasi dan timeline penyusunan dokumen pola karier agar dokumen pol karier dapat terselesaikan tepat waktu pada tahun 2025
A190: 187 | B190: BPKU-25 | C190: Penyusunan Dokumen Peta Jalan Pengembangan Kompetensi Pegawai Tenaga Kependidikan yang disesuaikan dengan Renstra Polinema | D190: 12500000 | E190: 3 | F190: 4 | G190: MIDDLE | I190: Kegiatan penyusunan Dokumen Peta Jalan tidak terlaksana, sehingga dapat menyebabkan penataan pegawai dan jenjang karir pegawai tidak memiliki pedoman | J190: Apabila kegiatan penyusunan Peta Jalan Pengembangan Kompetensi Pegawai Tenaga Kependidikan tidak terlksana, maka Polinema tidak memiliki dokumen Peta Jalan Pengembangan Kompetensi Pegawai Tenaga Kependidikan sebagai pedoman penataan jenjang karir pegawai. | K190: Melaksanakan koordinasi dan penyusunan timeline agar target penyusunan dokumen Peta Jalan Pengembangan Kompetensi Pegawai Tenaga Kependidikan dapat tercapai sesuai rencana
A191: 188 | B191: BPKU-28 | C191: Workshop Peningkatan Pengelolaan Kearsipan | D191: 9300000 | E191: 4 | F191: 3 | G191: MIDDLE | I191: Dengan pelaksanaan workshop pengelolaan kearsipan di harapkan layanan surat menyurat di masing-masing jurusan, unit dan bagian dapat lebih berjalan dengan baik | J191: Karena kurangnya data nara sumber yang memiliki kompetensi sesuai dengan yang dibutuhkan mungkin Workshop pengelolaan kearsipan belum dapat dapat dilaksanakan dengan baik sehingga pengelolaan kearsipan belum dapat di laksanakan secara opti mal | K191: Diperlukan layanan yang baik dalam surat menyurat dan pengarsipan
A192: 189 | B192: BPKU-29 | C192: Workshop Sinkronisasi Data di SIMPEG, SINTA, SINERJA dan SIDAKIN Politeknik Negeri Malang | D192: 8980000 | E192: 4 | F192: 3 | G192: MIDDLE | I192: Dapat mengakibatkan tidak tercapainya kinerja Direktur yang telah di targetkan dalam masing-masing IKU sehingga tidak diterimanya reward anggaran kinerja | J192: Ketidaksesuaian data pada aplikasi SIMPEG, SINTA dan SISTER akan terintegrasi pada penilaian kinerja di aplikasi SIDAKIN yang dilaksanakan pada akhir tahun. Data pada aplikasi SIDAKIN yang tidak valid mengakibatkan tidak tercapainya kinerja Direktur yang telah di targetkan dalam masing-masing IKU | K192: pengisian dan update data secara rutin pada apliaksi SIMPEG dan SISTER sehingga data valid
A193: 190 | B193: BPKU-30 | C193: Pelatihan Peningkatan Layanan Prima Bagi Tenaga Kependidikan dalam upaya meningkatkan motivasi dan kualitas layanan di Jajaran BPKU Polinema - BPKU | D193: 91456000 | E193: 3 | F193: 5 | G193: MIDDLE | I193: Tidak terlaksananya kegiatan pemberian motivasi untuk peningkatan kualitas layanan berdapak pada kurangnya motivali layanan prima yang berdampak pada kurang berkualitasnya layanan serta layanan tidak dapat dipercaya. | J193: Karena kurangnya data nara sumber yang memiliki kompetensi sesuai dengan yang dibutuhkan mungkin pelatihan peningkatan layanan prima bagi tenaga kependidikan tidak dapat dilaksanakan dengan baik sehingga layanan tidak dapat dipercaya dan kurang berkualitas. | K193: Diperlukan adanya motivasi dan kualitas layanan terbaik dalam menjalankan tugas di jajaran BPKU
A194: 191 | B194: D-II Perangkat Piranti Lunak Situs-2 | C194: Sinkronisasi Dokumen Kurikulum dengan Capaian - D-II Perangkat Piranti Lunak Situs - D-II Perangkat Piranti Lunak Situs | D194: 8839000 | E194: 4 | F194: 3 | G194: MIDDLE | I194: 1. Data yang diperoleh kurang sesuai 2. Terhambatnya kegiatan penyusunan LKPS dan persiapan Akreditasi | J194: Karena adanya kekurangan data/sumber data yang dikumpulkan, mungkin data yang disampaikan kurang akurat/up to date, sehingga penyusunan LKPS dan persiapan Akreditasi D2 PLS menjadi terhambat. | K194: 1. Memastikan bahwa petugas/tim yang menangani penyusunan LKPS dan persiapan Akreditasi D4 dapat mengumpulkan data sejak awal secara bertahap dan sistematis 2. Memastikan data yang dikumpulkan sudah data terbaru/up to date
A195: 192 | B195: D-III Teknik Listrik-8 | C195: Penyempurnaan Dokumen Kurikulum | D195: 15550000 | E195: 4 | F195: 3 | G195: MIDDLE | I195: tidak adanya Prodi yang telah memiliki kurikulum berbasis DUDI yang telah disusun dan diimplementasikan di kampus | J195: Karena tidak ada acuan (SOP) untuk menyusun Kurikulum, Silabus Berbasis DUDI mungkin tidak ada SDM untuk menyusun Kurikulum, Silabus Berbasis DUDI sehingga Tidak tersedianya Kurikulum, Silabus dan penyusunan kurikulum berbasis DUDI | K195: melakukan workshop serta pendampingan pembuatan kurikulum yang sesuai dengan DUDI
A196: 193 | B196: D-III Teknik Mesin-3 | C196: Monitoring dan Supervisi Pelaksanaan Magang Industri Mahasiswa Program Studi D3 Teknik Mesin | D196: 29851000 | E196: 3 | F196: 5 | G196: MIDDLE | I196: Masukan terhadap perbaikan kurikulum serta rencana pelaksanaan magang/PKL mahasiswa dengan berlakunya kurikulum 4+1+1 (1 smstr PKL di industri) tidak maksimal tersampaikan. | J196: Karena kurangnya komunikasi dan perencanaan jadwal kunjungan yang sesuai mungkin tidak banyak perusahaan yang menerima mahasiswa PKL dapat dikunjungi untuk kegiatan monev sehingga masukan terkait pelaksanaan PKL dan masukan terhadap perbaikan kurikulum belum dapat memperoleh feedback. | K196: Perlu ditingkatkan komunikasi dan perencanaan yang matang terkait rencana monev, supervisi dan kunjungan ke industri tempat mahasiswa PKL sehingga target kegiatan dapat tercapai
A197: 194 | B197: D-III Teknik Telekomunikasi-7 | C197: Pengadaan Alat Pendidikan Penunjang Pembelajaran - D-III Teknik Telekomunikasi | D197: 99073750 | E197: 3 | F197: 5 | G197: MIDDLE | I197: Menurunnya jumlah alat/fasilitas/sarpra yang telah dipelihara dan berfungsi dengan baik | J197: Karena tidak adanya SDM yang dapat mencari alat praktikum dengan kandungan TKDN serta menyusun HPS ditingkat prodi mungkin lamanya waktu yang diperlukan untuk mencari alat praktikum dengan TKDN serta penyusunan HPS sehingga tidak tersedia alat praktikum yang memadai | K197: Menyertakan tim teknis perumus HPS dalam penyusunan HPS untuk memenuhi TKDN mengikuti database yang ada dan minimum 40% dan monitoring proses pengadaan
... A541: 538 | B541: S-2 Sistem Informasi Akuntansi-4 | C541: PENINGKATAN KERJASAMA PROGRAM STUDI MELALUI FGD DENGAN INDUSTRI PRODI S-2 SISTEM INFORMASI AKUNTANSI | D541: 7755000 | E541: 3 | F541: 3 | G541: LOW | I541: tidak memiliki database industri yang akan dikunjungi Kegiatan tidak berjalan sesuai waktu yang telah direncanakan di awal (di simkeu) | J541: Karena objek kunjungan merupakan mitra industri, waktu perlu menyesuaikan dengan kesibukan mitra industri, dan tidak memiliki database industri yang akan dikunjungi mungkin Industri Sasaran yang sesuai untuk Pengembangan Kerjasama belum siap untuk dikunjungi sehingga kegiatan tidak berjalan sesuai skedul yang direncanakan (di simkeu) | K541: menentukan tujuan industri dan menghubungi pihak industri terkait dengan pelaksanaan kegiatan kunjungan industri
A542: 539 | B542: S-2 Teknik Elektro-2 | C542: Implementasi Kerjasama Tri Dharma dengan UTeM - S-2 Teknik Elektro - S-2 Teknik Elektro | D542: 15500000 | E542: 3 | F542: 3 | G542: LOW | I542: menurunnya : (1) Persentase mata kuliah yang menggunakan metode Team-Based Project; (2) Persentase mata kuliah yang menggunakan metode Case Method | J542: karena tidak ada acuan RPS dengan metode pembelajaran CM dan PBL, mungkin tidak ada SDM untuk menyusun RPS, sehingga mengakibatkan tidak tersedianya RPS dengan metode pembelajaran CM dan PBL
A543: 540 | B543: S-2 Teknik Elektro-3 | C543: Workshop Rekonstruksi Kurikulum dan Pembuatan SOP - S-2 Teknik Elektro | D543: 22000000 | E543: 2 | F543: 3 | G543: LOW | I543: tidak adanya Prodi yang telah memiliki kurikulum berbasis DUDI yang telah disusun dan diimplementasikan di kampus | J543: Karena tidak ada acuan (SOP) untuk menyusun Kurikulum, Silabus Berbasis DUDI mungkin tidak ada SDM untuk menyusun Kurikulum, Silabus Berbasis DUDI sehingga Tidak tersedianya Kurikulum, Silabus dan penyusunan kurikulum berbasis DUDI | K543: melakukan workshop serta pendampingan pembuatan kurikulum yang sesuai dengan DUDI
